Workbook
Name AUTH_SIGNATORY: DropdownData!$B$2:$B$17
Name CPV_DETAIL: DropdownData!$C$2:$C$105
Name CUSTOMER_BANK: DropdownData!$D$2:$D$13
Name GURANTOR: DropdownData!$E$2:$E$34
Name LegacyFiles: DropdownData!$A$2:$A$11
Name RC_CUSTOMER_ACCOUNT: DropdownData!$F$2:$F$161
Name RC_DOC_DESPATCH_MASTER: DropdownData!$G$2:$G$10
Name RC_INSTRUMENT_DETAIL: DropdownData!$H$2:$H$21
Name RC_RC_INV_RECEIVING_DETAIL: DropdownData!$I$2:$I$23
Name RC_RC_INV_STATUS: DropdownData!$J$2:$J$28
Name RC_SOURCE_REFERENCE: DropdownData!$K$2:$K$6

Sheet MappingEditor
A1: new_field | B1: new_page | C1: new_section | D1: applies_when | E1: flow_notes | F1: legacy_file | G1: legacy_field | H1: fallback_priority | I1: transform | J1: active | K1: notes | L1: example_legacy_value | M1: example_new_value | N1: case_value_preview
A2: approval_approvalDate | B2: Approval | C2: Loan Form With Steps | D2: Financed flow | E2: For legacy migration, use disbursement date when explicit approval date is absent. | F2: RC_CUSTOMER_ACCOUNT.json | G2: DATE_OF_DISBURSE | H2: 1 | I2: identity | J2: Y | K2: ISO | N2: =IFERROR(_xludf.XLOOKUP($F2&"."&$G2,CaseSource!$A$2:$A$371,CaseSource!$B$2:$B$371,""),"")
A3: approval_approvalDate | B3: Approval | C3: Loan Form With Steps | D3: Financed flow | E3: For legacy migration, use disbursement date when explicit approval date is absent. | F3: RC_RC_INV_STATUS.json | G3: DATE_OF_DISBURSE | H3: 2 | I3: identity | J3: Y | K3: ISO | N3: =IFERROR(_xludf.XLOOKUP($F3&"."&$G3,CaseSource!$A$2:$A$371,CaseSource!$B$2:$B$371,""),"")
A4: approval_approvalDate | B4: Approval | C4: Loan Form With Steps | D4: Financed flow | E4: For legacy migration, use disbursement date when explicit approval date is absent. | F4: RC_CUSTOMER_ACCOUNT.json | G4: DATE_OF_FILE_DESPATCH | H4: 3 | I4: identity | J4: Y | K4: ISO | N4: =IFERROR(_xludf.XLOOKUP($F4&"."&$G4,CaseSource!$A$2:$A$371,CaseSource!$B$2:$B$371,""),"")
A5: approval_approvalDate | B5: Approval | C5: Loan Form With Steps | D5: Financed flow | E5: For legacy migration, use disbursement date when explicit approval date is absent. | F5: CPV_DETAIL.json | G5: CPV_DATE | H5: 4 | I5: identity | J5: Y | K5: ISO | N5: =IFERROR(_xludf.XLOOKUP($F5&"."&$G5,CaseSource!$A$2:$A$371,CaseSource!$B$2:$B$371,""),"")
A6: payoutPercentage | B6: Approval | C6: Loan Form With Steps | D6: Always | F6: RC_CUSTOMER_ACCOUNT.json | G6: PAYOUT_RATE | H6: 1 | I6: identity | J6: Y | K6: numeric | N6: =IFERROR(_xludf.XLOOKUP($F6&"."&$G6,CaseSource!$A$2:$A$371,CaseSource!$B$2:$B$371,""),"")
A7: approval_bankId | B7: Approval | C7: Loan Form With Steps | D7: Always | H7: 1 | I7: identity | J7: Y | N7: =IFERROR(_xludf.XLOOKUP($F7&"."&$G7,CaseSource!$A$2:$A$371,CaseSource!$B$2:$B$371,""),"")
A8: approval_bankName | B8: Approval | C8: Loan Form With Steps | D8: Always | H8: 1 | I8: identity | J8: Y | N8: =IFERROR(_xludf.XLOOKUP($F8&"."&$G8,CaseSource!$A$2:$A$371,CaseSource!$B$2:$B$371,""),"")
A9: approval_breakup_creditAssured | B9: Approval | C9: Loan Form With Steps | D9: Always | H9: 1 | I9: identity | J9: Y | N9: =IFERROR(_xludf.XLOOKUP($F9&"."&$G9,CaseSource!$A$2:$A$371,CaseSource!$B$2:$B$371,""),"")
A10: approval_breakup_ewFinance | B10: Approval | C10: Loan Form With Steps | D10: Always | H10: 1 | I10: identity | J10: Y | N10: =IFERROR(_xludf.XLOOKUP($F10&"."&$G10,CaseSource!$A$2:$A$371,CaseSource!$B$2:$B$371,""),"")
A11: approval_breakup_insuranceFinance | B11: Approval | C11: Loan Form With Steps | D11: Always | H11: 1 | I11: identity | J11: Y | N11: =IFERROR(_xludf.XLOOKUP($F11&"."&$G11,CaseSource!$A$2:$A$371,CaseSource!$B$2:$B$371,""),"")
A12: approval_breakup_netLoanApproved | B12: Approval | C12: Loan Form With Steps | D12: Always | H12: 1 | I12: identity | J12: Y | N12: =IFERROR(_xludf.XLOOKUP($F12&"."&$G12,CaseSource!$A$2:$A$371,CaseSource!$B$2:$B$371,""),"")
A13: approval_disbursedDate | B13: Approval | C13: Loan Form With Steps | D13: Financed flow | E13: Critical for post-file/delivery unlock in migrated records. | H13: 1 | I13: identity | J13: Y | N13: =IFERROR(_xludf.XLOOKUP($F13&"."&$G13,CaseSource!$A$2:$A$371,CaseSource!$B$2:$B$371,""),"")
A14: approval_loanAmountApproved | B14: Approval | C14: Loan Form With Steps | D14: Always | H14: 1 | I14: identity | J14: Y | N14: =IFERROR(_xludf.XLOOKUP($F14&"."&$G14,CaseSource!$A$2:$A$371,CaseSource!$B$2:$B$371,""),"")
A15: approval_loanAmountDisbursed | B15: Approval | C15: Loan Form With Steps | D15: Always | H15: 1 | I15: identity | J15: Y | N15: =IFERROR(_xludf.XLOOKUP($F15&"."&$G15,CaseSource!$A$2:$A$371,CaseSource!$B$2:$B$371,""),"")
A16: approval_processingFees | B16: Approval | C16: Loan Form With Steps | D16: Always | H16: 1 | I16: identity | J16: Y | N16: =IFERROR(_xludf.XLOOKUP($F16&"."&$G16,CaseSource!$A$2:$A$371,CaseSource!$B$2:$B$371,""),"")
A17: approval_roi | B17: Approval | C17: Loan Form With Steps | D17: Always | H17: 1 | I17: identity | J17: Y | N17: =IFERROR(_xludf.XLOOKUP($F17&"."&$G17,CaseSource!$A$2:$A$371,CaseSource!$B$2:$B$371,""),"")
A18: approval_status | B18: Approval | C18: Loan Form With Steps | D18: Financed flow | E18: Set approved/disbursed correctly; downstream stages depend on it. | H18: 1 | I18: identity | J18: Y | N18: =IFERROR(_xludf.XLOOKUP($F18&"."&$G18,CaseSource!$A$2:$A$371,CaseSource!$B$2:$B$371,""),"")
A19: approval_statusHistory | B19: Approval | C19: Loan Approval Step | D19: Always | H19: 1 | I19: identity | J19: Y | N19: =IFERROR(_xludf.XLOOKUP($F19&"."&$G19,CaseSource!$A$2:$A$371,CaseSource!$B$2:$B$371,""),"")
A20: approval_tenureMonths | B20: Approval | C20: Loan Form With Steps | D20: Always | H20: 1 | I20: identity | J20: Y | N20: =IFERROR(_xludf.XLOOKUP($F20&"."&$G20,CaseSource!$A$2:$A$371,CaseSource!$B$2:$B$371,""),"")
A21: NEW | B21: Approval | C21: Loan Approval Step | D21: Always | H21: 1 | I21: identity | J21: Y | N21: =IFERROR(_xludf.XLOOKUP($F21&"."&$G21,CaseSource!$A$2:$A$371,CaseSource!$B$2:$B$371,""),"")
A22: delivery_date | B22: Delivery | C22: Vehicle Delivery Step | D22: Always | F22: RC_CUSTOMER_ACCOUNT.json | G22: DATE_OF_DELIVERY | H22: 1 | I22: identity | J22: Y | K22: only when `typeOfLoan=New Car` in payload currently | N22: =IFERROR(_xludf.XLOOKUP($F22&"."&$G22,CaseSource!$A$2:$A$371,CaseSource!$B$2:$B$371,""),"")
A23: delivery_date | B23: Delivery | C23: Vehicle Delivery Step | D23: Always | F23: RC_RC_INV_STATUS.json | G23: DATE_OF_DELIVERY | H23: 2 | I23: identity | J23: Y | K23: only when `typeOfLoan=New Car` in payload currently | N23: =IFERROR(_xludf.XLOOKUP($F23&"."&$G23,CaseSource!$A$2:$A$371,CaseSource!$B$2:$B$371,""),"")
A24: invoice_number | B24: Delivery | C24: Loan Sticky Header | D24: Always | F24: RC_RC_INV_RECEIVING_DETAIL.json | G24: INVOICE_NUMBER | H24: 1 | I24: identity | J24: Y | K24: invoice-row priority logic | N24: =IFERROR(_xludf.XLOOKUP($F24&"."&$G24,CaseSource!$A$2:$A$371,CaseSource!$B$2:$B$371,""),"")
A25: invoice_number | B25: Delivery | C25: Loan Sticky Header | D25: Always | F25: RC_RC_INV_STATUS.json | G25: INVOICE_NUMBER | H25: 2 | I25: identity | J25: Y | K25: invoice-row priority logic | N25: =IFERROR(_xludf.XLOOKUP($F25&"."&$G25,CaseSource!$A$2:$A$371,CaseSource!$B$2:$B$371,""),"")
A26: invoice_date | B26: Delivery | C26: Vehicle Delivery Step | D26: Always | F26: RC_RC_INV_RECEIVING_DETAIL.json | G26: INVOICE_DATE | H26: 1 | I26: identity | J26: Y | K26: date | N26: =IFERROR(_xludf.XLOOKUP($F26&"."&$G26,CaseSource!$A$2:$A$371,CaseSource!$B$2:$B$371,""),"")
A27: invoice_date | B27: Delivery | C27: Vehicle Delivery Step | D27: Always | F27: RC_RC_INV_STATUS.json | G27: INVOICE_DATE | H27: 2 | I27: identity | J27: Y | K27: date | N27: =IFERROR(_xludf.XLOOKUP($F27&"."&$G27,CaseSource!$A$2:$A$371,CaseSource!$B$2:$B$371,""),"")
A28: invoice_received_as | B28: Delivery | C28: Vehicle Delivery Step | D28: Always | F28: RC_RC_INV_RECEIVING_DETAIL.json | G28: INV_RECEIVED_ON_DATE_2 | H28: 1 | I28: identity | J28: Y | K28: normalized enum | N28: =IFERROR(_xludf.XLOOKUP($F28&"."&$G28,CaseSource!$A$2:$A$371,CaseSource!$B$2:$B$371,""),"")
A29: invoice_received_from | B29: Delivery | C29: Vehicle Delivery Step | D29: Always | F29: RC_RC_INV_RECEIVING_DETAIL.json | G29: INV_RECEIVED_FROM | H29: 1 | I29: identity | J29: Y | K29: clean | N29: =IFERROR(_xludf.XLOOKUP($F29&"."&$G29,CaseSource!$A$2:$A$371,CaseSource!$B$2:$B$371,""),"")
A30: invoice_received_date | B30: Delivery | C30: Vehicle Delivery Step | D30: Always | F30: RC_RC_INV_RECEIVING_DETAIL.json | G30: INV_RECEIVED_ON_DATE | H30: 1 | I30: identity | J30: Y | K30: date | N30: =IFERROR(_xludf.XLOOKUP($F30&"."&$G30,CaseSource!$A$2:$A$371,CaseSource!$B$2:$B$371,""),"")
A31: rc_redg_no | B31: Delivery | C31: Loan Sticky Header | D31: Always | F31: RC_RC_INV_RECEIVING_DETAIL.json | G31: REGD_NUMBER | H31: 1 | I31: identity | J31: Y | K31: clean | N31: =IFERROR(_xludf.XLOOKUP($F31&"."&$G31,CaseSource!$A$2:$A$371,CaseSource!$B$2:$B$371,""),"")
A32: rc_redg_no | B32: Delivery | C32: Loan Sticky Header | D32: Always | F32: RC_CUSTOMER_ACCOUNT.json | G32: REGISTRATION_NUMBER | H32: 2 | I32: identity | J32: Y | K32: clean | N32: =IFERROR(_xludf.XLOOKUP($F32&"."&$G32,CaseSource!$A$2:$A$371,CaseSource!$B$2:$B$371,""),"")
A33: rc_redg_no | B33: Delivery | C33: Loan Sticky Header | D33: Always | F33: RC_RC_INV_STATUS.json | G33: REGD_NUMBER | H33: 3 | I33: identity | J33: Y | K33: clean | N33: =IFERROR(_xludf.XLOOKUP($F33&"."&$G33,CaseSource!$A$2:$A$371,CaseSource!$B$2:$B$371,""),"")
... A42: rc_received_date | B42: Delivery | C42: Loan Sticky Header | D42: Always | F42: RC_RC_INV_RECEIVING_DETAIL.json | G42: RC_RECEIVED_ON_DATE | H42: 1 | I42: identity | J42: Y | K42: date | N42: =IFERROR(_xludf.XLOOKUP($F42&"."&$G42,CaseSource!$A$2:$A$371,CaseSource!$B$2:$B$371,""),"")
A43: delivery_by | B43: Delivery | C43: Vehicle Delivery Step | D43: Always | H43: 1 | I43: identity | J43: Y | N43: =IFERROR(_xludf.XLOOKUP($F43&"."&$G43,CaseSource!$A$2:$A$371,CaseSource!$B$2:$B$371,""),"")
A44: delivery_dealerAddress | B44: Delivery | C44: Vehicle Delivery Step | D44: Always | H44: 1 | I44: identity | J44: Y | N44: =IFERROR(_xludf.XLOOKUP($F44&"."&$G44,CaseSource!$A$2:$A$371,CaseSource!$B$2:$B$371,""),"")
A45: delivery_dealerContactNumber | B45: Delivery | C45: Vehicle Delivery Step | D45: Always | H45: 1 | I45: identity | J45: Y | N45: =IFERROR(_xludf.XLOOKUP($F45&"."&$G45,CaseSource!$A$2:$A$371,CaseSource!$B$2:$B$371,""),"")
A46: delivery_dealerContactPerson | B46: Delivery | C46: Vehicle Delivery Step | D46: Always | H46: 1 | I46: identity | J46: Y | N46: =IFERROR(_xludf.XLOOKUP($F46&"."&$G46,CaseSource!$A$2:$A$371,CaseSource!$B$2:$B$371,""),"")
A47: delivery_dealerName | B47: Delivery | C47: Vehicle Delivery Step | D47: Always | H47: 1 | I47: identity | J47: Y | N47: =IFERROR(_xludf.XLOOKUP($F47&"."&$G47,CaseSource!$A$2:$A$371,CaseSource!$B$2:$B$371,""),"")
A48: insurance_by | B48: Delivery | C48: Vehicle Delivery Step | D48: Always | H48: 1 | I48: identity | J48: Y | N48: =IFERROR(_xludf.XLOOKUP($F48&"."&$G48,CaseSource!$A$2:$A$371,CaseSource!$B$2:$B$371,""),"")
A49: insurance_company_name | B49: Delivery | C49: Vehicle Delivery Step | D49: Always | H49: 1 | I49: identity | J49: Y | N49: =IFERROR(_xludf.XLOOKUP($F49&"."&$G49,CaseSource!$A$2:$A$371,CaseSource!$B$2:$B$371,""),"")
A50: insurance_policy_duration_od | B50: Delivery | C50: VehicleDeliveryStep | D50: Always | H50: 1 | I50: identity | J50: Y | N50: =IFERROR(_xludf.XLOOKUP($F50&"."&$G50,CaseSource!$A$2:$A$371,CaseSource!$B$2:$B$371,""),"")
A51: insurance_policy_end_date_od | B51: Delivery | C51: VehicleDeliveryStep | D51: Always | H51: 1 | I51: identity | J51: Y | N51: =IFERROR(_xludf.XLOOKUP($F51&"."&$G51,CaseSource!$A$2:$A$371,CaseSource!$B$2:$B$371,""),"")
A52: insurance_policy_number | B52: Delivery | C52: Vehicle Delivery Step | D52: Always | H52: 1 | I52: identity | J52: Y | N52: =IFERROR(_xludf.XLOOKUP($F52&"."&$G52,CaseSource!$A$2:$A$371,CaseSource!$B$2:$B$371,""),"")
A53: insurance_policy_start_date | B53: Delivery | C53: VehicleDeliveryStep | D53: Always | H53: 1 | I53: identity | J53: Y | N53: =IFERROR(_xludf.XLOOKUP($F53&"."&$G53,CaseSource!$A$2:$A$371,CaseSource!$B$2:$B$371,""),"")
A54: yearOfManufacture | B54: Delivery | C54: VehicleDeliveryStep | D54: Always | H54: 1 | I54: identity | J54: Y | N54: =IFERROR(_xludf.XLOOKUP($F54&"."&$G54,CaseSource!$A$2:$A$371,CaseSource!$B$2:$B$371,""),"")
A55: panNumber | B55: Header / Shared | C55: Loan Sticky Header | D55: Always | F55: CPV_DETAIL.json | G55: PAN_NUMBER | H55: 1 | I55: identity | J55: Y | K55: clean text | N55: =IFERROR(_xludf.XLOOKUP($F55&"."&$G55,CaseSource!$A$2:$A$371,CaseSource!$B$2:$B$371,""),"")
A56: aadhaarNumber | B56: Header / Shared | C56: Loan Sticky Header | D56: Always | H56: 1 | I56: identity | J56: Y | N56: =IFERROR(_xludf.XLOOKUP($F56&"."&$G56,CaseSource!$A$2:$A$371,CaseSource!$B$2:$B$371,""),"")
A57: caseType | B57: Header / Shared | C57: Loan Sticky Header | D57: Always | H57: 1 | I57: identity | J57: Y | N57: =IFERROR(_xludf.XLOOKUP($F57&"."&$G57,CaseSource!$A$2:$A$371,CaseSource!$B$2:$B$371,""),"")
A58: co_name | B58: Header / Shared | C58: Loan Sticky Header | D58: Always | H58: 1 | I58: identity | J58: Y | N58: =IFERROR(_xludf.XLOOKUP($F58&"."&$G58,CaseSource!$A$2:$A$371,CaseSource!$B$2:$B$371,""),"")
A59: coApplicant_name | B59: Header / Shared | C59: Loan Sticky Header | D59: Always | H59: 1 | I59: identity | J59: Y | N59: =IFERROR(_xludf.XLOOKUP($F59&"."&$G59,CaseSource!$A$2:$A$371,CaseSource!$B$2:$B$371,""),"")
A60: createdAt | B60: Header / Shared | C60: Loan Form With Steps | D60: Always | H60: 1 | I60: identity | J60: Y | N60: =IFERROR(_xludf.XLOOKUP($F60&"."&$G60,CaseSource!$A$2:$A$371,CaseSource!$B$2:$B$371,""),"")
A61: customerAadhar | B61: Header / Shared | C61: Loan Sticky Header | D61: Always | H61: 1 | I61: identity | J61: Y | N61: =IFERROR(_xludf.XLOOKUP($F61&"."&$G61,CaseSource!$A$2:$A$371,CaseSource!$B$2:$B$371,""),"")
A62: customerAddress | B62: Header / Shared | C62: Loan Sticky Header | D62: Always | H62: 1 | I62: identity | J62: Y | N62: =IFERROR(_xludf.XLOOKUP($F62&"."&$G62,CaseSource!$A$2:$A$371,CaseSource!$B$2:$B$371,""),"")
A63: customerEmail | B63: Header / Shared | C63: Loan Sticky Header | D63: Always | H63: 1 | I63: identity | J63: Y | N63: =IFERROR(_xludf.XLOOKUP($F63&"."&$G63,CaseSource!$A$2:$A$371,CaseSource!$B$2:$B$371,""),"")
A64: customerPan | B64: Header / Shared | C64: Loan Sticky Header | D64: Always | H64: 1 | I64: identity | J64: Y | N64: =IFERROR(_xludf.XLOOKUP($F64&"."&$G64,CaseSource!$A$2:$A$371,CaseSource!$B$2:$B$371,""),"")
A65: downPayment | B65: Header / Shared | C65: Loan Sticky Header | D65: Always | H65: 1 | I65: identity | J65: Y | N65: =IFERROR(_xludf.XLOOKUP($F65&"."&$G65,CaseSource!$A$2:$A$371,CaseSource!$B$2:$B$371,""),"")
A66: gu_name | B66: Header / Shared | C66: Loan Sticky Header | D66: Always | H66: 1 | I66: identity | J66: Y | N66: =IFERROR(_xludf.XLOOKUP($F66&"."&$G66,CaseSource!$A$2:$A$371,CaseSource!$B$2:$B$371,""),"")
A67: guarantor_name | B67: Header / Shared | C67: Loan Sticky Header | D67: Always | H67: 1 | I67: identity | J67: Y | N67: =IFERROR(_xludf.XLOOKUP($F67&"."&$G67,CaseSource!$A$2:$A$371,CaseSource!$B$2:$B$371,""),"")
... A89: total_amount_received | B89: Payout | C89: Payout Receivables Dashboard | D89: Always | H89: 1 | I89: identity | J89: Y | N89: =IFERROR(_xludf.XLOOKUP($F89&"."&$G89,CaseSource!$A$2:$A$371,CaseSource!$B$2:$B$371,""),"")
A90: loan_number | B90: Post-File | C90: PostFileDispatchAndRecords | D90: Always | F90: RC_CUSTOMER_ACCOUNT.json | G90: LOAN_NUMBER_PREFIX | H90: 1 | I90: identity | J90: Y | K90: concatenated available parts | N90: =IFERROR(_xludf.XLOOKUP($F90&"."&$G90,CaseSource!$A$2:$A$371,CaseSource!$B$2:$B$371,""),"")
A91: postfile_firstEmiDate | B91: Post-File | C91: Loan Form With Steps | D91: Always | F91: RC_CUSTOMER_ACCOUNT.json | G91: EMI_DUE_DATE | H91: 1 | I91: identity | J91: Y | K91: date | N91: =IFERROR(_xludf.XLOOKUP($F91&"."&$G91,CaseSource!$A$2:$A$371,CaseSource!$B$2:$B$371,""),"")
A92: postfile_emiAmount | B92: Post-File | C92: Loan Form With Steps | D92: Always | F92: RC_CUSTOMER_ACCOUNT.json | G92: EMI | H92: 1 | I92: identity | J92: Y | K92: numeric | N92: =IFERROR(_xludf.XLOOKUP($F92&"."&$G92,CaseSource!$A$2:$A$371,CaseSource!$B$2:$B$371,""),"")
A93: postfile_emiMode | B93: Post-File | C93: Post File Approval Details | D93: Always | F93: RC_CUSTOMER_ACCOUNT.json | G93: EMI_TYPE_ARREAR_ADVANCE | H93: 1 | I93: identity | J93: Y | K93: default `Arrear` | N93: =IFERROR(_xludf.XLOOKUP($F93&"."&$G93,CaseSource!$A$2:$A$371,CaseSource!$B$2:$B$371,""),"")
A94: postfile_disbursedCreditAssured | B94: Post-File | C94: Emicalculator | D94: Always | F94: RC_CUSTOMER_ACCOUNT.json | G94: ICICI_CREDIT_ASSURED | H94: 1 | I94: identity | J94: Y | K94: numeric | N94: =IFERROR(_xludf.XLOOKUP($F94&"."&$G94,CaseSource!$A$2:$A$371,CaseSource!$B$2:$B$371,""),"")
A95: postfile_disbursedInsurance | B95: Post-File | C95: Emicalculator | D95: Always | F95: RC_CUSTOMER_ACCOUNT.json | G95: INSURANCE_FINANCED | H95: 1 | I95: identity | J95: Y | K95: numeric | N95: =IFERROR(_xludf.XLOOKUP($F95&"."&$G95,CaseSource!$A$2:$A$371,CaseSource!$B$2:$B$371,""),"")
A96: dispatch_date | B96: Post-File | C96: Post File Dispatch And Records | D96: Always | F96: RC_DOC_DESPATCH_MASTER.json | G96: DATE_OF_DESP | H96: 1 | I96: identity | J96: Y | K96: date | N96: =IFERROR(_xludf.XLOOKUP($F96&"."&$G96,CaseSource!$A$2:$A$371,CaseSource!$B$2:$B$371,""),"")
A97: dispatch_date | B97: Post-File | C97: Post File Dispatch And Records | D97: Always | F97: RC_CUSTOMER_ACCOUNT.json | G97: DATE_OF_FILE_DESPATCH | H97: 2 | I97: identity | J97: Y | K97: date | N97: =IFERROR(_xludf.XLOOKUP($F97&"."&$G97,CaseSource!$A$2:$A$371,CaseSource!$B$2:$B$371,""),"")
A98: dispatch_time | B98: Post-File | C98: Post File Dispatch And Records | D98: Always | F98: RC_DOC_DESPATCH_MASTER.json | G98: TIME_OF_DESP | H98: 1 | I98: identity | J98: Y | K98: time | N98: =IFERROR(_xludf.XLOOKUP($F98&"."&$G98,CaseSource!$A$2:$A$371,CaseSource!$B$2:$B$371,""),"")
A99: dispatch_time | B99: Post-File | C99: Post File Dispatch And Records | D99: Always | F99: RC_CUSTOMER_ACCOUNT.json | G99: TIME_OF_FILE_DESPATCH | H99: 2 | I99: identity | J99: Y | K99: time | N99: =IFERROR(_xludf.XLOOKUP($F99&"."&$G99,CaseSource!$A$2:$A$371,CaseSource!$B$2:$B$371,""),"")
A100: dispatch_through | B100: Post-File | C100: Post File Dispatch And Records | D100: Always | F100: RC_DOC_DESPATCH_MASTER.json | G100: DESP_THROUGH | H100: 1 | I100: identity | J100: Y | K100: clean | N100: =IFERROR(_xludf.XLOOKUP($F100&"."&$G100,CaseSource!$A$2:$A$371,CaseSource!$B$2:$B$371,""),"")
A101: dispatch_through | B101: Post-File | C101: Post File Dispatch And Records | D101: Always | F101: RC_CUSTOMER_ACCOUNT.json | G101: DESPATCH_FOR_APPROVAL_THROUGH | H101: 2 | I101: identity | J101: Y | K101: clean | N101: =IFERROR(_xludf.XLOOKUP($F101&"."&$G101,CaseSource!$A$2:$A$371,CaseSource!$B$2:$B$371,""),"")
... A104: si_signedBy | B104: Post-File | C104: Post File Instrument Details | D104: Always | F104: RC_INSTRUMENT_DETAIL.json | G104: INSTRMNT_BY_BORWR_GRNTR | H104: 1 | I104: identity | J104: Y | K104: normalized party | N104: =IFERROR(_xludf.XLOOKUP($F104&"."&$G104,CaseSource!$A$2:$A$371,CaseSource!$B$2:$B$371,""),"")
A105: aadhaarCardDocUrl | B105: Post-File | C105: Documents List | D105: Always | H105: 1 | I105: identity | J105: Y | N105: =IFERROR(_xludf.XLOOKUP($F105&"."&$G105,CaseSource!$A$2:$A$371,CaseSource!$B$2:$B$371,""),"")
A106: addressProofDocUrl | B106: Post-File | C106: Documents List | D106: Always | H106: 1 | I106: identity | J106: Y | N106: =IFERROR(_xludf.XLOOKUP($F106&"."&$G106,CaseSource!$A$2:$A$371,CaseSource!$B$2:$B$371,""),"")
A107: cheque_1_accountNumber | B107: Post-File | C107: PostFileInstrumentDetails | D107: Always | H107: 1 | I107: identity | J107: Y | N107: =IFERROR(_xludf.XLOOKUP($F107&"."&$G107,CaseSource!$A$2:$A$371,CaseSource!$B$2:$B$371,""),"")
A108: cheque_1_amount | B108: Post-File | C108: PostFileInstrumentDetails | D108: Always | H108: 1 | I108: identity | J108: Y | N108: =IFERROR(_xludf.XLOOKUP($F108&"."&$G108,CaseSource!$A$2:$A$371,CaseSource!$B$2:$B$371,""),"")
A109: cheque_1_bankName | B109: Post-File | C109: PostFileInstrumentDetails | D109: Always | H109: 1 | I109: identity | J109: Y | N109: =IFERROR(_xludf.XLOOKUP($F109&"."&$G109,CaseSource!$A$2:$A$371,CaseSource!$B$2:$B$371,""),"")
A110: cheque_1_date | B110: Post-File | C110: PostFileInstrumentDetails | D110: Always | H110: 1 | I110: identity | J110: Y | N110: =IFERROR(_xludf.XLOOKUP($F110&"."&$G110,CaseSource!$A$2:$A$371,CaseSource!$B$2:$B$371,""),"")
A111: cheque_1_favouring | B111: Post-File | C111: PostFileInstrumentDetails | D111: Always | H111: 1 | I111: identity | J111: Y | N111: =IFERROR(_xludf.XLOOKUP($F111&"."&$G111,CaseSource!$A$2:$A$371,CaseSource!$B$2:$B$371,""),"")
A112: cheque_1_number | B112: Post-File | C112: PostFileInstrumentDetails | D112: Always | H112: 1 | I112: identity | J112: Y | N112: =IFERROR(_xludf.XLOOKUP($F112&"."&$G112,CaseSource!$A$2:$A$371,CaseSource!$B$2:$B$371,""),"")
A113: cheque_1_signedBy | B113: Post-File | C113: PostFileInstrumentDetails | D113: Always | H113: 1 | I113: identity | J113: Y | N113: =IFERROR(_xludf.XLOOKUP($F113&"."&$G113,CaseSource!$A$2:$A$371,CaseSource!$B$2:$B$371,""),"")
A114: cheque_1_tag | B114: Post-File | C114: PostFileInstrumentDetails | D114: Always | H114: 1 | I114: identity | J114: Y | N114: =IFERROR(_xludf.XLOOKUP($F114&"."&$G114,CaseSource!$A$2:$A$371,CaseSource!$B$2:$B$371,""),"")
A115: co_aadhaarCardDocUrl | B115: Post-File | C115: Documents List | D115: Always | H115: 1 | I115: identity | J115: Y | N115: =IFERROR(_xludf.XLOOKUP($F115&"."&$G115,CaseSource!$A$2:$A$371,CaseSource!$B$2:$B$371,""),"")
A116: co_addressProofDocUrl | B116: Post-File | C116: Documents List | D116: Always | H116: 1 | I116: identity | J116: Y | N116: =IFERROR(_xludf.XLOOKUP($F116&"."&$G116,CaseSource!$A$2:$A$371,CaseSource!$B$2:$B$371,""),"")
... A122: delivery_rcFile | B122: Post-File | C122: Loan Form With Steps | D122: Always | H122: 1 | I122: identity | J122: Y | N122: =IFERROR(_xludf.XLOOKUP($F122&"."&$G122,CaseSource!$A$2:$A$371,CaseSource!$B$2:$B$371,""),"")
A123: disbursement_date | B123: Post-File | C123: Loan Sticky Header | D123: Financed flow | E123: Keep aligned with approval_disbursedDate. | H123: 1 | I123: identity | J123: Y | N123: =IFERROR(_xludf.XLOOKUP($F123&"."&$G123,CaseSource!$A$2:$A$371,CaseSource!$B$2:$B$371,""),"")
A124: disbursement_time | B124: Post-File | C124: Post File Dispatch And Records | D124: Always | H124: 1 | I124: identity | J124: Y | N124: =IFERROR(_xludf.XLOOKUP($F124&"."&$G124,CaseSource!$A$2:$A$371,CaseSource!$B$2:$B$371,""),"")
A125: dlDocUrl | B125: Post-File | C125: Documents List | D125: Always | H125: 1 | I125: identity | J125: Y | N125: =IFERROR(_xludf.XLOOKUP($F125&"."&$G125,CaseSource!$A$2:$A$371,CaseSource!$B$2:$B$371,""),"")
A126: ecs_accountNumber | B126: Post-File | C126: Post File Instrument Details | D126: Always | H126: 1 | I126: identity | J126: Y | N126: =IFERROR(_xludf.XLOOKUP($F126&"."&$G126,CaseSource!$A$2:$A$371,CaseSource!$B$2:$B$371,""),"")
A127: ecs_amount | B127: Post-File | C127: Post File Instrument Details | D127: Always | H127: 1 | I127: identity | J127: Y | N127: =IFERROR(_xludf.XLOOKUP($F127&"."&$G127,CaseSource!$A$2:$A$371,CaseSource!$B$2:$B$371,""),"")
A128: ecs_bankName | B128: Post-File | C128: Post File Instrument Details | D128: Always | H128: 1 | I128: identity | J128: Y | N128: =IFERROR(_xludf.XLOOKUP($F128&"."&$G128,CaseSource!$A$2:$A$371,CaseSource!$B$2:$B$371,""),"")
A129: ecs_date | B129: Post-File | C129: Post File Instrument Details | D129: Always | H129: 1 | I129: identity | J129: Y | N129: =IFERROR(_xludf.XLOOKUP($F129&"."&$G129,CaseSource!$A$2:$A$371,CaseSource!$B$2:$B$371,""),"")
A130: ecs_favouring | B130: Post-File | C130: Post File Instrument Details | D130: Always | H130: 1 | I130: identity | J130: Y | N130: =IFERROR(_xludf.XLOOKUP($F130&"."&$G130,CaseSource!$A$2:$A$371,CaseSource!$B$2:$B$371,""),"")
A131: ecs_image | B131: Post-File | C131: Post File Instrument Details | D131: Always | H131: 1 | I131: identity | J131: Y | N131: =IFERROR(_xludf.XLOOKUP($F131&"."&$G131,CaseSource!$A$2:$A$371,CaseSource!$B$2:$B$371,""),"")
A132: ecs_micrCode | B132: Post-File | C132: Post File Instrument Details | D132: Always | H132: 1 | I132: identity | J132: Y | N132: =IFERROR(_xludf.XLOOKUP($F132&"."&$G132,CaseSource!$A$2:$A$371,CaseSource!$B$2:$B$371,""),"")
A133: ecs_signedBy | B133: Post-File | C133: Post File Instrument Details | D133: Always | H133: 1 | I133: identity | J133: Y | N133: =IFERROR(_xludf.XLOOKUP($F133&"."&$G133,CaseSource!$A$2:$A$371,CaseSource!$B$2:$B$371,""),"")
A134: ecs_tag | B134: Post-File | C134: Post File Instrument Details | D134: Always | H134: 1 | I134: identity | J134: Y | N134: =IFERROR(_xludf.XLOOKUP($F134&"."&$G134,CaseSource!$A$2:$A$371,CaseSource!$B$2:$B$371,""),"")
A135: gstDocUrl | B135: Post-File | C135: Documents List | D135: Always | H135: 1 | I135: identity | J135: Y | N135: =IFERROR(_xludf.XLOOKUP($F135&"."&$G135,CaseSource!$A$2:$A$371,CaseSource!$B$2:$B$371,""),"")
... A169: vehicleRCUrl | B169: Post-File | C169: Documents List | D169: Always | H169: 1 | I169: identity | J169: Y | N169: =IFERROR(_xludf.XLOOKUP($F169&"."&$G169,CaseSource!$A$2:$A$371,CaseSource!$B$2:$B$371,""),"")
...

Sheet NewFieldCatalog
A1: new_field | B1: new_type | C1: new_page | D1: new_section | E1: applies_when | F1: flow_notes | G1: new_source_files
A2: aadhaarCardDocUrl | B2: string | C2: Post-File | D2: Documents List | E2: Always | G2: src/modules/loans/components/loan-form/post-file/DocumentsList.jsx; src/modules/loans/components/loan-form/post-file/PostFileDocumentManagement.jsx
A3: aadhaarNumber | B3: string | C3: Header / Shared | D3: Loan Sticky Header | E3: Always | G3: src/modules/loans/components/LoanStickyHeader.jsx
A4: accessoriesAmount | B4: number | C4: Pre-File | D4: Post File Vehicle Verification | E4: Always | G4: src/modules/loans/components/loan-form/post-file/PostFileVehicleVerification.jsx; src/modules/loans/components/loan-form/pre-file/VehiclePricingLoanDetails.jsx
A5: accountNumber | B5: number | C5: Pre-File | D5: Post File Dispatch And Records | E5: Always | G5: src/modules/loans/components/loan-form/post-file/PostFileDispatchAndRecords.jsx; src/modules/loans/components/loan-form/pre-file/IncomeBankingDetailsPreFile.jsx
A6: accountSinceYears | B6: number | C6: Pre-File | D6: Income Banking Details Pre File | E6: Always | G6: src/modules/loans/components/loan-form/pre-file/IncomeBankingDetailsPreFile.jsx
A7: accountType | B7: string | C7: Pre-File | D7: Income Banking Details Pre File | E7: Always | G7: src/modules/loans/components/loan-form/pre-file/IncomeBankingDetailsPreFile.jsx
A8: addressProofDocUrl | B8: string | C8: Post-File | D8: Documents List | E8: Always | G8: src/modules/loans/components/loan-form/post-file/DocumentsList.jsx; src/modules/loans/components/loan-form/post-file/PostFileDocumentManagement.jsx
A9: addressProofNumber | B9: boolean | C9: Pre-File | D9: Personal Details Pre File | E9: Always | G9: src/modules/loans/components/loan-form/pre-file/PersonalDetailsPreFile.jsx
A10: addressProofType | B10: boolean | C10: Pre-File | D10: Personal Details Pre File | E10: Always | G10: src/modules/loans/components/loan-form/pre-file/PersonalDetailsPreFile.jsx
A11: addressType | B11: number | C11: Pre-File | D11: Personal Details Pre File | E11: Always | G11: src/modules/loans/components/loan-form/pre-file/PersonalDetailsPreFile.jsx
A12: advanceEmi | B12: number | C12: Pre-File | D12: Vehicle Pricing Loan Details | E12: Always | G12: src/modules/loans/components/loan-form/pre-file/VehiclePricingLoanDetails.jsx
A13: applicantType | B13: string | C13: Profile | D13: Lead Details | E13: Always | F13: Individual vs Company changes form visibility and required sections. | G13: src/modules/loans/components/loan-form/customer-profile/LeadDetails.jsx; src/modules/loans/components/loan-form/pre-file/AuthorisedSignatorySection.jsx; src/modules/loans/components/loan-form/pre-file/OccupationalDetailsPreFile.jsx
A14: approval_approvalDate | B14: string | C14: Approval | D14: Loan Form With Steps | E14: Financed flow | F14: For legacy migration, use disbursement date when explicit approval date is absent. | G14: src/modules/loans/components/LoanFormWithSteps.jsx; src/modules/loans/components/loan-form/loan-approval/LoanApprovalStep.jsx
A15: approval_bankId | B15: string | C15: Approval | D15: Loan Form With Steps | E15: Always | G15: src/modules/loans/components/LoanFormWithSteps.jsx; src/modules/loans/components/loan-form/loan-approval/LoanApprovalStep.jsx
A16: approval_bankName | B16: string | C16: Approval | D16: Loan Form With Steps | E16: Always | G16: src/modules/loans/components/LoanFormWithSteps.jsx; src/modules/loans/components/LoanStickyHeader.jsx; src/modules/loans/components/loan-form/loan-approval/LoanApprovalStep.jsx; src/modules/loans/components/loan-form/payout/PayoutSection.jsx; src/modules/loans/components/loan-form/post-file/PostFileApprovalDetails.jsx; src/modules/loans/components/loan-form/vehicle-delivery/VehicleDeliveryStep.jsx
A17: approval_banksData | B17: string | C17: Shared | D17: Loan Form With Steps | E17: Always | G17: src/modules/loans/components/LoanFormWithSteps.jsx
A18: approval_breakup_creditAssured | B18: string | C18: Approval | D18: Loan Form With Steps | E18: Always | G18: src/modules/loans/components/LoanFormWithSteps.jsx; src/modules/loans/components/loan-form/loan-approval/LoanApprovalStep.jsx
A19: approval_breakup_ewFinance | B19: string | C19: Approval | D19: Loan Form With Steps | E19: Always | G19: src/modules/loans/components/LoanFormWithSteps.jsx; src/modules/loans/components/loan-form/loan-approval/LoanApprovalStep.jsx
A20: approval_breakup_insuranceFinance | B20: string | C20: Approval | D20: Loan Form With Steps | E20: Always | G20: src/modules/loans/components/LoanFormWithSteps.jsx; src/modules/loans/components/loan-form/loan-approval/LoanApprovalStep.jsx
A21: approval_breakup_netLoanApproved | B21: string | C21: Approval | D21: Loan Form With Steps | E21: Always | G21: src/modules/loans/components/LoanFormWithSteps.jsx; src/modules/loans/components/loan-form/loan-approval/LoanApprovalStep.jsx; src/modules/loans/components/loan-form/payout/PayoutSection.jsx
A22: approval_disbursedDate | B22: string | C22: Approval | D22: Loan Form With Steps | E22: Financed flow | F22: Critical for post-file/delivery unlock in migrated records. | G22: src/modules/loans/components/LoanFormWithSteps.jsx; src/modules/loans/components/loan-form/loan-approval/LoanApprovalStep.jsx; src/modules/loans/components/loan-form/post-file/PostFileApprovalDetails.jsx
A23: approval_loanAmountApproved | B23: string | C23: Approval | D23: Loan Form With Steps | E23: Always | G23: src/modules/loans/components/LoanFormWithSteps.jsx; src/modules/loans/components/LoanStickyHeader.jsx; src/modules/loans/components/loan-form/loan-approval/LoanApprovalStep.jsx; src/modules/loans/components/loan-form/post-file/PostFileApprovalDetails.jsx
A24: approval_loanAmountDisbursed | B24: string | C24: Approval | D24: Loan Form With Steps | E24: Always | G24: src/modules/loans/components/LoanFormWithSteps.jsx; src/modules/loans/components/loan-form/loan-approval/LoanApprovalStep.jsx; src/modules/loans/components/loan-form/payout/PayoutSection.jsx; src/modules/loans/components/loan-form/post-file/PostFileApprovalDetails.jsx
A25: approval_processingFees | B25: string | C25: Approval | D25: Loan Form With Steps | E25: Always | G25: src/modules/loans/components/LoanFormWithSteps.jsx; src/modules/loans/components/loan-form/loan-approval/LoanApprovalStep.jsx; src/modules/loans/components/loan-form/post-file/PostFileApprovalDetails.jsx
A26: approval_roi | B26: string | C26: Approval | D26: Loan Form With Steps | E26: Always | G26: src/modules/loans/components/LoanFormWithSteps.jsx; src/modules/loans/components/loan-form/loan-approval/LoanApprovalStep.jsx; src/modules/loans/components/loan-form/post-file/PostFileApprovalDetails.jsx
A27: approval_status | B27: string | C27: Approval | D27: Loan Form With Steps | E27: Financed flow | F27: Set approved/disbursed correctly; downstream stages depend on it. | G27: src/modules/loans/components/LoanFormWithSteps.jsx; src/modules/loans/components/LoanStickyHeader.jsx; src/modules/loans/components/loan-form/loan-approval/LoanApprovalStep.jsx; src/modules/loans/components/loan-form/payout/PayoutSection.jsx; src/modules/loans/components/loan-form/post-file/PostFileApprovalDetails.jsx
A28: approval_statusHistory | B28: string | C28: Approval | D28: Loan Approval Step | E28: Always | G28: src/modules/loans/components/loan-form/loan-approval/LoanApprovalStep.jsx
A29: approval_tenureMonths | B29: string | C29: Approval | D29: Loan Form With Steps | E29: Always | G29: src/modules/loans/components/LoanFormWithSteps.jsx; src/modules/loans/components/LoanStickyHeader.jsx; src/modules/loans/components/loan-form/loan-approval/LoanApprovalStep.jsx; src/modules/loans/components/loan-form/post-file/PostFileApprovalDetails.jsx
A30: bankName | B30: string | C30: Pre-File | D30: Loan Form With Steps | E30: Always | G30: src/modules/loans/components/LoanFormWithSteps.jsx; src/modules/loans/components/loan-form/post-file/PostFileDispatchAndRecords.jsx; src/modules/loans/components/loan-form/pre-file/IncomeBankingDetailsPreFile.jsx
A31: billDate | B31: string | C31: Payout | D31: Bill Printing Modal | E31: Always | G31: src/modules/loans/components/loan-form/payout/BillPrintingModal.jsx
A32: billNumber | B32: string | C32: Payout | D32: Bill Printing Modal | E32: Always | G32: src/modules/loans/components/loan-form/payout/BillPrintingModal.jsx
A33: boughtInYear | B33: number | C33: Pre-File | D33: Post File Vehicle Verification | E33: Always | G33: src/modules/loans/components/loan-form/post-file/PostFileVehicleVerification.jsx; src/modules/loans/components/loan-form/pre-file/VehiclePricingLoanDetails.jsx
A34: branch | B34: number | C34: Pre-File | D34: Post File Dispatch And Records | E34: Always | G34: src/modules/loans/components/loan-form/post-file/PostFileDispatchAndRecords.jsx; src/modules/loans/components/loan-form/pre-file/IncomeBankingDetailsPreFile.jsx
A35: bulk_next_action | B35: string | C35: Payout | D35: Payout Receivables Dashboard | E35: Always | G35: src/modules/loans/components/loan-form/payout/PayoutReceivablesDashboard.jsx
A36: bulk_priority | B36: string | C36: Payout | D36: Payout Receivables Dashboard | E36: Always | G36: src/modules/loans/components/loan-form/payout/PayoutReceivablesDashboard.jsx
A37: bulk_remarks | B37: string | C37: Payout | D37: Payout Receivables Dashboard | E37: Always | G37: src/modules/loans/components/loan-form/payout/PayoutReceivablesDashboard.jsx
A38: businessNature | B38: string | C38: Pre-File | D38: Occupational Details Pre File | E38: Always | G38: src/modules/loans/components/loan-form/pre-file/OccupationalDetailsPreFile.jsx
A39: caseType | B39: string | C39: Header / Shared | D39: Loan Sticky Header | E39: Always | G39: src/modules/loans/components/LoanStickyHeader.jsx
... A92: createdAt | B92: string | C92: Header / Shared | D92: Loan Form With Steps | E92: Always | G92: src/modules/loans/components/LoanFormWithSteps.jsx; src/modules/loans/components/LoanStickyHeader.jsx
A93: currentStage | B93: string | C93: Shared | D93: Loan Form With Steps | E93: Always | F93: Must respect legacy approval/disbursement progression for migration cases. | G93: src/modules/loans/components/LoanFormWithSteps.jsx
A94: customerAadhar | B94: string | C94: Header / Shared | D94: Loan Sticky Header | E94: Always | G94: src/modules/loans/components/LoanStickyHeader.jsx
A95: customerAddress | B95: string | C95: Header / Shared | D95: Loan Sticky Header | E95: Always | G95: src/modules/loans/components/LoanStickyHeader.jsx
A96: customerEmail | B96: string | C96: Header / Shared | D96: Loan Sticky Header | E96: Always | G96: src/modules/loans/components/LoanStickyHeader.jsx
A97: customerId | B97: number | C97: Pre-File | D97: Loan Form With Steps | E97: Always | G97: src/modules/loans/components/LoanFormWithSteps.jsx; src/modules/loans/components/loan-form/post-file/PostFileDocumentManagement.jsx; src/modules/loans/components/loan-form/pre-file/IncomeBankingDetailsPreFile.jsx; src/modules/loans/components/loan-form/pre-file/PreFileStep.jsx
A98: customerIdDisplay | B98: number | C98: Pre-File | D98: IncomeBankingDetailsPreFile | E98: Always | G98: /Users/gauravgrover/cdb-frontend/src/modules/loans/components/loan-form/pre-file/IncomeBankingDetailsPreFile.jsx
A99: customerName | B99: number | C99: Profile | D99: Emicustomer Details | E99: Always | G99: src/modules/loans/components/EMICustomerDetails.jsx; src/modules/loans/components/LoanFormWithSteps.jsx; src/modules/loans/components/LoanStickyHeader.jsx; src/modules/loans/components/loan-form/customer-profile/PersonalDetailsSimplified.jsx; src/modules/loans/components/loan-form/pre-file/PersonalDetailsPreFile.jsx
A100: customerPan | B100: string | C100: Header / Shared | D100: Loan Sticky Header | E100: Always | G100: src/modules/loans/components/LoanStickyHeader.jsx
A101: customerType | B101: string | C101: Post-File | D101: Post File Document Management | E101: Always | G101: src/modules/loans/components/loan-form/post-file/PostFileDocumentManagement.jsx
A102: dealerAddress | B102: string | C102: Profile | D102: Lead Details | E102: Always | G102: src/modules/loans/components/loan-form/customer-profile/LeadDetails.jsx; src/modules/loans/components/loan-form/post-file/PostFileVehicleVerification.jsx; src/modules/loans/components/loan-form/pre-file/Section7RecordDetails.jsx; src/modules/loans/components/loan-form/pre-file/VehiclePricingLoanDetails.jsx
A103: dealerContactNumber | B103: string | C103: Pre-File | D103: Post File Vehicle Verification | E103: Always | G103: src/modules/loans/components/loan-form/post-file/PostFileVehicleVerification.jsx; src/modules/loans/components/loan-form/pre-file/VehiclePricingLoanDetails.jsx
A104: dealerContactPerson | B104: string | C104: Pre-File | D104: Post File Vehicle Verification | E104: Always | G104: src/modules/loans/components/loan-form/post-file/PostFileVehicleVerification.jsx; src/modules/loans/components/loan-form/pre-file/VehiclePricingLoanDetails.jsx
A105: dealerDiscount | B105: number | C105: Pre-File | D105: Vehicle Pricing Popup | E105: Always | G105: src/modules/loans/components/VehiclePricingPopup.jsx; src/modules/loans/components/loan-form/post-file/PostFileVehicleVerification.jsx; src/modules/loans/components/loan-form/pre-file/VehiclePricingLoanDetails.jsx
... A107: dealerName | B107: string | C107: Profile | D107: Lead Details | E107: Always | G107: src/modules/loans/components/loan-form/customer-profile/LeadDetails.jsx; src/modules/loans/components/loan-form/post-file/PostFileVehicleVerification.jsx; src/modules/loans/components/loan-form/pre-file/Section7RecordDetails.jsx; src/modules/loans/components/loan-form/pre-file/VehiclePricingLoanDetails.jsx
A108: dealtBy | B108: string | C108: Profile | D108: Lead Details | E108: Record details / dispatch handling | F108: Map from DEALT_BY-like legacy field. Do NOT swap with sourceName. | G108: src/modules/loans/components/loan-form/customer-profile/LeadDetails.jsx; src/modules/loans/components/loan-form/pre-file/Section7RecordDetails.jsx
A109: delivery_by | B109: string | C109: Delivery | D109: Vehicle Delivery Step | E109: Always | G109: src/modules/loans/components/loan-form/vehicle-delivery/VehicleDeliveryStep.jsx
A110: delivery_date | B110: string | C110: Delivery | D110: Vehicle Delivery Step | E110: Always | G110: src/modules/loans/components/loan-form/vehicle-delivery/VehicleDeliveryStep.jsx
A111: delivery_dealerAddress | B111: string | C111: Delivery | D111: Vehicle Delivery Step | E111: Always | G111: src/modules/loans/components/loan-form/vehicle-delivery/VehicleDeliveryStep.jsx
A112: delivery_dealerContactNumber | B112: string | C112: Delivery | D112: Vehicle Delivery Step | E112: Always | G112: src/modules/loans/components/loan-form/vehicle-delivery/VehicleDeliveryStep.jsx
A113: delivery_dealerContactPerson | B113: string | C113: Delivery | D113: Vehicle Delivery Step | E113: Always | G113: src/modules/loans/components/loan-form/vehicle-delivery/VehicleDeliveryStep.jsx
A114: delivery_dealerName | B114: string | C114: Delivery | D114: Vehicle Delivery Step | E114: Always | G114: src/modules/loans/components/loan-form/vehicle-delivery/VehicleDeliveryStep.jsx
A115: delivery_invoiceFile | B115: string | C115: Post-File | D115: Loan Form With Steps | E115: Always | G115: src/modules/loans/components/LoanFormWithSteps.jsx; src/modules/loans/components/loan-form/post-file/DocumentsList.jsx
A116: delivery_rcFile | B116: string | C116: Post-File | D116: Loan Form With Steps | E116: Always | G116: src/modules/loans/components/LoanFormWithSteps.jsx; src/modules/loans/components/loan-form/post-file/DocumentsList.jsx
A117: deliveryStatus | B117: string | C117: Shared | D117: Loan Form With Steps | E117: Always | G117: src/modules/loans/components/LoanFormWithSteps.jsx
A118: dependents | B118: number | C118: Profile | D118: Personal Details Simplified | E118: Always | G118: src/modules/loans/components/loan-form/customer-profile/PersonalDetailsSimplified.jsx; src/modules/loans/components/loan-form/pre-file/PersonalDetailsPreFile.jsx
A119: designation | B119: string | C119: Pre-File | D119: Authorised Signatory Section | E119: Always | G119: src/modules/loans/components/loan-form/pre-file/AuthorisedSignatorySection.jsx; src/modules/loans/components/loan-form/pre-file/OccupationalDetailsPreFile.jsx
A120: disburse_bankName | B120: string | C120: Shared | D120: Loan Form With Steps | E120: Always | G120: src/modules/loans/components/LoanFormWithSteps.jsx
... A124: disbursedDate | B124: string | C124: Shared | D124: Disbursement Step | E124: Always | G124: src/modules/loans/components/loan-form/disbursement/DisbursementStep.jsx
A125: disbursement_date | B125: string | C125: Post-File | D125: Loan Sticky Header | E125: Financed flow | F125: Keep aligned with approval_disbursedDate. | G125: src/modules/loans/components/LoanStickyHeader.jsx; src/modules/loans/components/loan-form/post-file/PostFileDispatchAndRecords.jsx; src/modules/loans/components/loan-form/post-file/PrincipalOutstanding.jsx
A126: disbursement_status | B126: string | C126: Payout | D126: Payout Section | E126: Always | G126: src/modules/loans/components/loan-form/payout/PayoutSection.jsx
A127: disbursement_time | B127: string | C127: Post-File | D127: Post File Dispatch And Records | E127: Always | G127: src/modules/loans/components/loan-form/post-file/PostFileDispatchAndRecords.jsx
A128: disbursementDate | B128: string | C128: Shared | D128: Disbursement Step | E128: Always | G128: src/modules/loans/components/loan-form/disbursement/DisbursementStep.jsx
A129: disbursementStatus | B129: string | C129: Shared | D129: Disbursement Step | E129: Always | G129: src/modules/loans/components/loan-form/disbursement/DisbursementStep.jsx
A130: dispatch_date | B130: string | C130: Post-File | D130: Post File Dispatch And Records | E130: Always | G130: src/modules/loans/components/loan-form/post-file/PostFileDispatchAndRecords.jsx
A131: dispatch_through | B131: string | C131: Post-File | D131: Post File Dispatch And Records | E131: Always | G131: src/modules/loans/components/loan-form/post-file/PostFileDispatchAndRecords.jsx
A132: dispatch_time | B132: string | C132: Post-File | D132: Post File Dispatch And Records | E132: Always | G132: src/modules/loans/components/loan-form/post-file/PostFileDispatchAndRecords.jsx
A133: dlDocUrl | B133: string | C133: Post-File | D133: Documents List | E133: Always | G133: src/modules/loans/components/loan-form/post-file/DocumentsList.jsx; src/modules/loans/components/loan-form/post-file/PostFileDocumentManagement.jsx
A134: dob | B134: number | C134: Pre-File | D134: Personal Details Pre File | E134: Always | G134: src/modules/loans/components/loan-form/pre-file/PersonalDetailsPreFile.jsx
A135: docsPreparedBy | B135: string | C135: Pre-File | D135: Section7Record Details | E135: Pre-file/Post-file record details | F135: Map from PRE/POST docs prepared-by chain, not source channel. | G135: src/modules/loans/components/loan-form/pre-file/Section7RecordDetails.jsx
A136: downPayment | B136: string | C136: Header / Shared | D136: Loan Sticky Header | E136: Always | G136: src/modules/loans/components/LoanStickyHeader.jsx
A137: dsaCode | B137: string | C137: Shared | D137: LoanFormWithSteps | E137: Always | G137: /Users/gauravgrover/cdb-frontend/src/modules/loans/components/LoanFormWithSteps.jsx
A138: ecs_accountNumber | B138: number | C138: Post-File | D138: Post File Instrument Details | E138: Always | G138: src/modules/loans/components/loan-form/post-file/PostFileInstrumentDetails.jsx
A139: ecs_amount | B139: number | C139: Post-File | D139: Post File Instrument Details | E139: Always | G139: src/modules/loans/components/loan-form/post-file/PostFileInstrumentDetails.jsx
A140: ecs_bankName | B140: number | C140: Post-File | D140: Post File Instrument Details | E140: Always | G140: src/modules/loans/components/loan-form/post-file/PostFileInstrumentDetails.jsx
A141: ecs_date | B141: number | C141: Post-File | D141: Post File Instrument Details | E141: Always | G141: src/modules/loans/components/loan-form/post-file/PostFileInstrumentDetails.jsx
A142: ecs_favouring | B142: string | C142: Post-File | D142: Post File Instrument Details | E142: Always | G142: src/modules/loans/components/loan-form/post-file/PostFileInstrumentDetails.jsx
A143: ecs_image | B143: string | C143: Post-File | D143: Post File Instrument Details | E143: Always | G143: src/modules/loans/components/loan-form/post-file/PostFileInstrumentDetails.jsx
A144: ecs_micrCode | B144: number | C144: Post-File | D144: Post File Instrument Details | E144: Always | G144: src/modules/loans/components/loan-form/post-file/PostFileInstrumentDetails.jsx
A145: ecs_signedBy | B145: string | C145: Post-File | D145: Post File Instrument Details | E145: Always | G145: src/modules/loans/components/loan-form/post-file/PostFileInstrumentDetails.jsx
A146: ecs_tag | B146: string | C146: Post-File | D146: Post File Instrument Details | E146: Always | G146: src/modules/loans/components/loan-form/post-file/PostFileInstrumentDetails.jsx
A147: education | B147: string | C147: Pre-File | D147: Personal Details Pre File | E147: Always | G147: src/modules/loans/components/loan-form/pre-file/PersonalDetailsPreFile.jsx
... A218: invoice_received_from | B218: string | C218: Delivery | D218: Vehicle Delivery Step | E218: Always | G218: src/modules/loans/components/loan-form/vehicle-delivery/VehicleDeliveryStep.jsx
A219: isFinanced | B219: string | C219: Profile | D219: Loan Form With Steps | E219: Always | F219: If No => cash flow (Profile + Delivery only). If Yes => Pre-File/Approval/Post-File/Delivery/Payout flow. | G219: src/modules/loans/components/LoanFormWithSteps.jsx; src/modules/loans/components/loan-form/customer-profile/FinanceDetailsForm.jsx; src/modules/loans/components/loan-form/customer-profile/VehicleDetailsForm.jsx; src/modules/loans/components/loan-form/pre-file/PreFileStep.jsx; src/modules/loans/components/loan-form/vehicle-delivery/VehicleDeliveryStep.jsx
A220: isMSME | B220: string | C220: Profile | D220: Lead Details | E220: Always | G220: src/modules/loans/components/loan-form/customer-profile/LeadDetails.jsx; src/modules/loans/components/loan-form/pre-file/OccupationalDetailsPreFile.jsx
A221: isMultipleCars | B221: string | C221: Pre-File | D221: Bulk Loan Creation Section | E221: Always | G221: src/modules/loans/components/loan-form/pre-file/BulkLoanCreationSection.jsx
A222: isSameVehicle | B222: string | C222: Pre-File | D222: Bulk Loan Creation Section | E222: Always | G222: src/modules/loans/components/loan-form/pre-file/BulkLoanCreationSection.jsx
A223: leadDate | B223: string | C223: Profile | D223: Lead Details | E223: Always | G223: src/modules/loans/components/loan-form/customer-profile/LeadDetails.jsx
A224: leadTime | B224: string | C224: Profile | D224: Lead Details | E224: Always | G224: src/modules/loans/components/loan-form/customer-profile/LeadDetails.jsx
A225: loan_notes | B225: string | C225: Shared | D225: Loan Form With Steps | E225: Always | G225: src/modules/loans/components/LoanFormWithSteps.jsx; src/modules/loans/components/NotesModal.jsx
A226: loan_number | B226: string | C226: Post-File | D226: PostFileDispatchAndRecords | E226: Always | G226: /Users/gauravgrover/cdb-frontend/src/modules/loans/components/loan-form/post-file/PostFileDispatchAndRecords.jsx; /Users/gauravgrover/cdb-frontend/src/modules/loans/components/LoanFormWithSteps.jsx
...

Sheet LegacyCatalog
A1: legacy_file | B1: legacy_field
A2: AUTH_SIGNATORY.json | B2: ACCOUNT_NUMBER_TYPE
A3: AUTH_SIGNATORY.json | B3: ADD1
A4: AUTH_SIGNATORY.json | B4: ADD2
A5: AUTH_SIGNATORY.json | B5: AUTH_AADHAAR_NUMBER
A6: AUTH_SIGNATORY.json | B6: CITY
A7: AUTH_SIGNATORY.json | B7: CPV_ACCOUNT_NO
A8: AUTH_SIGNATORY.json | B8: DATA_LOCATION_CODE
A9: AUTH_SIGNATORY.json | B9: DATE_OF_BIRTH
A10: AUTH_SIGNATORY.json | B10: DESIGNATION
A11: AUTH_SIGNATORY.json | B11: FAX
A12: AUTH_SIGNATORY.json | B12: HP_GROUP
... A409: RC_SOURCE_REFERENCE.json | B409: TEMP_CUST_CODE

Sheet DropdownData
A1: legacy_files | B1: AUTH_SIGNATORY.json | C1: CPV_DETAIL.json | D1: CUSTOMER_BANK.json | E1: GURANTOR.json | F1: RC_CUSTOMER_ACCOUNT.json | G1: RC_DOC_DESPATCH_MASTER.json | H1: RC_INSTRUMENT_DETAIL.json | I1: RC_RC_INV_RECEIVING_DETAIL.json | J1: RC_RC_INV_STATUS.json | K1: RC_SOURCE_REFERENCE.json
A2: AUTH_SIGNATORY.json | B2: ACCOUNT_NUMBER_TYPE | C2: AADHAAR_NUMBER | D2: ACCOUNT_NUMBER_TYPE | E2: ACCOUNT_NUMBER_TYPE | F2: ACCOUNT_STATUS | G2: DATA_LOCATION_CODE | H2: ACCOUNT_NUMBER | I2: CHASIS_NUMBER | J2: AGEING_FOR_BANK | K2: DATA_LOCATION_CODE
A3: CPV_DETAIL.json | B3: ADD1 | C3: ACCOUNT_NUMBER_TYPE | D3: BANK_ADDRESS | E3: ANNUAL_INCOME | F3: ADDRESS_FOR_REGISTER | G3: DATE_OF_DESP | H3: DATA_LOCATION_CODE | I3: DATA_LOCATION_CODE | J3: AGEING_FOR_US | K3: HP_GROUP
A4: CUSTOMER_BANK.json | B4: ADD2 | C4: ANNUAL_INCOME | D4: BANK_FAX | E4: CPV_ACCOUNT_NO | F4: ADDRESS_PROOF_FOR_REGISTRATION | G4: DESP_THROUGH | H4: DRAWN_ON | I4: DATE_OF_REGISTRATION | J4: CASE_TYPE_CODE | K4: PHONE_NUMBER
A5: GURANTOR.json | B5: AUTH_AADHAAR_NUMBER | C5: CAR_MODEL | D5: BANK_NAME | E5: DATA_LOCATION_CODE | F5: AGEING_FOR_BANK | G5: DESPATCH_ID | H5: ENTERED_BY | I5: DISPLACEMENT | J5: CHASIS_NUMBER | K5: REFERENCE_BY
A6: RC_CUSTOMER_ACCOUNT.json | B6: CITY | C6: CATEGORY | D6: BANK_PHONE | E6: DATE_OF_BIRTH | F6: AGEING_FOR_US | G6: DOC_DESP_AS | H6: ENTERED_ON_DATE | I6: ENGINE_NUMBER | J6: DATA_LOCATION_CODE | K6: TEMP_CUST_CODE
A7: RC_DOC_DESPATCH_MASTER.json | B7: CPV_ACCOUNT_NO | C7: CDB_ACCOUNT_NO | D7: CA_ACCOUNT_NO | E7: EDUCATION | F7: APPLIED_EMI | G7: DOCS_COLLECTED_BY | H7: HP_GROUP | I7: INV_RECEIVED_AS | J7: DATE_OF_DELIVERY
A8: RC_INSTRUMENT_DETAIL.json | B8: DATA_LOCATION_CODE | C8: CLS_REMARKS | D8: CPV_ACCOUNT_NO | E8: G_AADHAAR_NUMBER | F8: APPLIED_EMI_DUE_DATE | G8: DOCS_PREPARED_BY | H8: INSTRMNT_AMOUNT | I8: INV_RECEIVED_FROM | J8: DATE_OF_DISBURSE
A9: RC_RC_INV_RECEIVING_DETAIL.json | B9: DATE_OF_BIRTH | C9: CLS_STATUS | D9: DATA_LOCATION_CODE | E9: G_ICICI_ENTRY_NUMBER | F9: APPLIED_LOAN_AMOUNT | G9: TEMP_CUST_CODE | H9: INSTRMNT_BY_BORWR_GRNTR | I9: INV_RECEIVED_ON_DATE | J9: DATE_OF_REGISTRATION
A10: RC_RC_INV_STATUS.json | B10: DESIGNATION | C10: CPV_ACCOUNT_NO | D10: HP_GROUP | E10: HP_GROUP | F10: APPLIED_ROI | G10: TIME_OF_DESP | H10: INSTRMNT_DATE | I10: INVOICE_DATE | J10: ENGINE_NUMBER
A11: RC_SOURCE_REFERENCE.json | B11: FAX | C11: CPV_DATE | D11: OD_LIMIT | E11: MARITAL_STATUS | F11: APPLIED_TENOR | H11: INSTRMNT_FAVOURING | I11: INVOICE_NUMBER | J11: HP_GROUP
B12: HP_GROUP | C12: CPV_G_OFF_STATUS | D12: ORIGINAL_HP_GROUP | E12: MOBILE | F12: BANK_FILE_NUMBER | H12: INSTRMNT_NO | I12: LIEN_MARK | J12: INV_STATUS
B13: MOBILE | C13: CPV_G_RES_STATUS | D13: SB_ACCOUNT_NO | E13: NAME | F13: BORROWER_CATEGORY | H13: INSTRMNT_RECPT_ID_NO | I13: NO_OF_CYLINDERS | J13: INVOICE_DATE
B14: NAME | C14: CPV_MONTH_YEAR | E14: NO_OF_DEPEND | F14: BORROWER_RELATION | H14: INSTRMNT_TYPE | I14: ON_DATE | J14: INVOICE_NUMBER
B15: ORIGINAL_HP_GROUP | C15: CPV_OFF_STATUS | E15: OFF_ADD1 | F15: CASE_FOR_YEAR_MONTH | H15: LAST_UPDATE_ON_DATE | I15: RC_RECEIVED_AS | J15: IS_RC_DESPATCH_TO_BANK
B16: PHONE | C16: CPV_RES_STATUS | E16: OFF_ADD2 | F16: CASE_ORIGIN | H16: LAST_UPDATED_BY_USER | I16: RC_RECEIVED_FROM | J16: IS_VEHICLE_DELIVERED
B17: PIN | C17: CPV_SEND_AT_TIME | E17: OFF_CITY | F17: CASE_TYPE | H17: MICR_CODE | I17: RC_RECEIVED_ON_DATE | J17: LIEN_MARK
C18: CPV_SEND_ON_DATE | E18: OFF_FAX | F18: CASE_TYPE_CODE | H18: STATUS | I18: RECEIVING_NO | J18: MAKE_MODEL
C19: CREATED_BY_USER | E19: OFF_NAME | F19: CHANNEL_CODE | H19: STATUS_BY_USER | I19: REGD_NUMBER | J19: MANUFACTURER_CODE
C20: CREATED_ON_DATE | E20: OFF_PHONE | F20: CHASIS_NUMBER | H20: STATUS_ON_DATE | I20: SEATING_CAPACITY | J20: MFG_YEAR
C21: CREATED_ON_TIME | E21: OFF_PIN | F21: CLOSED_BY | H21: TEMP_CUST_CODE | I21: TEMP_CUST_CODE | J21: MODEL_CODE
C22: CUST_NAME_FIRST | E22: ORIGINAL_HP_GROUP | F22: CLOSEDBY_CODE | I22: UNLAIDEN_WEIGHT | J22: ORIGINAL_HP_GROUP
C23: CUST_NAME_LAST | E23: PROFESSION_TYPE | F23: CPV_ACCOUNT_NO | I23: USER_NAME | J23: OVERALL_STATUS
C24: CUST_NAME_MIDDLE | E24: RESI_ADD1 | F24: CPV_ACCOUNT_NUMBER_TYPE | J24: RC_STATUS
C25: CUSTOMER_NAME | E25: RESI_ADD2 | F25: CUST_CODE | J25: RC_STORAGE_NUMBER
C26: DATA_LOCATION_CODE | E26: RESI_CITY | F26: CUST_NAME | J26: REGD_NUMBER
C27: DATA_STATUS | E27: RESI_PHONE | F27: DATA_LOCATION_CODE | J27: TEMP_CUST_CODE
C28: DATE_OF_BIRTH | E28: RESI_PIN | F28: DATE_OF_APPROVAL_STATUS_TAKEN | J28: VARIANT_CODE
C29: DEALT_BY | E29: RESIDENCE_TYPE | F29: DATE_OF_DELIVERY
C30: DRIVING_LICENSE | E30: SEX | F30: DATE_OF_DESPATCH_FOR_APPROVAL
C31: E_MAIL | E31: VEHICLE_HAVE | F31: DATE_OF_DISBURSE
C32: EDUCATION | E32: VEHICLE_OWNERSHIP | F32: DATE_OF_FILE_DESPATCH
C33: EMAIL_ADDRESS | E33: YEARS_AT_PROFESSION | F33: DATE_WHEN_FILE_DESPATCH
C34: FATHERS_NAME_FIRST | E34: YEARS_AT_RESIDENCE | F34: DATE_WHEN_FILE_IN_BOOKING
C35: FATHERS_NAME_LAST | F35: DATE_WHEN_FILE_MOVED_TO_BANK
C36: FATHERS_NAME_MIDDLE | F36: DATE_WHEN_FILE_REACHED_AT_CPA
C37: FINANCER | F37: DATE_WHEN_FILE_RECEIVED
C38: GURANTOR_AVAILABLE | F38: DATE_WHEN_FILE_REJECT_WITHDRWN
C39: HEAD_NAME | F39: DEALER_CODE
C40: HIRE_TYPE | F40: DEALER_SUBVENTION
C41: HP_GROUP | F41: DEALT_BY
C42: HUSBAND_NAME | F42: DEALTBY_CODE
C43: ICICI_ENTRY_NUMBER | F43: DELIQUENCY_IN_BUCKET
C44: INDUSTRY_DETAIL | F44: DELIQUENCY_STATUS_GIVE_ON_DATE
C45: IS_REQ_G_OFF_VERIFICATION | F45: DELIQUENTY_STATUS_GIVE_BY
C46: IS_REQ_G_RES_VERIFICATION | F46: DELIVERED_MAKE_MODEL
... C105: YEARS_AT_RESIDENCE | F105: LOAN_RECEIVED_AMOUNT
F106: MAKE_MODEL
F107: MANUFACTURER_CODE
F108: MFG_YEAR
F109: MOBILE_NUMBER
F110: MODEL_CODE
F111: ORIGIN_CODE
F112: ORIGINAL_HP_GROUP
F113: OVERALL_STATUS
F114: PAYMENT_FAVOURING_AT_BOOKING
F115: PAYMENT_FAVOURING_AT_DESPATCH
F116: PAYOUT_RATE
F117: PERSON_WHO_DELIVERED_THE_CAR
... F161: VERIFIED_FILE_RECEIVED

Sheet Instructions
A1: How to use this workbook
A3: 1. Open sheet 'MappingEditor'.
A4: 2. Columns 'applies_when' and 'flow_notes' explain conditional flow dependencies.
A5: 3. Each row is one mapping rule. Duplicate rows to add fallbacks for the same new_field.
A6: 4. Select 'legacy_file' from dropdown first, then 'legacy_field' from dependent dropdown.
A7: 5. Use fallback_priority: 1 (highest), 2, 3 ...
A8: 6. Set transform (identity, normalize_yes_no, to_date, to_number, concat, custom).
A9: 7. Set active = Y/N.
A10: 8. Important: keep Source vs Dealt By separate (sourceName <- SOURCE-like, dealtBy <- DEALT_BY-like).
A11: 9. Save workbook and run parser script to generate JSON mapping config.
A13: Parser command:
A14: python3 scripts/parse_mapping_workbook.py --workbook migration_analysis/loan_field_mapping_workbook.xlsx --out migration_analysis/loan_field_mapping_config.json
... A19: Workbook generated for case: 3000004231

Sheet UnmappedNewFields
A1: new_field | B1: new_page | C1: new_section | D1: status
A2: aadhaarCardDocUrl | B2: Post-File | C2: Documents List | D2: =IF((COUNTIFS(MappingEditor!$A:$A,$A2,MappingEditor!$J:$J,"Y")+COUNTIFS(FallbackEditor!$A:$A,$A2,FallbackEditor!$J:$J,"Y"))>0,"mapped","unmapped") -> mapped
A3: aadhaarNumber | B3: Header / Shared | C3: Loan Sticky Header | D3: =IF((COUNTIFS(MappingEditor!$A:$A,$A3,MappingEditor!$J:$J,"Y")+COUNTIFS(FallbackEditor!$A:$A,$A3,FallbackEditor!$J:$J,"Y"))>0,"mapped","unmapped") -> mapped
A4: accessoriesAmount | B4: Pre-File | C4: Post File Vehicle Verification | D4: =IF((COUNTIFS(MappingEditor!$A:$A,$A4,MappingEditor!$J:$J,"Y")+COUNTIFS(FallbackEditor!$A:$A,$A4,FallbackEditor!$J:$J,"Y"))>0,"mapped","unmapped") -> mapped
A5: accountNumber | B5: Pre-File | C5: Post File Dispatch And Records | D5: =IF((COUNTIFS(MappingEditor!$A:$A,$A5,MappingEditor!$J:$J,"Y")+COUNTIFS(FallbackEditor!$A:$A,$A5,FallbackEditor!$J:$J,"Y"))>0,"mapped","unmapped") -> mapped
A6: accountSinceYears | B6: Pre-File | C6: Income Banking Details Pre File | D6: =IF((COUNTIFS(MappingEditor!$A:$A,$A6,MappingEditor!$J:$J,"Y")+COUNTIFS(FallbackEditor!$A:$A,$A6,FallbackEditor!$J:$J,"Y"))>0,"mapped","unmapped") -> mapped
A7: accountType | B7: Pre-File | C7: Income Banking Details Pre File | D7: =IF((COUNTIFS(MappingEditor!$A:$A,$A7,MappingEditor!$J:$J,"Y")+COUNTIFS(FallbackEditor!$A:$A,$A7,FallbackEditor!$J:$J,"Y"))>0,"mapped","unmapped") -> mapped
A8: addressProofDocUrl | B8: Post-File | C8: Documents List | D8: =IF((COUNTIFS(MappingEditor!$A:$A,$A8,MappingEditor!$J:$J,"Y")+COUNTIFS(FallbackEditor!$A:$A,$A8,FallbackEditor!$J:$J,"Y"))>0,"mapped","unmapped") -> mapped
A9: addressProofNumber | B9: Pre-File | C9: Personal Details Pre File | D9: =IF((COUNTIFS(MappingEditor!$A:$A,$A9,MappingEditor!$J:$J,"Y")+COUNTIFS(FallbackEditor!$A:$A,$A9,FallbackEditor!$J:$J,"Y"))>0,"mapped","unmapped") -> mapped
A10: addressProofType | B10: Pre-File | C10: Personal Details Pre File | D10: =IF((COUNTIFS(MappingEditor!$A:$A,$A10,MappingEditor!$J:$J,"Y")+COUNTIFS(FallbackEditor!$A:$A,$A10,FallbackEditor!$J:$J,"Y"))>0,"mapped","unmapped") -> mapped
A11: addressType | B11: Pre-File | C11: Personal Details Pre File | D11: =IF((COUNTIFS(MappingEditor!$A:$A,$A11,MappingEditor!$J:$J,"Y")+COUNTIFS(FallbackEditor!$A:$A,$A11,FallbackEditor!$J:$J,"Y"))>0,"mapped","unmapped") -> mapped
A12: advanceEmi | B12: Pre-File | C12: Vehicle Pricing Loan Details | D12: =IF((COUNTIFS(MappingEditor!$A:$A,$A12,MappingEditor!$J:$J,"Y")+COUNTIFS(FallbackEditor!$A:$A,$A12,FallbackEditor!$J:$J,"Y"))>0,"mapped","unmapped") -> mapped
A13: applicantType | B13: Profile | C13: Lead Details | D13: =IF((COUNTIFS(MappingEditor!$A:$A,$A13,MappingEditor!$J:$J,"Y")+COUNTIFS(FallbackEditor!$A:$A,$A13,FallbackEditor!$J:$J,"Y"))>0,"mapped","unmapped") -> mapped
... A357: yearsInCurrentHouse | B357: Profile | C357: Personal Details Simplified | D357: =IF((COUNTIFS(MappingEditor!$A:$A,$A357,MappingEditor!$J:$J,"Y")+COUNTIFS(FallbackEditor!$A:$A,$A357,FallbackEditor!$J:$J,"Y"))>0,"mapped","unmapped") -> mapped

Sheet UnmappedLegacyFields
A1: legacy_file | B1: legacy_field | C1: status
A2: AUTH_SIGNATORY.json | B2: ACCOUNT_NUMBER_TYPE | C2: =IF((COUNTIFS(MappingEditor!$F:$F,$A2,MappingEditor!$G:$G,$B2,MappingEditor!$J:$J,"Y")+COUNTIFS(FallbackEditor!$G:$G,$A2,FallbackEditor!$H:$H,$B2,FallbackEditor!$J:$J,"Y"))>0,"mapped","unmapped") -> unmapped
A3: AUTH_SIGNATORY.json | B3: ADD1 | C3: =IF((COUNTIFS(MappingEditor!$F:$F,$A3,MappingEditor!$G:$G,$B3,MappingEditor!$J:$J,"Y")+COUNTIFS(FallbackEditor!$G:$G,$A3,FallbackEditor!$H:$H,$B3,FallbackEditor!$J:$J,"Y"))>0,"mapped","unmapped") -> unmapped
A4: AUTH_SIGNATORY.json | B4: ADD2 | C4: =IF((COUNTIFS(MappingEditor!$F:$F,$A4,MappingEditor!$G:$G,$B4,MappingEditor!$J:$J,"Y")+COUNTIFS(FallbackEditor!$G:$G,$A4,FallbackEditor!$H:$H,$B4,FallbackEditor!$J:$J,"Y"))>0,"mapped","unmapped") -> unmapped
A5: AUTH_SIGNATORY.json | B5: AUTH_AADHAAR_NUMBER | C5: =IF((COUNTIFS(MappingEditor!$F:$F,$A5,MappingEditor!$G:$G,$B5,MappingEditor!$J:$J,"Y")+COUNTIFS(FallbackEditor!$G:$G,$A5,FallbackEditor!$H:$H,$B5,FallbackEditor!$J:$J,"Y"))>0,"mapped","unmapped") -> mapped
A6: AUTH_SIGNATORY.json | B6: CITY | C6: =IF((COUNTIFS(MappingEditor!$F:$F,$A6,MappingEditor!$G:$G,$B6,MappingEditor!$J:$J,"Y")+COUNTIFS(FallbackEditor!$G:$G,$A6,FallbackEditor!$H:$H,$B6,FallbackEditor!$J:$J,"Y"))>0,"mapped","unmapped") -> unmapped
A7: AUTH_SIGNATORY.json | B7: CPV_ACCOUNT_NO | C7: =IF((COUNTIFS(MappingEditor!$F:$F,$A7,MappingEditor!$G:$G,$B7,MappingEditor!$J:$J,"Y")+COUNTIFS(FallbackEditor!$G:$G,$A7,FallbackEditor!$H:$H,$B7,FallbackEditor!$J:$J,"Y"))>0,"mapped","unmapped") -> unmapped
A8: AUTH_SIGNATORY.json | B8: DATA_LOCATION_CODE | C8: =IF((COUNTIFS(MappingEditor!$F:$F,$A8,MappingEditor!$G:$G,$B8,MappingEditor!$J:$J,"Y")+COUNTIFS(FallbackEditor!$G:$G,$A8,FallbackEditor!$H:$H,$B8,FallbackEditor!$J:$J,"Y"))>0,"mapped","unmapped") -> unmapped
A9: AUTH_SIGNATORY.json | B9: DATE_OF_BIRTH | C9: =IF((COUNTIFS(MappingEditor!$F:$F,$A9,MappingEditor!$G:$G,$B9,MappingEditor!$J:$J,"Y")+COUNTIFS(FallbackEditor!$G:$G,$A9,FallbackEditor!$H:$H,$B9,FallbackEditor!$J:$J,"Y"))>0,"mapped","unmapped") -> unmapped
A10: AUTH_SIGNATORY.json | B10: DESIGNATION | C10: =IF((COUNTIFS(MappingEditor!$F:$F,$A10,MappingEditor!$G:$G,$B10,MappingEditor!$J:$J,"Y")+COUNTIFS(FallbackEditor!$G:$G,$A10,FallbackEditor!$H:$H,$B10,FallbackEditor!$J:$J,"Y"))>0,"mapped","unmapped") -> unmapped
A11: AUTH_SIGNATORY.json | B11: FAX | C11: =IF((COUNTIFS(MappingEditor!$F:$F,$A11,MappingEditor!$G:$G,$B11,MappingEditor!$J:$J,"Y")+COUNTIFS(FallbackEditor!$G:$G,$A11,FallbackEditor!$H:$H,$B11,FallbackEditor!$J:$J,"Y"))>0,"mapped","unmapped") -> unmapped
A12: AUTH_SIGNATORY.json | B12: HP_GROUP | C12: =IF((COUNTIFS(MappingEditor!$F:$F,$A12,MappingEditor!$G:$G,$B12,MappingEditor!$J:$J,"Y")+COUNTIFS(FallbackEditor!$G:$G,$A12,FallbackEditor!$H:$H,$B12,FallbackEditor!$J:$J,"Y"))>0,"mapped","unmapped") -> unmapped
A13: AUTH_SIGNATORY.json | B13: MOBILE | C13: =IF((COUNTIFS(MappingEditor!$F:$F,$A13,MappingEditor!$G:$G,$B13,MappingEditor!$J:$J,"Y")+COUNTIFS(FallbackEditor!$G:$G,$A13,FallbackEditor!$H:$H,$B13,FallbackEditor!$J:$J,"Y"))>0,"mapped","unmapped") -> unmapped
... A409: RC_SOURCE_REFERENCE.json | B409: TEMP_CUST_CODE | C409: =IF((COUNTIFS(MappingEditor!$F:$F,$A409,MappingEditor!$G:$G,$B409,MappingEditor!$J:$J,"Y")+COUNTIFS(FallbackEditor!$G:$G,$A409,FallbackEditor!$H:$H,$B409,FallbackEditor!$J:$J,"Y"))>0,"mapped","unmapped") -> unmapped

Sheet FallbackEditor
A1: new_field | B1: new_page | C1: new_section | D1: applies_when | E1: flow_notes | F1: fallback_priority | G1: legacy_file | H1: legacy_field | I1: transform | J1: active | K1: notes | L1: case_value_preview
A2: accountNumber | B2: Pre-File | C2: Post File Dispatch And Records | D2: Always | F2: 1 | G2: CUSTOMER_BANK.json | H2: CA_ACCOUNT_NO | I2: identity | J2: Y | K2: clean | L2: =IFERROR(_xludf.XLOOKUP($G2&"."&$H2,CaseSource!$A$2:$A$371,CaseSource!$B$2:$B$371,""),"")
A3: accountNumber | B3: Pre-File | C3: Post File Dispatch And Records | D3: Always | F3: 2 | G3: CUSTOMER_BANK.json | H3: SB_ACCOUNT_NO | I3: identity | J3: Y | K3: clean | L3: =IFERROR(_xludf.XLOOKUP($G3&"."&$H3,CaseSource!$A$2:$A$371,CaseSource!$B$2:$B$371,""),"")
A4: addressProofNumber | B4: Pre-File | C4: Personal Details Pre File | D4: Always | F4: 1 | G4: CPV_DETAIL.json | H4: AADHAAR_NUMBER | I4: identity | J4: Y | K4: clean | L4: =IFERROR(_xludf.XLOOKUP($G4&"."&$H4,CaseSource!$A$2:$A$371,CaseSource!$B$2:$B$371,""),"")
A5: applicantType | B5: Profile | C5: Lead Details | D5: Always | E5: Individual vs Company changes form visibility and required sections. | F5: 1 | G5: CPV_DETAIL.json | H5: HIRE_TYPE | I5: identity | J5: Y | K5: `normalizeApplicantType(...)` => `Individual`/`Company`. | L5: =IFERROR(_xludf.XLOOKUP($G5&"."&$H5,CaseSource!$A$2:$A$371,CaseSource!$B$2:$B$371,""),"")
A6: approval_approvalDate | B6: Approval | C6: Loan Form With Steps | D6: Financed flow | E6: For legacy migration, use disbursement date when explicit approval date is absent. | F6: 1 | G6: RC_CUSTOMER_ACCOUNT.json | H6: DATE_OF_DISBURSE | I6: identity | J6: Y | K6: ISO | L6: =IFERROR(_xludf.XLOOKUP($G6&"."&$H6,CaseSource!$A$2:$A$371,CaseSource!$B$2:$B$371,""),"")
A7: approval_approvalDate | B7: Approval | C7: Loan Form With Steps | D7: Financed flow | E7: For legacy migration, use disbursement date when explicit approval date is absent. | F7: 2 | G7: RC_RC_INV_STATUS.json | H7: DATE_OF_DISBURSE | I7: identity | J7: Y | K7: ISO | L7: =IFERROR(_xludf.XLOOKUP($G7&"."&$H7,CaseSource!$A$2:$A$371,CaseSource!$B$2:$B$371,""),"")
A8: approval_approvalDate | B8: Approval | C8: Loan Form With Steps | D8: Financed flow | E8: For legacy migration, use disbursement date when explicit approval date is absent. | F8: 3 | G8: RC_CUSTOMER_ACCOUNT.json | H8: DATE_OF_FILE_DESPATCH | I8: identity | J8: Y | K8: ISO | L8: =IFERROR(_xludf.XLOOKUP($G8&"."&$H8,CaseSource!$A$2:$A$371,CaseSource!$B$2:$B$371,""),"")
A9: approval_approvalDate | B9: Approval | C9: Loan Form With Steps | D9: Financed flow | E9: For legacy migration, use disbursement date when explicit approval date is absent. | F9: 4 | G9: CPV_DETAIL.json | H9: CPV_DATE | I9: identity | J9: Y | K9: ISO | L9: =IFERROR(_xludf.XLOOKUP($G9&"."&$H9,CaseSource!$A$2:$A$371,CaseSource!$B$2:$B$371,""),"")
A10: approval_bankName` / `postfile_bankName | D10: Always | F10: 1 | G10: RC_CUSTOMER_ACCOUNT.json | H10: HP_TO | I10: identity | J10: Y | K10: bank normalization | L10: =IFERROR(_xludf.XLOOKUP($G10&"."&$H10,CaseSource!$A$2:$A$371,CaseSource!$B$2:$B$371,""),"")
A11: approval_bankName` / `postfile_bankName | D11: Always | F11: 2 | G11: CPV_DETAIL.json | H11: FINANCER | I11: identity | J11: Y | K11: bank normalization | L11: =IFERROR(_xludf.XLOOKUP($G11&"."&$H11,CaseSource!$A$2:$A$371,CaseSource!$B$2:$B$371,""),"")
A12: approval_disbursedDate` / `disbursement_date | D12: Always | F12: 1 | G12: RC_CUSTOMER_ACCOUNT.json | H12: DATE_OF_DISBURSE | I12: identity | J12: Y | K12: date | L12: =IFERROR(_xludf.XLOOKUP($G12&"."&$H12,CaseSource!$A$2:$A$371,CaseSource!$B$2:$B$371,""),"")
A13: approval_disbursedDate` / `disbursement_date | D13: Always | F13: 2 | G13: RC_RC_INV_STATUS.json | H13: DATE_OF_DISBURSE | I13: identity | J13: Y | K13: date | L13: =IFERROR(_xludf.XLOOKUP($G13&"."&$H13,CaseSource!$A$2:$A$371,CaseSource!$B$2:$B$371,""),"")
A14: approval_loanAmountApproved` / `postfile_loanAmountApproved | D14: Always | F14: 1 | G14: RC_CUSTOMER_ACCOUNT.json | H14: LOAN_AMOUNT | I14: identity | J14: Y | K14: numeric | L14: =IFERROR(_xludf.XLOOKUP($G14&"."&$H14,CaseSource!$A$2:$A$371,CaseSource!$B$2:$B$371,""),"")
A15: approval_loanAmountApproved` / `postfile_loanAmountApproved | D15: Always | F15: 2 | G15: CPV_DETAIL.json | H15: LOAN_EXPECTED | I15: identity | J15: Y | K15: numeric | L15: =IFERROR(_xludf.XLOOKUP($G15&"."&$H15,CaseSource!$A$2:$A$371,CaseSource!$B$2:$B$371,""),"")
A16: approval_roi` / `postfile_roi | D16: Always | F16: 1 | G16: RC_CUSTOMER_ACCOUNT.json | H16: ROI | I16: identity | J16: Y | K16: numeric | L16: =IFERROR(_xludf.XLOOKUP($G16&"."&$H16,CaseSource!$A$2:$A$371,CaseSource!$B$2:$B$371,""),"")
A17: approval_tenureMonths` / `postfile_tenureMonths | D17: Always | F17: 1 | G17: RC_CUSTOMER_ACCOUNT.json | H17: TENOR | I17: identity | J17: Y | K17: numeric | L17: =IFERROR(_xludf.XLOOKUP($G17&"."&$H17,CaseSource!$A$2:$A$371,CaseSource!$B$2:$B$371,""),"")
A18: approval_tenureMonths` / `postfile_tenureMonths | D18: Always | F18: 2 | G18: CPV_DETAIL.json | H18: TENDOR | I18: identity | J18: Y | K18: numeric | L18: =IFERROR(_xludf.XLOOKUP($G18&"."&$H18,CaseSource!$A$2:$A$371,CaseSource!$B$2:$B$371,""),"")
A19: bankName | B19: Pre-File | C19: Loan Form With Steps | D19: Always | F19: 1 | G19: CUSTOMER_BANK.json | H19: BANK_NAME | I19: identity | J19: Y | K19: normalized bank name | L19: =IFERROR(_xludf.XLOOKUP($G19&"."&$H19,CaseSource!$A$2:$A$371,CaseSource!$B$2:$B$371,""),"")
A20: boughtInYear | B20: Pre-File | C20: Post File Vehicle Verification | D20: Always | F20: 1 | G20: RC_CUSTOMER_ACCOUNT.json | H20: BOUGHT_IN_YEAR | I20: identity | J20: Y | K20: parse 4-digit/2-digit year normalization | L20: =IFERROR(_xludf.XLOOKUP($G20&"."&$H20,CaseSource!$A$2:$A$371,CaseSource!$B$2:$B$371,""),"")
A21: boughtInYear | B21: Pre-File | C21: Post File Vehicle Verification | D21: Always | F21: 2 | G21: RC_CUSTOMER_ACCOUNT.json | H21: VEHICLE_YEAR | I21: identity | J21: Y | K21: parse 4-digit/2-digit year normalization | L21: =IFERROR(_xludf.XLOOKUP($G21&"."&$H21,CaseSource!$A$2:$A$371,CaseSource!$B$2:$B$371,""),"")
A22: boughtInYear | B22: Pre-File | C22: Post File Vehicle Verification | D22: Always | F22: 3 | G22: CPV_DETAIL.json | H22: BOUGHT_IN_YEAR | I22: identity | J22: Y | K22: parse 4-digit/2-digit year normalization | L22: =IFERROR(_xludf.XLOOKUP($G22&"."&$H22,CaseSource!$A$2:$A$371,CaseSource!$B$2:$B$371,""),"")
A23: branch | B23: Pre-File | C23: Post File Dispatch And Records | D23: Always | F23: 1 | G23: CUSTOMER_BANK.json | H23: BANK_ADDRESS | I23: identity | J23: Y | K23: clean | L23: =IFERROR(_xludf.XLOOKUP($G23&"."&$H23,CaseSource!$A$2:$A$371,CaseSource!$B$2:$B$371,""),"")
A24: businessNature | B24: Pre-File | C24: Occupational Details Pre File | D24: Always | F24: 1 | G24: CPV_DETAIL.json | H24: ORGANISATION_TYPE | I24: identity | J24: Y | K24: multi-value combined | L24: =IFERROR(_xludf.XLOOKUP($G24&"."&$H24,CaseSource!$A$2:$A$371,CaseSource!$B$2:$B$371,""),"")
A25: city | B25: Pre-File | C25: Loan Sticky Header | D25: Always | F25: 1 | G25: CPV_DETAIL.json | H25: OFF_CITY | I25: identity | J25: Y | K25: clean | L25: =IFERROR(_xludf.XLOOKUP($G25&"."&$H25,CaseSource!$A$2:$A$371,CaseSource!$B$2:$B$371,""),"")
A26: city | B26: Pre-File | C26: Loan Sticky Header | D26: Always | F26: 2 | G26: CPV_DETAIL.json | H26: RESI_CITY | I26: identity | J26: Y | K26: clean | L26: =IFERROR(_xludf.XLOOKUP($G26&"."&$H26,CaseSource!$A$2:$A$371,CaseSource!$B$2:$B$371,""),"")
A27: co_aadhaar | B27: Pre-File | C27: Co Applicant Section | D27: Always | F27: 1 | G27: AUTH_SIGNATORY.json | H27: AUTH_AADHAAR_NUMBER | I27: identity | J27: Y | K27: clean | L27: =IFERROR(_xludf.XLOOKUP($G27&"."&$H27,CaseSource!$A$2:$A$371,CaseSource!$B$2:$B$371,""),"")
A28: co_aadhaar | B28: Pre-File | C28: Co Applicant Section | D28: Always | F28: 2 | G28: GURANTOR.json | H28: G_AADHAAR_NUMBER | I28: identity | J28: Y | K28: clean | L28: =IFERROR(_xludf.XLOOKUP($G28&"."&$H28,CaseSource!$A$2:$A$371,CaseSource!$B$2:$B$371,""),"")
A29: co_aadhaar | B29: Pre-File | C29: Co Applicant Section | D29: Always | F29: 3 | G29: CPV_DETAIL.json | H29: AADHAAR_NUMBER | I29: identity | J29: Y | K29: clean | L29: =IFERROR(_xludf.XLOOKUP($G29&"."&$H29,CaseSource!$A$2:$A$371,CaseSource!$B$2:$B$371,""),"")
A30: co_address | B30: Pre-File | C30: Co Applicant Section | D30: Always | F30: 1 | G30: AUTH_SIGNATORY.json | H30: ADD1_1 | I30: identity | J30: Y | K30: clean | L30: =IFERROR(_xludf.XLOOKUP($G30&"."&$H30,CaseSource!$A$2:$A$371,CaseSource!$B$2:$B$371,""),"")
... A36: co_city | B36: Pre-File | C36: Co Applicant Section | D36: Always | F36: 3 | G36: CPV_DETAIL.json | H36: RESI_CITY | I36: identity | J36: Y | K36: clean | L36: =IFERROR(_xludf.XLOOKUP($G36&"."&$H36,CaseSource!$A$2:$A$371,CaseSource!$B$2:$B$371,""),"")
A37: co_currentExperience` / `co_totalExperience | D37: Always | F37: 1 | G37: CPV_DETAIL.json | H37: YEAR_AT_PROFESSION | I37: identity | J37: Y | K37: numeric | L37: =IFERROR(_xludf.XLOOKUP($G37&"."&$H37,CaseSource!$A$2:$A$371,CaseSource!$B$2:$B$371,""),"")
A38: co_customerName | B38: Pre-File | C38: Co Applicant Section | D38: Always | F38: 1 | G38: AUTH_SIGNATORY.json | H38: NAME_1 | I38: identity | J38: Y | K38: clean | L38: =IFERROR(_xludf.XLOOKUP($G38&"."&$H38,CaseSource!$A$2:$A$371,CaseSource!$B$2:$B$371,""),"")
A39: co_customerName | B39: Pre-File | C39: Co Applicant Section | D39: Always | F39: 2 | G39: AUTH_SIGNATORY.json | H39: NAME | I39: identity | J39: Y | K39: clean | L39: =IFERROR(_xludf.XLOOKUP($G39&"."&$H39,CaseSource!$A$2:$A$371,CaseSource!$B$2:$B$371,""),"")
A40: co_customerName | B40: Pre-File | C40: Co Applicant Section | D40: Always | F40: 3 | G40: GURANTOR.json | H40: NAME | I40: identity | J40: Y | K40: clean | L40: =IFERROR(_xludf.XLOOKUP($G40&"."&$H40,CaseSource!$A$2:$A$371,CaseSource!$B$2:$B$371,""),"")
A41: co_dependents | B41: Pre-File | C41: Co Applicant Section | D41: Always | F41: 1 | G41: CPV_DETAIL.json | H41: NO_OF_DEPENDANTS | I41: identity | J41: Y | K41: numeric | L41: =IFERROR(_xludf.XLOOKUP($G41&"."&$H41,CaseSource!$A$2:$A$371,CaseSource!$B$2:$B$371,""),"")
A42: co_dependents | B42: Pre-File | C42: Co Applicant Section | D42: Always | F42: 2 | G42: GURANTOR.json | H42: NO_OF_DEPEND | I42: identity | J42: Y | K42: numeric | L42: =IFERROR(_xludf.XLOOKUP($G42&"."&$H42,CaseSource!$A$2:$A$371,CaseSource!$B$2:$B$371,""),"")
A43: co_designation | B43: Pre-File | C43: Co Applicant Section | D43: Always | F43: 1 | G43: AUTH_SIGNATORY.json | H43: DESIGNATION_1 | I43: identity | J43: Y | K43: clean | L43: =IFERROR(_xludf.XLOOKUP($G43&"."&$H43,CaseSource!$A$2:$A$371,CaseSource!$B$2:$B$371,""),"")
A44: co_dob | B44: Pre-File | C44: Co Applicant Section | D44: Always | F44: 1 | G44: AUTH_SIGNATORY.json | H44: DATE_OF_BIRTH_1 | I44: identity | J44: Y | K44: ISO | L44: =IFERROR(_xludf.XLOOKUP($G44&"."&$H44,CaseSource!$A$2:$A$371,CaseSource!$B$2:$B$371,""),"")
A45: co_dob | B45: Pre-File | C45: Co Applicant Section | D45: Always | F45: 2 | G45: CPV_DETAIL.json | H45: DATE_OF_BIRTH | I45: identity | J45: Y | K45: ISO | L45: =IFERROR(_xludf.XLOOKUP($G45&"."&$H45,CaseSource!$A$2:$A$371,CaseSource!$B$2:$B$371,""),"")
A46: co_houseType | B46: Pre-File | C46: Co Applicant Section | D46: Always | F46: 1 | G46: CPV_DETAIL.json | H46: RESIDENCE_TYPE | I46: identity | J46: Y | K46: normalized | L46: =IFERROR(_xludf.XLOOKUP($G46&"."&$H46,CaseSource!$A$2:$A$371,CaseSource!$B$2:$B$371,""),"")
A47: co_houseType | B47: Pre-File | C47: Co Applicant Section | D47: Always | F47: 2 | G47: GURANTOR.json | H47: RESIDENCE_TYPE | I47: identity | J47: Y | K47: normalized | L47: =IFERROR(_xludf.XLOOKUP($G47&"."&$H47,CaseSource!$A$2:$A$371,CaseSource!$B$2:$B$371,""),"")
A48: co_pincode | B48: Pre-File | C48: Co Applicant Section | D48: Always | F48: 1 | G48: AUTH_SIGNATORY.json | H48: PIN_1 | I48: identity | J48: Y | K48: clean | L48: =IFERROR(_xludf.XLOOKUP($G48&"."&$H48,CaseSource!$A$2:$A$371,CaseSource!$B$2:$B$371,""),"")
A49: co_pincode | B49: Pre-File | C49: Co Applicant Section | D49: Always | F49: 2 | G49: GURANTOR.json | H49: RESI_PIN | I49: identity | J49: Y | K49: clean | L49: =IFERROR(_xludf.XLOOKUP($G49&"."&$H49,CaseSource!$A$2:$A$371,CaseSource!$B$2:$B$371,""),"")
... A57: companyType | B57: Pre-File | C57: Occupational Details Pre File | D57: Always | F57: 2 | G57: CPV_DETAIL.json | H57: ORGANISATION_TYPE | I57: identity | J57: Y | K57: normalized | L57: =IFERROR(_xludf.XLOOKUP($G57&"."&$H57,CaseSource!$A$2:$A$371,CaseSource!$B$2:$B$371,""),"")
A58: currentStage | B58: Shared | C58: Loan Form With Steps | D58: Always | E58: Must respect legacy approval/disbursement progression for migration cases. | F58: 1 | G58: RC_CUSTOMER_ACCOUNT.json | H58: DATE_OF_DISBURSE | I58: identity | J58: Y | K58: If cash loan (`isFinanced=No`) => `delivery`; cash-in/refinance with disburse => `payout`; else delivery/disburse/dispatch fallback. | L58: =IFERROR(_xludf.XLOOKUP($G58&"."&$H58,CaseSource!$A$2:$A$371,CaseSource!$B$2:$B$371,""),"")
A59: currentStage | B59: Shared | C59: Loan Form With Steps | D59: Always | E59: Must respect legacy approval/disbursement progression for migration cases. | F59: 2 | G59: RC_RC_INV_STATUS.json | H59: DATE_OF_DISBURSE | I59: identity | J59: Y | K59: If cash loan (`isFinanced=No`) => `delivery`; cash-in/refinance with disburse => `payout`; else delivery/disburse/dispatch fallback. | L59: =IFERROR(_xludf.XLOOKUP($G59&"."&$H59,CaseSource!$A$2:$A$371,CaseSource!$B$2:$B$371,""),"")
A60: currentStage | B60: Shared | C60: Loan Form With Steps | D60: Always | E60: Must respect legacy approval/disbursement progression for migration cases. | F60: 3 | G60: RC_CUSTOMER_ACCOUNT.json | H60: DATE_OF_DELIVERY | I60: identity | J60: Y | K60: If cash loan (`isFinanced=No`) => `delivery`; cash-in/refinance with disburse => `payout`; else delivery/disburse/dispatch fallback. | L60: =IFERROR(_xludf.XLOOKUP($G60&"."&$H60,CaseSource!$A$2:$A$371,CaseSource!$B$2:$B$371,""),"")
A61: currentStage | B61: Shared | C61: Loan Form With Steps | D61: Always | E61: Must respect legacy approval/disbursement progression for migration cases. | F61: 4 | G61: RC_RC_INV_STATUS.json | H61: DATE_OF_DELIVERY | I61: identity | J61: Y | K61: If cash loan (`isFinanced=No`) => `delivery`; cash-in/refinance with disburse => `payout`; else delivery/disburse/dispatch fallback. | L61: =IFERROR(_xludf.XLOOKUP($G61&"."&$H61,CaseSource!$A$2:$A$371,CaseSource!$B$2:$B$371,""),"")
A62: currentStage | B62: Shared | C62: Loan Form With Steps | D62: Always | E62: Must respect legacy approval/disbursement progression for migration cases. | F62: 5 | G62: RC_CUSTOMER_ACCOUNT.json | H62: DATE_OF_FILE_DESPATCH | I62: identity | J62: Y | K62: If cash loan (`isFinanced=No`) => `delivery`; cash-in/refinance with disburse => `payout`; else delivery/disburse/dispatch fallback. | L62: =IFERROR(_xludf.XLOOKUP($G62&"."&$H62,CaseSource!$A$2:$A$371,CaseSource!$B$2:$B$371,""),"")
A63: currentStage | B63: Shared | C63: Loan Form With Steps | D63: Always | E63: Must respect legacy approval/disbursement progression for migration cases. | F63: 6 | G63: RC_CUSTOMER_ACCOUNT.json | H63: DATE_WHEN_FILE_DESPATCH | I63: identity | J63: Y | K63: If cash loan (`isFinanced=No`) => `delivery`; cash-in/refinance with disburse => `payout`; else delivery/disburse/dispatch fallback. | L63: =IFERROR(_xludf.XLOOKUP($G63&"."&$H63,CaseSource!$A$2:$A$371,CaseSource!$B$2:$B$371,""),"")
A64: customerName | B64: Profile | C64: Emicustomer Details | D64: Always | F64: 1 | G64: RC_CUSTOMER_ACCOUNT.json | H64: CUST_NAME | I64: identity | J64: Y | K64: `pickName(...)` uses case-aware row preference. | L64: =IFERROR(_xludf.XLOOKUP($G64&"."&$H64,CaseSource!$A$2:$A$371,CaseSource!$B$2:$B$371,""),"")
A65: customerName | B65: Profile | C65: Emicustomer Details | D65: Always | F65: 2 | G65: CPV_DETAIL.json | H65: CUSTOMER_NAME | I65: identity | J65: Y | K65: `pickName(...)` uses case-aware row preference. | L65: =IFERROR(_xludf.XLOOKUP($G65&"."&$H65,CaseSource!$A$2:$A$371,CaseSource!$B$2:$B$371,""),"")
A66: dealerName | B66: Profile | C66: Lead Details | D66: Always | F66: 1 | G66: RC_CUSTOMER_ACCOUNT.json | H66: PAYMENT_FAVOURING_AT_DESPATCH | I66: identity | J66: Y | K66: ignored if literal `customer name` | L66: =IFERROR(_xludf.XLOOKUP($G66&"."&$H66,CaseSource!$A$2:$A$371,CaseSource!$B$2:$B$371,""),"")
A67: delivery_date | B67: Delivery | C67: Vehicle Delivery Step | D67: Always | F67: 1 | G67: RC_CUSTOMER_ACCOUNT.json | H67: DATE_OF_DELIVERY | I67: identity | J67: Y | K67: only when `typeOfLoan=New Car` in payload currently | L67: =IFERROR(_xludf.XLOOKUP($G67&"."&$H67,CaseSource!$A$2:$A$371,CaseSource!$B$2:$B$371,""),"")
A68: delivery_date | B68: Delivery | C68: Vehicle Delivery Step | D68: Always | F68: 2 | G68: RC_RC_INV_STATUS.json | H68: DATE_OF_DELIVERY | I68: identity | J68: Y | K68: only when `typeOfLoan=New Car` in payload currently | L68: =IFERROR(_xludf.XLOOKUP($G68&"."&$H68,CaseSource!$A$2:$A$371,CaseSource!$B$2:$B$371,""),"")
A69: dependents | B69: Profile | C69: Personal Details Simplified | D69: Always | F69: 1 | G69: CPV_DETAIL.json | H69: NO_OF_DEPENDANTS | I69: identity | J69: Y | K69: numeric | L69: =IFERROR(_xludf.XLOOKUP($G69&"."&$H69,CaseSource!$A$2:$A$371,CaseSource!$B$2:$B$371,""),"")
A70: designation | B70: Pre-File | C70: Authorised Signatory Section | D70: Always | F70: 1 | G70: AUTH_SIGNATORY.json | H70: DESIGNATION_1 | I70: identity | J70: Y | K70: clean | L70: =IFERROR(_xludf.XLOOKUP($G70&"."&$H70,CaseSource!$A$2:$A$371,CaseSource!$B$2:$B$371,""),"")
A71: designation | B71: Pre-File | C71: Authorised Signatory Section | D71: Always | F71: 2 | G71: CPV_DETAIL.json | H71: INDUSTRY_DETAIL | I71: identity | J71: Y | K71: clean | L71: =IFERROR(_xludf.XLOOKUP($G71&"."&$H71,CaseSource!$A$2:$A$371,CaseSource!$B$2:$B$371,""),"")
A72: dispatch_date | B72: Post-File | C72: Post File Dispatch And Records | D72: Always | F72: 1 | G72: RC_DOC_DESPATCH_MASTER.json | H72: DATE_OF_DESP | I72: identity | J72: Y | K72: date | L72: =IFERROR(_xludf.XLOOKUP($G72&"."&$H72,CaseSource!$A$2:$A$371,CaseSource!$B$2:$B$371,""),"")
A73: dispatch_date | B73: Post-File | C73: Post File Dispatch And Records | D73: Always | F73: 2 | G73: RC_CUSTOMER_ACCOUNT.json | H73: DATE_OF_FILE_DESPATCH | I73: identity | J73: Y | K73: date | L73: =IFERROR(_xludf.XLOOKUP($G73&"."&$H73,CaseSource!$A$2:$A$371,CaseSource!$B$2:$B$371,""),"")
A74: dispatch_through | B74: Post-File | C74: Post File Dispatch And Records | D74: Always | F74: 1 | G74: RC_DOC_DESPATCH_MASTER.json | H74: DESP_THROUGH | I74: identity | J74: Y | K74: clean | L74: =IFERROR(_xludf.XLOOKUP($G74&"."&$H74,CaseSource!$A$2:$A$371,CaseSource!$B$2:$B$371,""),"")
A75: dispatch_through | B75: Post-File | C75: Post File Dispatch And Records | D75: Always | F75: 2 | G75: RC_CUSTOMER_ACCOUNT.json | H75: DESPATCH_FOR_APPROVAL_THROUGH | I75: identity | J75: Y | K75: clean | L75: =IFERROR(_xludf.XLOOKUP($G75&"."&$H75,CaseSource!$A$2:$A$371,CaseSource!$B$2:$B$371,""),"")
... A78: dob | B78: Pre-File | C78: Personal Details Pre File | D78: Always | F78: 1 | G78: CPV_DETAIL.json | H78: DATE_OF_BIRTH | I78: identity | J78: Y | K78: ISO date | L78: =IFERROR(_xludf.XLOOKUP($G78&"."&$H78,CaseSource!$A$2:$A$371,CaseSource!$B$2:$B$371,""),"")
A79: docsPreparedBy | B79: Pre-File | C79: Section7Record Details | D79: Pre-file/Post-file record details | E79: Map from PRE/POST docs prepared-by chain, not source channel. | F79: 1 | G79: RC_DOC_DESPATCH_MASTER.json | H79: DOCS_PREPARED_BY | I79: identity | J79: Y | K79: clean | L79: =IFERROR(_xludf.XLOOKUP($G79&"."&$H79,CaseSource!$A$2:$A$371,CaseSource!$B$2:$B$371,""),"")
A80: docsPreparedBy | B80: Pre-File | C80: Section7Record Details | D80: Pre-file/Post-file record details | E80: Map from PRE/POST docs prepared-by chain, not source channel. | F80: 2 | G80: RC_CUSTOMER_ACCOUNT.json | H80: PRE_DOCS_PREPARED_BY | I80: identity | J80: Y | K80: clean | L80: =IFERROR(_xludf.XLOOKUP($G80&"."&$H80,CaseSource!$A$2:$A$371,CaseSource!$B$2:$B$371,""),"")
A81: dsaCode | B81: Shared | C81: LoanFormWithSteps | D81: Always | F81: 1 | G81: RC_CUSTOMER_ACCOUNT.json | H81: DSA_CODE | I81: identity | J81: Y | K81: clean | L81: =IFERROR(_xludf.XLOOKUP($G81&"."&$H81,CaseSource!$A$2:$A$371,CaseSource!$B$2:$B$371,""),"")
A82: education | B82: Pre-File | C82: Personal Details Pre File | D82: Always | F82: 1 | G82: CPV_DETAIL.json | H82: EDUCATION | I82: identity | J82: Y | K82: normalized | L82: =IFERROR(_xludf.XLOOKUP($G82&"."&$H82,CaseSource!$A$2:$A$371,CaseSource!$B$2:$B$371,""),"")
A83: email | B83: Profile | C83: Emicustomer Details | D83: Always | F83: 1 | G83: CPV_DETAIL.json | H83: E_MAIL | I83: identity | J83: Y | K83: clean text | L83: =IFERROR(_xludf.XLOOKUP($G83&"."&$H83,CaseSource!$A$2:$A$371,CaseSource!$B$2:$B$371,""),"")
A84: email | B84: Profile | C84: Emicustomer Details | D84: Always | F84: 2 | G84: CPV_DETAIL.json | H84: EMAIL_ADDRESS | I84: identity | J84: Y | K84: clean text | L84: =IFERROR(_xludf.XLOOKUP($G84&"."&$H84,CaseSource!$A$2:$A$371,CaseSource!$B$2:$B$371,""),"")
A85: employmentAddress | B85: Pre-File | C85: Occupational Details Pre File | D85: Always | F85: 1 | G85: CPV_DETAIL.json | H85: OFF_ADD1 | I85: identity | J85: Y | K85: clean | L85: =IFERROR(_xludf.XLOOKUP($G85&"."&$H85,CaseSource!$A$2:$A$371,CaseSource!$B$2:$B$371,""),"")
A86: employmentCity | B86: Pre-File | C86: Occupational Details Pre File | D86: Always | F86: 1 | G86: CPV_DETAIL.json | H86: OFF_CITY | I86: identity | J86: Y | K86: clean | L86: =IFERROR(_xludf.XLOOKUP($G86&"."&$H86,CaseSource!$A$2:$A$371,CaseSource!$B$2:$B$371,""),"")
A87: employmentPincode | B87: Pre-File | C87: Occupational Details Pre File | D87: Always | F87: 1 | G87: CPV_DETAIL.json | H87: OFF_PIN | I87: identity | J87: Y | K87: clean | L87: =IFERROR(_xludf.XLOOKUP($G87&"."&$H87,CaseSource!$A$2:$A$371,CaseSource!$B$2:$B$371,""),"")
A88: experienceCurrent | B88: Pre-File | C88: Occupational Details Pre File | D88: Always | F88: 1 | G88: CPV_DETAIL.json | H88: YEAR_AT_PROFESSION | I88: identity | J88: Y | K88: numeric | L88: =IFERROR(_xludf.XLOOKUP($G88&"."&$H88,CaseSource!$A$2:$A$371,CaseSource!$B$2:$B$371,""),"")
A89: exShowroomPrice | B89: Pre-File | C89: Loan Sticky Header | D89: Always | F89: 1 | G89: RC_CUSTOMER_ACCOUNT.json | H89: EX_SHOWROOM_OR_VALUATION | I89: identity | J89: Y | K89: numeric | L89: =IFERROR(_xludf.XLOOKUP($G89&"."&$H89,CaseSource!$A$2:$A$371,CaseSource!$B$2:$B$371,""),"")
A90: financeExpectation | B90: Profile | C90: Loan Sticky Header | D90: Always | F90: 1 | G90: RC_CUSTOMER_ACCOUNT.json | H90: LOAN_AMOUNT | I90: identity | J90: Y | K90: numeric | L90: =IFERROR(_xludf.XLOOKUP($G90&"."&$H90,CaseSource!$A$2:$A$371,CaseSource!$B$2:$B$371,""),"")
A91: financeExpectation | B91: Profile | C91: Loan Sticky Header | D91: Always | F91: 2 | G91: RC_CUSTOMER_ACCOUNT.json | H91: APPLIED_LOAN_AMOUNT | I91: identity | J91: Y | K91: numeric | L91: =IFERROR(_xludf.XLOOKUP($G91&"."&$H91,CaseSource!$A$2:$A$371,CaseSource!$B$2:$B$371,""),"")
A92: financeExpectation | B92: Profile | C92: Loan Sticky Header | D92: Always | F92: 3 | G92: CPV_DETAIL.json | H92: LOAN_EXPECTED | I92: identity | J92: Y | K92: numeric | L92: =IFERROR(_xludf.XLOOKUP($G92&"."&$H92,CaseSource!$A$2:$A$371,CaseSource!$B$2:$B$371,""),"")
... A107: invoice_received_from | B107: Delivery | C107: Vehicle Delivery Step | D107: Always | F107: 1 | G107: RC_RC_INV_RECEIVING_DETAIL.json | H107: INV_RECEIVED_FROM | I107: identity | J107: Y | K107: clean | L107: =IFERROR(_xludf.XLOOKUP($G107&"."&$H107,CaseSource!$A$2:$A$371,CaseSource!$B$2:$B$371,""),"")
A108: isFinanced | B108: Profile | C108: Loan Form With Steps | D108: Always | E108: If No => cash flow (Profile + Delivery only). If Yes => Pre-File/Approval/Post-File/Delivery/Payout flow. | F108: 1 | G108: RC_CUSTOMER_ACCOUNT.json | H108: LOAN_AMOUNT | I108: identity | J108: Y | K108: `Car Cash-in/Refinance => Yes`; else loan amount or financier present => `Yes`, else `No`. | L108: =IFERROR(_xludf.XLOOKUP($G108&"."&$H108,CaseSource!$A$2:$A$371,CaseSource!$B$2:$B$371,""),"")
A109: isFinanced | B109: Profile | C109: Loan Form With Steps | D109: Always | E109: If No => cash flow (Profile + Delivery only). If Yes => Pre-File/Approval/Post-File/Delivery/Payout flow. | F109: 2 | G109: RC_CUSTOMER_ACCOUNT.json | H109: APPLIED_LOAN_AMOUNT | I109: identity | J109: Y | K109: `Car Cash-in/Refinance => Yes`; else loan amount or financier present => `Yes`, else `No`. | L109: =IFERROR(_xludf.XLOOKUP($G109&"."&$H109,CaseSource!$A$2:$A$371,CaseSource!$B$2:$B$371,""),"")
A110: isFinanced | B110: Profile | C110: Loan Form With Steps | D110: Always | E110: If No => cash flow (Profile + Delivery only). If Yes => Pre-File/Approval/Post-File/Delivery/Payout flow. | F110: 3 | G110: CPV_DETAIL.json | H110: LOAN_EXPECTED | I110: identity | J110: Y | K110: `Car Cash-in/Refinance => Yes`; else loan amount or financier present => `Yes`, else `No`. | L110: =IFERROR(_xludf.XLOOKUP($G110&"."&$H110,CaseSource!$A$2:$A$371,CaseSource!$B$2:$B$371,""),"")
A111: isFinanced | B111: Profile | C111: Loan Form With Steps | D111: Always | E111: If No => cash flow (Profile + Delivery only). If Yes => Pre-File/Approval/Post-File/Delivery/Payout flow. | F111: 4 | G111: RC_CUSTOMER_ACCOUNT.json | H111: HP_TO | I111: identity | J111: Y | K111: `Car Cash-in/Refinance => Yes`; else loan amount or financier present => `Yes`, else `No`. | L111: =IFERROR(_xludf.XLOOKUP($G111&"."&$H111,CaseSource!$A$2:$A$371,CaseSource!$B$2:$B$371,""),"")
A112: isFinanced | B112: Profile | C112: Loan Form With Steps | D112: Always | E112: If No => cash flow (Profile + Delivery only). If Yes => Pre-File/Approval/Post-File/Delivery/Payout flow. | F112: 5 | G112: CPV_DETAIL.json | H112: FINANCER | I112: identity | J112: Y | K112: `Car Cash-in/Refinance => Yes`; else loan amount or financier present => `Yes`, else `No`. | L112: =IFERROR(_xludf.XLOOKUP($G112&"."&$H112,CaseSource!$A$2:$A$371,CaseSource!$B$2:$B$371,""),"")
A113: loan_number | B113: Post-File | C113: PostFileDispatchAndRecords | D113: Always | F113: 1 | G113: RC_CUSTOMER_ACCOUNT.json | H113: LOAN_NUMBER_PREFIX | I113: identity | J113: Y | K113: concatenated available parts | L113: =IFERROR(_xludf.XLOOKUP($G113&"."&$H113,CaseSource!$A$2:$A$371,CaseSource!$B$2:$B$371,""),"")
A114: loanTenureMonths | B114: Profile | C114: Finance Details Form | D114: Always | F114: 1 | G114: RC_CUSTOMER_ACCOUNT.json | H114: TENOR | I114: identity | J114: Y | K114: numeric | L114: =IFERROR(_xludf.XLOOKUP($G114&"."&$H114,CaseSource!$A$2:$A$371,CaseSource!$B$2:$B$371,""),"")
A115: loanTenureMonths | B115: Profile | C115: Finance Details Form | D115: Always | F115: 2 | G115: RC_CUSTOMER_ACCOUNT.json | H115: APPLIED_TENOR | I115: identity | J115: Y | K115: numeric | L115: =IFERROR(_xludf.XLOOKUP($G115&"."&$H115,CaseSource!$A$2:$A$371,CaseSource!$B$2:$B$371,""),"")
A116: loanTenureMonths | B116: Profile | C116: Finance Details Form | D116: Always | F116: 3 | G116: CPV_DETAIL.json | H116: TENDOR | I116: identity | J116: Y | K116: numeric | L116: =IFERROR(_xludf.XLOOKUP($G116&"."&$H116,CaseSource!$A$2:$A$371,CaseSource!$B$2:$B$371,""),"")
A117: maritalStatus | B117: Profile | C117: Personal Details Simplified | D117: Always | F117: 1 | G117: CPV_DETAIL.json | H117: MARITAL_STATUS | I117: identity | J117: Y | K117: normalized | L117: =IFERROR(_xludf.XLOOKUP($G117&"."&$H117,CaseSource!$A$2:$A$371,CaseSource!$B$2:$B$371,""),"")
A118: motherName | B118: Pre-File | C118: Personal Details Pre File | D118: Always | F118: 1 | G118: CPV_DETAIL.json | H118: MOTHERS_MAIDEN_NAME | I118: identity | J118: Y | K118: clean | L118: =IFERROR(_xludf.XLOOKUP($G118&"."&$H118,CaseSource!$A$2:$A$371,CaseSource!$B$2:$B$371,""),"")
A119: occupationType | B119: Pre-File | C119: Occupational Details Pre File | D119: Always | F119: 1 | G119: CPV_DETAIL.json | H119: PROFESSION_TYPE | I119: identity | J119: Y | K119: normalized | L119: =IFERROR(_xludf.XLOOKUP($G119&"."&$H119,CaseSource!$A$2:$A$371,CaseSource!$B$2:$B$371,""),"")
A120: panNumber | B120: Header / Shared | C120: Loan Sticky Header | D120: Always | F120: 1 | G120: CPV_DETAIL.json | H120: PAN_NUMBER | I120: identity | J120: Y | K120: clean text | L120: =IFERROR(_xludf.XLOOKUP($G120&"."&$H120,CaseSource!$A$2:$A$371,CaseSource!$B$2:$B$371,""),"")
A121: payoutPercentage | B121: Approval | C121: Loan Form With Steps | D121: Always | F121: 1 | G121: RC_CUSTOMER_ACCOUNT.json | H121: PAYOUT_RATE | I121: identity | J121: Y | K121: numeric | L121: =IFERROR(_xludf.XLOOKUP($G121&"."&$H121,CaseSource!$A$2:$A$371,CaseSource!$B$2:$B$371,""),"")
A122: permanentAddress | B122: Pre-File | C122: Loan Sticky Header | D122: Always | F122: 1 | G122: CPV_DETAIL.json | H122: PERMANENT_ADDRESS | I122: identity | J122: Y | K122: Parsed; if empty/NA then same as current. | L122: =IFERROR(_xludf.XLOOKUP($G122&"."&$H122,CaseSource!$A$2:$A$371,CaseSource!$B$2:$B$371,""),"")
A123: pincode | B123: Pre-File | C123: Personal Details Pre File | D123: Always | F123: 1 | G123: CPV_DETAIL.json | H123: OFF_PIN | I123: identity | J123: Y | K123: clean | L123: =IFERROR(_xludf.XLOOKUP($G123&"."&$H123,CaseSource!$A$2:$A$371,CaseSource!$B$2:$B$371,""),"")
A124: pincode | B124: Pre-File | C124: Personal Details Pre File | D124: Always | F124: 2 | G124: CPV_DETAIL.json | H124: RESI_PIN | I124: identity | J124: Y | K124: clean | L124: =IFERROR(_xludf.XLOOKUP($G124&"."&$H124,CaseSource!$A$2:$A$371,CaseSource!$B$2:$B$371,""),"")
... A128: postfile_emiMode | B128: Post-File | C128: Post File Approval Details | D128: Always | F128: 1 | G128: RC_CUSTOMER_ACCOUNT.json | H128: EMI_TYPE_ARREAR_ADVANCE | I128: identity | J128: Y | K128: default `Arrear` | L128: =IFERROR(_xludf.XLOOKUP($G128&"."&$H128,CaseSource!$A$2:$A$371,CaseSource!$B$2:$B$371,""),"")
A129: postfile_emiPlan` + `emiPlan | D129: Always | F129: 1 | G129: RC_CUSTOMER_ACCOUNT.json | H129: EMI_PLAN | I129: identity | J129: Y | K129: normalized (`1+1`, etc.) | L129: =IFERROR(_xludf.XLOOKUP($G129&"."&$H129,CaseSource!$A$2:$A$371,CaseSource!$B$2:$B$371,""),"")
A130: postfile_firstEmiDate | B130: Post-File | C130: Loan Form With Steps | D130: Always | F130: 1 | G130: RC_CUSTOMER_ACCOUNT.json | H130: EMI_DUE_DATE | I130: identity | J130: Y | K130: date | L130: =IFERROR(_xludf.XLOOKUP($G130&"."&$H130,CaseSource!$A$2:$A$371,CaseSource!$B$2:$B$371,""),"")
A131: prefile_sourcePayoutPercentage | B131: Pre-File | C131: Payout Section | D131: Always | F131: 1 | G131: RC_CUSTOMER_ACCOUNT.json | H131: PAYOUT_RATE | I131: identity | J131: Y | K131: numeric | L131: =IFERROR(_xludf.XLOOKUP($G131&"."&$H131,CaseSource!$A$2:$A$371,CaseSource!$B$2:$B$371,""),"")
...

Sheet CaseSource
A1: source_path | B1: value
A2: AUTH_SIGNATORY.json.ACCOUNT_NUMBER_TYPE | B2: CPV
A3: AUTH_SIGNATORY.json.ADD1 | B3: C-5 1504 CLEO COUNTY NOIDA SECTOR-121
A4: AUTH_SIGNATORY.json.ADD2
A5: AUTH_SIGNATORY.json.AUTH_AADHAAR_NUMBER | B5: 951419463882
A6: AUTH_SIGNATORY.json.CITY | B6: NOIDA
A7: AUTH_SIGNATORY.json.CPV_ACCOUNT_NO | B7: 3419
A8: AUTH_SIGNATORY.json.DATA_LOCATION_CODE | B8: 03
A9: AUTH_SIGNATORY.json.DATE_OF_BIRTH | B9: 1987-09-09T00:00:00
A10: AUTH_SIGNATORY.json.DESIGNATION | B10: DIRECTOR
A11: AUTH_SIGNATORY.json.FAX
A12: AUTH_SIGNATORY.json.HP_GROUP | B12: 01
A13: AUTH_SIGNATORY.json.MOBILE
A14: AUTH_SIGNATORY.json.NAME | B14: GAURAV KHANNA
A15: AUTH_SIGNATORY.json.ORIGINAL_HP_GROUP
A16: AUTH_SIGNATORY.json.PHONE | B16: 9811542232
A17: AUTH_SIGNATORY.json.PIN | B17: 201309
A18: CPV_DETAIL.json.AADHAAR_NUMBER
A19: CPV_DETAIL.json.ACCOUNT_NUMBER_TYPE | B19: CPV
A20: CPV_DETAIL.json.ANNUAL_INCOME | B20: 3797080
A21: CPV_DETAIL.json.CAR_MODEL | B21: S PRESSO LXI CNG
A22: CPV_DETAIL.json.CATEGORY | B22: PVT LTD
A23: CPV_DETAIL.json.CDB_ACCOUNT_NO | B23: 3000004231
A24: CPV_DETAIL.json.CLS_REMARKS
A25: CPV_DETAIL.json.CLS_STATUS
A26: CPV_DETAIL.json.CPV_ACCOUNT_NO | B26: 3419
A27: CPV_DETAIL.json.CPV_DATE | B27: 2025-01-02T00:00:00
A28: CPV_DETAIL.json.CPV_G_OFF_STATUS
A29: CPV_DETAIL.json.CPV_G_RES_STATUS
A30: CPV_DETAIL.json.CPV_MONTH_YEAR | B30: 012025
A31: CPV_DETAIL.json.CPV_OFF_STATUS
A32: CPV_DETAIL.json.CPV_RES_STATUS
A33: CPV_DETAIL.json.CPV_SEND_AT_TIME
A34: CPV_DETAIL.json.CPV_SEND_ON_DATE
A35: CPV_DETAIL.json.CREATED_BY_USER
A36: CPV_DETAIL.json.CREATED_ON_DATE
A37: CPV_DETAIL.json.CREATED_ON_TIME
A38: CPV_DETAIL.json.CUST_NAME_FIRST | B38: GOURAV
A39: CPV_DETAIL.json.CUST_NAME_LAST | B39: PVT LTD 2
A40: CPV_DETAIL.json.CUST_NAME_MIDDLE | B40: LUMINARIES
A41: CPV_DETAIL.json.CUSTOMER_NAME | B41: GOURAV LUMINARIES PVT LTD 2
A42: CPV_DETAIL.json.DATA_LOCATION_CODE | B42: 03
A43: CPV_DETAIL.json.DATA_STATUS | B43: COMPLETE
A44: CPV_DETAIL.json.DATE_OF_BIRTH | B44: 1995-10-12T00:00:00
A45: CPV_DETAIL.json.DEALT_BY | B45: DRG
A46: CPV_DETAIL.json.DRIVING_LICENSE
A47: CPV_DETAIL.json.E_MAIL | B47: GAURAV@GOURAVROSHNI.COM
A48: CPV_DETAIL.json.EDUCATION | B48: NA
A49: CPV_DETAIL.json.EMAIL_ADDRESS | B49: gaurav@gouravroshni.com
A50: CPV_DETAIL.json.FATHERS_NAME_FIRST
A51: CPV_DETAIL.json.FATHERS_NAME_LAST
A52: CPV_DETAIL.json.FATHERS_NAME_MIDDLE
A53: CPV_DETAIL.json.FINANCER | B53: HDFC
A54: CPV_DETAIL.json.GURANTOR_AVAILABLE | B54: N
A55: CPV_DETAIL.json.HEAD_NAME | B55: M/s.
A56: CPV_DETAIL.json.HIRE_TYPE | B56: Company
A57: CPV_DETAIL.json.HP_GROUP | B57: 01
A58: CPV_DETAIL.json.HUSBAND_NAME
A59: CPV_DETAIL.json.ICICI_ENTRY_NUMBER | B59: BY BANK
A60: CPV_DETAIL.json.INDUSTRY_DETAIL | B60: TRADING
A61: CPV_DETAIL.json.IS_REQ_G_OFF_VERIFICATION | B61: 0
A62: CPV_DETAIL.json.IS_REQ_G_RES_VERIFICATION | B62: 0
A63: CPV_DETAIL.json.IS_REQ_OFF_VERIFICATION | B63: 0
A64: CPV_DETAIL.json.IS_REQ_RES_VERIFICATION | B64: 1
A65: CPV_DETAIL.json.LAST_EDIT_BY_USER
A66: CPV_DETAIL.json.LAST_EDIT_ON_DATE
A67: CPV_DETAIL.json.LAST_EDIT_ON_TIME
A68: CPV_DETAIL.json.LOAN_EXPECTED | B68: 525000
A69: CPV_DETAIL.json.LOAN_TYPE | B69: Auto Loan
A70: CPV_DETAIL.json.MARITAL_STATUS
A71: CPV_DETAIL.json.MARKETING_BY | B71: 2021
A72: CPV_DETAIL.json.MOBILE
A73: CPV_DETAIL.json.MOTHERS_MAIDEN_NAME
A74: CPV_DETAIL.json.NCCB
A75: CPV_DETAIL.json.NO_OF_DEPENDANTS | B75: 0
A76: CPV_DETAIL.json.OFF_ADD1 | B76: PLOT NO-11/1,2 & 12/1 SITE-IV SAHIBABAD
A77: CPV_DETAIL.json.OFF_ADD2 | B77: INDUSTRIAL AREA
A78: CPV_DETAIL.json.OFF_CITY | B78: GHAZIABAD
A79: CPV_DETAIL.json.OFF_FAX
A80: CPV_DETAIL.json.OFF_NAME | B80: GOURAV LUMINARIES PVT LTD
A81: CPV_DETAIL.json.OFF_PHONE1 | B81: 9811542232
A82: CPV_DETAIL.json.OFF_PHONE2
A83: CPV_DETAIL.json.OFF_PHONE3
A84: CPV_DETAIL.json.OFF_PIN | B84: 201010
A85: CPV_DETAIL.json.ORGANISATION_TYPE | B85: ELECTRONIC
A86: CPV_DETAIL.json.ORIGINAL_HP_GROUP
A87: CPV_DETAIL.json.PAGER
A88: CPV_DETAIL.json.PAN_NUMBER | B88: AAACG3334L
A89: CPV_DETAIL.json.PASSPORT_NUMBER
A90: CPV_DETAIL.json.PERMANENT_ADDRESS | B90: C-5 1504 CLEO COUNTY NOIDA SECTOR-121 NOIDA 201309
A91: CPV_DETAIL.json.PREVIOUS_RELATION_WITH_US | B91: NO
A92: CPV_DETAIL.json.PROFESSION_TYPE | B92: Self-Employed
A93: CPV_DETAIL.json.PURPOSE_OF_LOAN | B93: Business
A94: CPV_DETAIL.json.REF1_ADD | B94: 12-D BLOCK PREET VIHAR DELHI 110092
A95: CPV_DETAIL.json.REF1_NAME | B95: ANIL SETHI
A96: CPV_DETAIL.json.REF1_PHONE | B96: 9811024536
A97: CPV_DETAIL.json.REF1_RELATION | B97: FRIEND
A98: CPV_DETAIL.json.REF2_ADD | B98: B-209 S/F SURYA NAGAR GHAZIABAD 201010
A99: CPV_DETAIL.json.REF2_NAME | B99: SANJAY NAGPAL
A100: CPV_DETAIL.json.REF2_PHONE | B100: 9811161499
...
