Workbook
Name LegacyFiles: 'DropdownData'!$A$2:$A$11
Name AUTH_SIGNATORY: 'DropdownData'!$B$2:$B$17
Name CPV_DETAIL: 'DropdownData'!$C$2:$C$105
Name CUSTOMER_BANK: 'DropdownData'!$D$2:$D$13
Name GURANTOR: 'DropdownData'!$E$2:$E$34
Name RC_CUSTOMER_ACCOUNT: 'DropdownData'!$F$2:$F$161
Name RC_DOC_DESPATCH_MASTER: 'DropdownData'!$G$2:$G$10
Name RC_INSTRUMENT_DETAIL: 'DropdownData'!$H$2:$H$21
Name RC_RC_INV_RECEIVING_DETAIL: 'DropdownData'!$I$2:$I$23
Name RC_RC_INV_STATUS: 'DropdownData'!$J$2:$J$28
Name RC_SOURCE_REFERENCE: 'DropdownData'!$K$2:$K$6

Sheet MappingEditor
A1: new_field | B1: new_page | C1: new_section | D1: applies_when | E1: flow_notes | F1: legacy_file | G1: legacy_field | H1: fallback_priority | I1: transform | J1: active | K1: notes | L1: example_legacy_value | M1: example_new_value | N1: case_value_preview
A2: typeOfLoan | B2: Profile | C2: Loan Form With Steps | D2: Always (drives downstream flow) | E2: Core flow selector: New Car / Used Car / Car Cash-in / Refinance. | F2: RC_CUSTOMER_ACCOUNT.json | G2: CASE_TYPE | H2: 1 | I2: identity | J2: Y | K2: **Priority is `CASE_TYPE`**; map contains `cash-in` => `Car Cash-in`, `refinance` => `Refinance`, `used` => `Used Car`, else `New Car`. | N2: =IFERROR(XLOOKUP($F2&"."&$G2,CaseSource!$A$2:$A$371,CaseSource!$B$2:$B$371,""),"")
A3: typeOfLoan | B3: Profile | C3: Loan Form With Steps | D3: Always (drives downstream flow) | E3: Core flow selector: New Car / Used Car / Car Cash-in / Refinance. | F3: CPV_DETAIL.json | G3: TYPE_OF_LOAN | H3: 2 | I3: identity | J3: Y | K3: **Priority is `CASE_TYPE`**; map contains `cash-in` => `Car Cash-in`, `refinance` => `Refinance`, `used` => `Used Car`, else `New Car`. | N3: =IFERROR(XLOOKUP($F3&"."&$G3,CaseSource!$A$2:$A$371,CaseSource!$B$2:$B$371,""),"")
A4: typeOfLoan | B4: Profile | C4: Loan Form With Steps | D4: Always (drives downstream flow) | E4: Core flow selector: New Car / Used Car / Car Cash-in / Refinance. | F4: CPV_DETAIL.json | G4: LOAN_TYPE | H4: 3 | I4: identity | J4: Y | K4: **Priority is `CASE_TYPE`**; map contains `cash-in` => `Car Cash-in`, `refinance` => `Refinance`, `used` => `Used Car`, else `New Car`. | N4: =IFERROR(XLOOKUP($F4&"."&$G4,CaseSource!$A$2:$A$371,CaseSource!$B$2:$B$371,""),"")
A5: typeOfLoan | B5: Profile | C5: Loan Form With Steps | D5: Always (drives downstream flow) | E5: Core flow selector: New Car / Used Car / Car Cash-in / Refinance. | F5: CPV_DETAIL.json | G5: HIRE_PURPOSE | H5: 4 | I5: identity | J5: Y | K5: **Priority is `CASE_TYPE`**; map contains `cash-in` => `Car Cash-in`, `refinance` => `Refinance`, `used` => `Used Car`, else `New Car`. | N5: =IFERROR(XLOOKUP($F5&"."&$G5,CaseSource!$A$2:$A$371,CaseSource!$B$2:$B$371,""),"")
A6: typeOfLoan | B6: Profile | C6: Loan Form With Steps | D6: Always (drives downstream flow) | E6: Core flow selector: New Car / Used Car / Car Cash-in / Refinance. | F6: CPV_DETAIL.json | G6: PURPOSE_OF_LOAN | H6: 5 | I6: identity | J6: Y | K6: **Priority is `CASE_TYPE`**; map contains `cash-in` => `Car Cash-in`, `refinance` => `Refinance`, `used` => `Used Car`, else `New Car`. | N6: =IFERROR(XLOOKUP($F6&"."&$G6,CaseSource!$A$2:$A$371,CaseSource!$B$2:$B$371,""),"")
A7: typeOfLoan | B7: Profile | C7: Loan Form With Steps | D7: Always (drives downstream flow) | E7: Core flow selector: New Car / Used Car / Car Cash-in / Refinance. | F7: RC_CUSTOMER_ACCOUNT.json | G7: TYPE_OF_LOAN | H7: 6 | I7: identity | J7: Y | K7: **Priority is `CASE_TYPE`**; map contains `cash-in` => `Car Cash-in`, `refinance` => `Refinance`, `used` => `Used Car`, else `New Car`. | N7: =IFERROR(XLOOKUP($F7&"."&$G7,CaseSource!$A$2:$A$371,CaseSource!$B$2:$B$371,""),"")
A8: typeOfLoan | B8: Profile | C8: Loan Form With Steps | D8: Always (drives downstream flow) | E8: Core flow selector: New Car / Used Car / Car Cash-in / Refinance. | F8: RC_CUSTOMER_ACCOUNT.json | G8: LOAN_TYPE | H8: 7 | I8: identity | J8: Y | K8: **Priority is `CASE_TYPE`**; map contains `cash-in` => `Car Cash-in`, `refinance` => `Refinance`, `used` => `Used Car`, else `New Car`. | N8: =IFERROR(XLOOKUP($F8&"."&$G8,CaseSource!$A$2:$A$371,CaseSource!$B$2:$B$371,""),"")
A9: typeOfLoan | B9: Profile | C9: Loan Form With Steps | D9: Always (drives downstream flow) | E9: Core flow selector: New Car / Used Car / Car Cash-in / Refinance. | F9: RC_CUSTOMER_ACCOUNT.json | G9: LOAN_FOR | H9: 8 | I9: identity | J9: Y | K9: **Priority is `CASE_TYPE`**; map contains `cash-in` => `Car Cash-in`, `refinance` => `Refinance`, `used` => `Used Car`, else `New Car`. | N9: =IFERROR(XLOOKUP($F9&"."&$G9,CaseSource!$A$2:$A$371,CaseSource!$B$2:$B$371,""),"")
A10: isFinanced | B10: Profile | C10: Loan Form With Steps | D10: Always | E10: If No => cash flow (Profile + Delivery only). If Yes => Pre-File/Approval/Post-File/Delivery/Payout flow. | F10: RC_CUSTOMER_ACCOUNT.json | G10: LOAN_AMOUNT | H10: 1 | I10: identity | J10: Y | K10: `Car Cash-in/Refinance => Yes`; else loan amount or financier present => `Yes`, else `No`. | N10: =IFERROR(XLOOKUP($F10&"."&$G10,CaseSource!$A$2:$A$371,CaseSource!$B$2:$B$371,""),"")
A11: isFinanced | B11: Profile | C11: Loan Form With Steps | D11: Always | E11: If No => cash flow (Profile + Delivery only). If Yes => Pre-File/Approval/Post-File/Delivery/Payout flow. | F11: RC_CUSTOMER_ACCOUNT.json | G11: APPLIED_LOAN_AMOUNT | H11: 2 | I11: identity | J11: Y | K11: `Car Cash-in/Refinance => Yes`; else loan amount or financier present => `Yes`, else `No`. | N11: =IFERROR(XLOOKUP($F11&"."&$G11,CaseSource!$A$2:$A$371,CaseSource!$B$2:$B$371,""),"")
A12: isFinanced | B12: Profile | C12: Loan Form With Steps | D12: Always | E12: If No => cash flow (Profile + Delivery only). If Yes => Pre-File/Approval/Post-File/Delivery/Payout flow. | F12: CPV_DETAIL.json | G12: LOAN_EXPECTED | H12: 3 | I12: identity | J12: Y | K12: `Car Cash-in/Refinance => Yes`; else loan amount or financier present => `Yes`, else `No`. | N12: =IFERROR(XLOOKUP($F12&"."&$G12,CaseSource!$A$2:$A$371,CaseSource!$B$2:$B$371,""),"")
A13: isFinanced | B13: Profile | C13: Loan Form With Steps | D13: Always | E13: If No => cash flow (Profile + Delivery only). If Yes => Pre-File/Approval/Post-File/Delivery/Payout flow. | F13: RC_CUSTOMER_ACCOUNT.json | G13: HP_TO | H13: 4 | I13: identity | J13: Y | K13: `Car Cash-in/Refinance => Yes`; else loan amount or financier present => `Yes`, else `No`. | N13: =IFERROR(XLOOKUP($F13&"."&$G13,CaseSource!$A$2:$A$371,CaseSource!$B$2:$B$371,""),"")
... A20: currentStage | B20: Shared | C20: Loan Form With Steps | D20: Always | E20: Must respect legacy approval/disbursement progression for migration cases. | F20: RC_CUSTOMER_ACCOUNT.json | G20: DATE_WHEN_FILE_DESPATCH | H20: 6 | I20: identity | J20: Y | K20: If cash loan (`isFinanced=No`) => `delivery`; cash-in/refinance with disburse => `payout`; else delivery/disburse/dispatch fallback. | N20: =IFERROR(XLOOKUP($F20&"."&$G20,CaseSource!$A$2:$A$371,CaseSource!$B$2:$B$371,""),"")
A21: customerName | B21: Profile | C21: Emicustomer Details | D21: Always | F21: RC_CUSTOMER_ACCOUNT.json | G21: CUST_NAME | H21: 1 | I21: identity | J21: Y | K21: `pickName(...)` uses case-aware row preference. | N21: =IFERROR(XLOOKUP($F21&"."&$G21,CaseSource!$A$2:$A$371,CaseSource!$B$2:$B$371,""),"")
A22: customerName | B22: Profile | C22: Emicustomer Details | D22: Always | F22: CPV_DETAIL.json | G22: CUSTOMER_NAME | H22: 2 | I22: identity | J22: Y | K22: `pickName(...)` uses case-aware row preference. | N22: =IFERROR(XLOOKUP($F22&"."&$G22,CaseSource!$A$2:$A$371,CaseSource!$B$2:$B$371,""),"")
A23: applicantType | B23: Profile | C23: Lead Details | D23: Always | E23: Individual vs Company changes form visibility and required sections. | F23: CPV_DETAIL.json | G23: HIRE_TYPE | H23: 1 | I23: identity | J23: Y | K23: `normalizeApplicantType(...)` => `Individual`/`Company`. | N23: =IFERROR(XLOOKUP($F23&"."&$G23,CaseSource!$A$2:$A$371,CaseSource!$B$2:$B$371,""),"")
A24: primaryMobile | B24: Profile | C24: Emicustomer Details | D24: Always | F24: CPV_DETAIL.json | G24: OFF_PHONE1 | H24: 1 | I24: identity | J24: Y | K24: Clean numeric text. | N24: =IFERROR(XLOOKUP($F24&"."&$G24,CaseSource!$A$2:$A$371,CaseSource!$B$2:$B$371,""),"")
A25: primaryMobile | B25: Profile | C25: Emicustomer Details | D25: Always | F25: GURANTOR.json | G25: OFF_PHONE | H25: 2 | I25: identity | J25: Y | K25: Clean numeric text. | N25: =IFERROR(XLOOKUP($F25&"."&$G25,CaseSource!$A$2:$A$371,CaseSource!$B$2:$B$371,""),"")
A26: primaryMobile | B26: Profile | C26: Emicustomer Details | D26: Always | F26: RC_CUSTOMER_ACCOUNT.json | G26: PHONE_NUMBERS_OFFICE | H26: 3 | I26: identity | J26: Y | K26: Clean numeric text. | N26: =IFERROR(XLOOKUP($F26&"."&$G26,CaseSource!$A$2:$A$371,CaseSource!$B$2:$B$371,""),"")
A27: primaryMobile | B27: Profile | C27: Emicustomer Details | D27: Always | F27: AUTH_SIGNATORY.json | G27: PHONE | H27: 4 | I27: identity | J27: Y | K27: Clean numeric text. | N27: =IFERROR(XLOOKUP($F27&"."&$G27,CaseSource!$A$2:$A$371,CaseSource!$B$2:$B$371,""),"")
A28: primaryMobile | B28: Profile | C28: Emicustomer Details | D28: Always | F28: CPV_DETAIL.json | G28: RESI_PHONE1 | H28: 5 | I28: identity | J28: Y | K28: Clean numeric text. | N28: =IFERROR(XLOOKUP($F28&"."&$G28,CaseSource!$A$2:$A$371,CaseSource!$B$2:$B$371,""),"")
A29: primaryMobile | B29: Profile | C29: Emicustomer Details | D29: Always | F29: CPV_DETAIL.json | G29: MOBILE | H29: 6 | I29: identity | J29: Y | K29: Clean numeric text. | N29: =IFERROR(XLOOKUP($F29&"."&$G29,CaseSource!$A$2:$A$371,CaseSource!$B$2:$B$371,""),"")
A30: primaryMobile | B30: Profile | C30: Emicustomer Details | D30: Always | F30: RC_CUSTOMER_ACCOUNT.json | G30: MOBILE_NUMBER | H30: 7 | I30: identity | J30: Y | K30: Clean numeric text. | N30: =IFERROR(XLOOKUP($F30&"."&$G30,CaseSource!$A$2:$A$371,CaseSource!$B$2:$B$371,""),"")
A31: primaryMobile | B31: Profile | C31: Emicustomer Details | D31: Always | F31: RC_CUSTOMER_ACCOUNT.json | G31: PHONE_NUMBERS_RESI | H31: 8 | I31: identity | J31: Y | K31: Clean numeric text. | N31: =IFERROR(XLOOKUP($F31&"."&$G31,CaseSource!$A$2:$A$371,CaseSource!$B$2:$B$371,""),"")
A32: primaryMobileAlt | D32: Always | F32: CPV_DETAIL.json | G32: RESI_PHONE2 | H32: 1 | I32: identity | J32: Y | K32: First number different from primary. | N32: =IFERROR(XLOOKUP($F32&"."&$G32,CaseSource!$A$2:$A$371,CaseSource!$B$2:$B$371,""),"")
A33: primaryMobileAlt | D33: Always | F33: GURANTOR.json | G33: RESI_PHONE | H33: 2 | I33: identity | J33: Y | K33: First number different from primary. | N33: =IFERROR(XLOOKUP($F33&"."&$G33,CaseSource!$A$2:$A$371,CaseSource!$B$2:$B$371,""),"")
A34: primaryMobileAlt | D34: Always | F34: GURANTOR.json | G34: OFF_PHONE | H34: 3 | I34: identity | J34: Y | K34: First number different from primary. | N34: =IFERROR(XLOOKUP($F34&"."&$G34,CaseSource!$A$2:$A$371,CaseSource!$B$2:$B$371,""),"")
A35: primaryMobileAlt | D35: Always | F35: CPV_DETAIL.json | G35: OFF_PHONE1 | H35: 4 | I35: identity | J35: Y | K35: First number different from primary. | N35: =IFERROR(XLOOKUP($F35&"."&$G35,CaseSource!$A$2:$A$371,CaseSource!$B$2:$B$371,""),"")
A36: email | B36: Profile | C36: Emicustomer Details | D36: Always | F36: CPV_DETAIL.json | G36: E_MAIL | H36: 1 | I36: identity | J36: Y | K36: clean text | N36: =IFERROR(XLOOKUP($F36&"."&$G36,CaseSource!$A$2:$A$371,CaseSource!$B$2:$B$371,""),"")
A37: email | B37: Profile | C37: Emicustomer Details | D37: Always | F37: CPV_DETAIL.json | G37: EMAIL_ADDRESS | H37: 2 | I37: identity | J37: Y | K37: clean text | N37: =IFERROR(XLOOKUP($F37&"."&$G37,CaseSource!$A$2:$A$371,CaseSource!$B$2:$B$371,""),"")
A38: panNumber | B38: Header / Shared | C38: Loan Sticky Header | D38: Always | F38: CPV_DETAIL.json | G38: PAN_NUMBER | H38: 1 | I38: identity | J38: Y | K38: clean text | N38: =IFERROR(XLOOKUP($F38&"."&$G38,CaseSource!$A$2:$A$371,CaseSource!$B$2:$B$371,""),"")
A39: gstNumber | D39: Always | F39: CPV_DETAIL.json | G39: GST_NUMBER | H39: 1 | I39: identity | J39: Y | K39: company flow only | N39: =IFERROR(XLOOKUP($F39&"."&$G39,CaseSource!$A$2:$A$371,CaseSource!$B$2:$B$371,""),"")
A40: gstNumber | D40: Always | F40: RC_CUSTOMER_ACCOUNT.json | G40: GST_NUMBER | H40: 2 | I40: identity | J40: Y | K40: company flow only | N40: =IFERROR(XLOOKUP($F40&"."&$G40,CaseSource!$A$2:$A$371,CaseSource!$B$2:$B$371,""),"")
A41: residenceAddress | B41: Pre-File | C41: Loan Sticky Header | D41: Always | F41: CPV_DETAIL.json | G41: OFF_ADD1 | H41: 1 | I41: identity | J41: Y | K41: joined cleaned text | N41: =IFERROR(XLOOKUP($F41&"."&$G41,CaseSource!$A$2:$A$371,CaseSource!$B$2:$B$371,""),"")
A42: residenceAddress | B42: Pre-File | C42: Loan Sticky Header | D42: Always | F42: CPV_DETAIL.json | G42: RESI_ADD1 | H42: 2 | I42: identity | J42: Y | K42: joined cleaned text | N42: =IFERROR(XLOOKUP($F42&"."&$G42,CaseSource!$A$2:$A$371,CaseSource!$B$2:$B$371,""),"")
A43: residenceAddress | B43: Pre-File | C43: Loan Sticky Header | D43: Always | F43: CPV_DETAIL.json | G43: RESIDENCE_ADDRESS | H43: 3 | I43: identity | J43: Y | K43: joined cleaned text | N43: =IFERROR(XLOOKUP($F43&"."&$G43,CaseSource!$A$2:$A$371,CaseSource!$B$2:$B$371,""),"")
A44: residenceAddress | B44: Pre-File | C44: Loan Sticky Header | D44: Always | F44: CPV_DETAIL.json | G44: RESI_ADDRESS | H44: 4 | I44: identity | J44: Y | K44: joined cleaned text | N44: =IFERROR(XLOOKUP($F44&"."&$G44,CaseSource!$A$2:$A$371,CaseSource!$B$2:$B$371,""),"")
A45: residenceAddress | B45: Pre-File | C45: Loan Sticky Header | D45: Always | F45: RC_CUSTOMER_ACCOUNT.json | G45: RESI_ADDRESS | H45: 5 | I45: identity | J45: Y | K45: joined cleaned text | N45: =IFERROR(XLOOKUP($F45&"."&$G45,CaseSource!$A$2:$A$371,CaseSource!$B$2:$B$371,""),"")
A46: residenceAddress | B46: Pre-File | C46: Loan Sticky Header | D46: Always | F46: RC_CUSTOMER_ACCOUNT.json | G46: CUST_ADDRESS | H46: 6 | I46: identity | J46: Y | K46: joined cleaned text | N46: =IFERROR(XLOOKUP($F46&"."&$G46,CaseSource!$A$2:$A$371,CaseSource!$B$2:$B$371,""),"")
A47: residenceAddress | B47: Pre-File | C47: Loan Sticky Header | D47: Always | F47: RC_CUSTOMER_ACCOUNT.json | G47: ADDRESS | H47: 7 | I47: identity | J47: Y | K47: joined cleaned text | N47: =IFERROR(XLOOKUP($F47&"."&$G47,CaseSource!$A$2:$A$371,CaseSource!$B$2:$B$371,""),"")
A48: pincode | B48: Pre-File | C48: Personal Details Pre File | D48: Always | F48: CPV_DETAIL.json | G48: OFF_PIN | H48: 1 | I48: identity | J48: Y | K48: clean | N48: =IFERROR(XLOOKUP($F48&"."&$G48,CaseSource!$A$2:$A$371,CaseSource!$B$2:$B$371,""),"")
A49: pincode | B49: Pre-File | C49: Personal Details Pre File | D49: Always | F49: CPV_DETAIL.json | G49: RESI_PIN | H49: 2 | I49: identity | J49: Y | K49: clean | N49: =IFERROR(XLOOKUP($F49&"."&$G49,CaseSource!$A$2:$A$371,CaseSource!$B$2:$B$371,""),"")
A50: city | B50: Pre-File | C50: Loan Sticky Header | D50: Always | F50: CPV_DETAIL.json | G50: OFF_CITY | H50: 1 | I50: identity | J50: Y | K50: clean | N50: =IFERROR(XLOOKUP($F50&"."&$G50,CaseSource!$A$2:$A$371,CaseSource!$B$2:$B$371,""),"")
A51: city | B51: Pre-File | C51: Loan Sticky Header | D51: Always | F51: CPV_DETAIL.json | G51: RESI_CITY | H51: 2 | I51: identity | J51: Y | K51: clean | N51: =IFERROR(XLOOKUP($F51&"."&$G51,CaseSource!$A$2:$A$371,CaseSource!$B$2:$B$371,""),"")
A52: permanentAddress | B52: Pre-File | C52: Loan Sticky Header | D52: Always | F52: CPV_DETAIL.json | G52: PERMANENT_ADDRESS | H52: 1 | I52: identity | J52: Y | K52: Parsed; if empty/NA then same as current. | N52: =IFERROR(XLOOKUP($F52&"."&$G52,CaseSource!$A$2:$A$371,CaseSource!$B$2:$B$371,""),"")
... A62: purposeOfLoan | B62: Pre-File | C62: Vehicle Pricing Loan Details | D62: Always | F62: CPV_DETAIL.json | G62: PURPOSE_OF_LOAN | H62: 1 | I62: identity | J62: Y | K62: normalized with loan-type rules | N62: =IFERROR(XLOOKUP($F62&"."&$G62,CaseSource!$A$2:$A$371,CaseSource!$B$2:$B$371,""),"")
A63: loan_number | D63: Always | F63: RC_CUSTOMER_ACCOUNT.json | G63: LOAN_NUMBER_PREFIX | H63: 1 | I63: identity | J63: Y | K63: concatenated available parts | N63: =IFERROR(XLOOKUP($F63&"."&$G63,CaseSource!$A$2:$A$371,CaseSource!$B$2:$B$371,""),"")
A64: loanTenureMonths | B64: Profile | C64: Finance Details Form | D64: Always | F64: RC_CUSTOMER_ACCOUNT.json | G64: TENOR | H64: 1 | I64: identity | J64: Y | K64: numeric | N64: =IFERROR(XLOOKUP($F64&"."&$G64,CaseSource!$A$2:$A$371,CaseSource!$B$2:$B$371,""),"")
A65: loanTenureMonths | B65: Profile | C65: Finance Details Form | D65: Always | F65: RC_CUSTOMER_ACCOUNT.json | G65: APPLIED_TENOR | H65: 2 | I65: identity | J65: Y | K65: numeric | N65: =IFERROR(XLOOKUP($F65&"."&$G65,CaseSource!$A$2:$A$371,CaseSource!$B$2:$B$371,""),"")
A66: loanTenureMonths | B66: Profile | C66: Finance Details Form | D66: Always | F66: CPV_DETAIL.json | G66: TENDOR | H66: 3 | I66: identity | J66: Y | K66: numeric | N66: =IFERROR(XLOOKUP($F66&"."&$G66,CaseSource!$A$2:$A$371,CaseSource!$B$2:$B$371,""),"")
A67: financeExpectation | B67: Profile | C67: Loan Sticky Header | D67: Always | F67: RC_CUSTOMER_ACCOUNT.json | G67: LOAN_AMOUNT | H67: 1 | I67: identity | J67: Y | K67: numeric | N67: =IFERROR(XLOOKUP($F67&"."&$G67,CaseSource!$A$2:$A$371,CaseSource!$B$2:$B$371,""),"")
A68: financeExpectation | B68: Profile | C68: Loan Sticky Header | D68: Always | F68: RC_CUSTOMER_ACCOUNT.json | G68: APPLIED_LOAN_AMOUNT | H68: 2 | I68: identity | J68: Y | K68: numeric | N68: =IFERROR(XLOOKUP($F68&"."&$G68,CaseSource!$A$2:$A$371,CaseSource!$B$2:$B$371,""),"")
A69: financeExpectation | B69: Profile | C69: Loan Sticky Header | D69: Always | F69: CPV_DETAIL.json | G69: LOAN_EXPECTED | H69: 3 | I69: identity | J69: Y | K69: numeric | N69: =IFERROR(XLOOKUP($F69&"."&$G69,CaseSource!$A$2:$A$371,CaseSource!$B$2:$B$371,""),"")
A70: hypothecationBank | B70: Pre-File | C70: Vehicle Pricing Loan Details | D70: Always | F70: RC_CUSTOMER_ACCOUNT.json | G70: HP_TO | H70: 1 | I70: identity | J70: Y | K70: normalized bank name | N70: =IFERROR(XLOOKUP($F70&"."&$G70,CaseSource!$A$2:$A$371,CaseSource!$B$2:$B$371,""),"")
A71: hypothecationBank | B71: Pre-File | C71: Vehicle Pricing Loan Details | D71: Always | F71: CPV_DETAIL.json | G71: FINANCER | H71: 2 | I71: identity | J71: Y | K71: normalized bank name | N71: =IFERROR(XLOOKUP($F71&"."&$G71,CaseSource!$A$2:$A$371,CaseSource!$B$2:$B$371,""),"")
A72: bankName | B72: Pre-File | C72: Loan Form With Steps | D72: Always | F72: CUSTOMER_BANK.json | G72: BANK_NAME | H72: 1 | I72: identity | J72: Y | K72: normalized bank name | N72: =IFERROR(XLOOKUP($F72&"."&$G72,CaseSource!$A$2:$A$371,CaseSource!$B$2:$B$371,""),"")
A73: accountNumber | B73: Pre-File | C73: Post File Dispatch And Records | D73: Always | F73: CUSTOMER_BANK.json | G73: CA_ACCOUNT_NO | H73: 1 | I73: identity | J73: Y | K73: clean | N73: =IFERROR(XLOOKUP($F73&"."&$G73,CaseSource!$A$2:$A$371,CaseSource!$B$2:$B$371,""),"")
A74: accountNumber | B74: Pre-File | C74: Post File Dispatch And Records | D74: Always | F74: CUSTOMER_BANK.json | G74: SB_ACCOUNT_NO | H74: 2 | I74: identity | J74: Y | K74: clean | N74: =IFERROR(XLOOKUP($F74&"."&$G74,CaseSource!$A$2:$A$371,CaseSource!$B$2:$B$371,""),"")
A75: branch | B75: Pre-File | C75: Post File Dispatch And Records | D75: Always | F75: CUSTOMER_BANK.json | G75: BANK_ADDRESS | H75: 1 | I75: identity | J75: Y | K75: clean | N75: =IFERROR(XLOOKUP($F75&"."&$G75,CaseSource!$A$2:$A$371,CaseSource!$B$2:$B$371,""),"")
A76: totalIncome | D76: Always | F76: CPV_DETAIL.json | G76: ANNUAL_INCOME | H76: 1 | I76: identity | J76: Y | K76: numeric | N76: =IFERROR(XLOOKUP($F76&"."&$G76,CaseSource!$A$2:$A$371,CaseSource!$B$2:$B$371,""),"")
A77: totalIncomeITR | B77: Pre-File | C77: Income Banking Details Pre File | D77: Always | F77: CPV_DETAIL.json | G77: ANNUAL_INCOME | H77: 1 | I77: identity | J77: Y | K77: numeric | N77: =IFERROR(XLOOKUP($F77&"."&$G77,CaseSource!$A$2:$A$371,CaseSource!$B$2:$B$371,""),"")
A78: dob | B78: Pre-File | C78: Personal Details Pre File | D78: Always | F78: CPV_DETAIL.json | G78: DATE_OF_BIRTH | H78: 1 | I78: identity | J78: Y | K78: ISO date | N78: =IFERROR(XLOOKUP($F78&"."&$G78,CaseSource!$A$2:$A$371,CaseSource!$B$2:$B$371,""),"")
A79: gender | B79: Pre-File | C79: Personal Details Pre File | D79: Always | F79: CPV_DETAIL.json | G79: SEX | H79: 1 | I79: identity | J79: Y | K79: normalized | N79: =IFERROR(XLOOKUP($F79&"."&$G79,CaseSource!$A$2:$A$371,CaseSource!$B$2:$B$371,""),"")
A80: motherName | B80: Pre-File | C80: Personal Details Pre File | D80: Always | F80: CPV_DETAIL.json | G80: MOTHERS_MAIDEN_NAME | H80: 1 | I80: identity | J80: Y | K80: clean | N80: =IFERROR(XLOOKUP($F80&"."&$G80,CaseSource!$A$2:$A$371,CaseSource!$B$2:$B$371,""),"")
A81: sdwOf | B81: Pre-File | C81: Personal Details Pre File | D81: Always | F81: CPV_DETAIL.json | G81: FATHERS_NAME_FIRST | H81: 1 | I81: identity | J81: Y | K81: clean | N81: =IFERROR(XLOOKUP($F81&"."&$G81,CaseSource!$A$2:$A$371,CaseSource!$B$2:$B$371,""),"")
A82: maritalStatus | B82: Profile | C82: Personal Details Simplified | D82: Always | F82: CPV_DETAIL.json | G82: MARITAL_STATUS | H82: 1 | I82: identity | J82: Y | K82: normalized | N82: =IFERROR(XLOOKUP($F82&"."&$G82,CaseSource!$A$2:$A$371,CaseSource!$B$2:$B$371,""),"")
A83: dependents | B83: Profile | C83: Personal Details Simplified | D83: Always | F83: CPV_DETAIL.json | G83: NO_OF_DEPENDANTS | H83: 1 | I83: identity | J83: Y | K83: numeric | N83: =IFERROR(XLOOKUP($F83&"."&$G83,CaseSource!$A$2:$A$371,CaseSource!$B$2:$B$371,""),"")
A84: education | B84: Pre-File | C84: Personal Details Pre File | D84: Always | F84: CPV_DETAIL.json | G84: EDUCATION | H84: 1 | I84: identity | J84: Y | K84: normalized | N84: =IFERROR(XLOOKUP($F84&"."&$G84,CaseSource!$A$2:$A$371,CaseSource!$B$2:$B$371,""),"")
A85: houseType | B85: Profile | C85: Personal Details Simplified | D85: Always | F85: CPV_DETAIL.json | G85: RESIDENCE_TYPE | H85: 1 | I85: identity | J85: Y | K85: normalized (e.g., your own->Owned) | N85: =IFERROR(XLOOKUP($F85&"."&$G85,CaseSource!$A$2:$A$371,CaseSource!$B$2:$B$371,""),"")
A86: yearsInCurrentCity | B86: Pre-File | C86: Personal Details Pre File | D86: Always | F86: CPV_DETAIL.json | G86: YEARS_AT_RESIDENCE | H86: 1 | I86: identity | J86: Y | K86: numeric | N86: =IFERROR(XLOOKUP($F86&"."&$G86,CaseSource!$A$2:$A$371,CaseSource!$B$2:$B$371,""),"")
A87: yearsInCurrentHouse | B87: Profile | C87: Personal Details Simplified | D87: Always | F87: CPV_DETAIL.json | G87: YEARS_AT_RESIDENCE | H87: 1 | I87: identity | J87: Y | K87: numeric | N87: =IFERROR(XLOOKUP($F87&"."&$G87,CaseSource!$A$2:$A$371,CaseSource!$B$2:$B$371,""),"")
A88: identityProofNumber | B88: Pre-File | C88: Personal Details Pre File | D88: Always | F88: CPV_DETAIL.json | G88: AADHAAR_NUMBER | H88: 1 | I88: identity | J88: Y | K88: clean | N88: =IFERROR(XLOOKUP($F88&"."&$G88,CaseSource!$A$2:$A$371,CaseSource!$B$2:$B$371,""),"")
... A100: employmentCity | B100: Pre-File | C100: Occupational Details Pre File | D100: Always | F100: CPV_DETAIL.json | G100: OFF_CITY | H100: 1 | I100: identity | J100: Y | K100: clean | N100: =IFERROR(XLOOKUP($F100&"."&$G100,CaseSource!$A$2:$A$371,CaseSource!$B$2:$B$371,""),"")
A101: reference1_* | D101: Always | F101: CPV_DETAIL.json | G101: REF1_NAME | H101: 1 | I101: identity | J101: Y | K101: `pincode` extracted from address (2-digit Delhi suffix -> `1100xx` rule in helper); city guessed. | N101: =IFERROR(XLOOKUP($F101&"."&$G101,CaseSource!$A$2:$A$371,CaseSource!$B$2:$B$371,""),"")
A102: reference2_* | D102: Always | F102: CPV_DETAIL.json | G102: REF2_NAME | H102: 1 | I102: identity | J102: Y | K102: same as above | N102: =IFERROR(XLOOKUP($F102&"."&$G102,CaseSource!$A$2:$A$371,CaseSource!$B$2:$B$371,""),"")
A103: referenceName` (record details) | D103: Always | F103: RC_SOURCE_REFERENCE.json | G103: REFERENCE_BY | H103: 1 | I103: identity | J103: Y | K103: pre-file record section | N103: =IFERROR(XLOOKUP($F103&"."&$G103,CaseSource!$A$2:$A$371,CaseSource!$B$2:$B$371,""),"")
A104: referenceNumber` (record details) | D104: Always | F104: RC_SOURCE_REFERENCE.json | G104: PHONE_NUMBER | H104: 1 | I104: identity | J104: Y | K104: pre-file record section | N104: =IFERROR(XLOOKUP($F104&"."&$G104,CaseSource!$A$2:$A$371,CaseSource!$B$2:$B$371,""),"")
A105: recordSource | B105: Profile | C105: Lead Details | D105: Always | F105: RC_CUSTOMER_ACCOUNT.json | G105: SOURCE | H105: 1 | I105: identity | J105: Y | K105: default `Direct` | N105: =IFERROR(XLOOKUP($F105&"."&$G105,CaseSource!$A$2:$A$371,CaseSource!$B$2:$B$371,""),"")
A106: sourceName | B106: Profile | C106: Lead Details | D106: Record source = Indirect (or available source capture) | E106: Map from SOURCE-like legacy field. Do NOT swap with dealtBy. | F106: CPV_DETAIL.json | G106: SOURCE_BY | H106: 1 | I106: identity | J106: Y | K106: normalized | N106: =IFERROR(XLOOKUP($F106&"."&$G106,CaseSource!$A$2:$A$371,CaseSource!$B$2:$B$371,""),"")
A107: sourceName | B107: Profile | C107: Lead Details | D107: Record source = Indirect (or available source capture) | E107: Map from SOURCE-like legacy field. Do NOT swap with dealtBy. | F107: RC_SOURCE_REFERENCE.json | G107: SOURCE_NAME | H107: 2 | I107: identity | J107: Y | K107: normalized | N107: =IFERROR(XLOOKUP($F107&"."&$G107,CaseSource!$A$2:$A$371,CaseSource!$B$2:$B$371,""),"")
A108: sourceName | B108: Profile | C108: Lead Details | D108: Record source = Indirect (or available source capture) | E108: Map from SOURCE-like legacy field. Do NOT swap with dealtBy. | F108: RC_CUSTOMER_ACCOUNT.json | G108: CASE_ORIGIN | H108: 3 | I108: identity | J108: Y | K108: normalized | N108: =IFERROR(XLOOKUP($F108&"."&$G108,CaseSource!$A$2:$A$371,CaseSource!$B$2:$B$371,""),"")
A109: docsPreparedBy | B109: Pre-File | C109: Section7Record Details | D109: Pre-file/Post-file record details | E109: Map from PRE/POST docs prepared-by chain, not source channel. | F109: RC_DOC_DESPATCH_MASTER.json | G109: DOCS_PREPARED_BY | H109: 1 | I109: identity | J109: Y | K109: clean | N109: =IFERROR(XLOOKUP($F109&"."&$G109,CaseSource!$A$2:$A$371,CaseSource!$B$2:$B$371,""),"")
A110: docsPreparedBy | B110: Pre-File | C110: Section7Record Details | D110: Pre-file/Post-file record details | E110: Map from PRE/POST docs prepared-by chain, not source channel. | F110: RC_CUSTOMER_ACCOUNT.json | G110: PRE_DOCS_PREPARED_BY | H110: 2 | I110: identity | J110: Y | K110: clean | N110: =IFERROR(XLOOKUP($F110&"."&$G110,CaseSource!$A$2:$A$371,CaseSource!$B$2:$B$371,""),"")
A111: dsaCode | D111: Always | F111: RC_CUSTOMER_ACCOUNT.json | G111: DSA_CODE | H111: 1 | I111: identity | J111: Y | K111: clean | N111: =IFERROR(XLOOKUP($F111&"."&$G111,CaseSource!$A$2:$A$371,CaseSource!$B$2:$B$371,""),"")
A112: dealerName | B112: Profile | C112: Lead Details | D112: Always | F112: RC_CUSTOMER_ACCOUNT.json | G112: PAYMENT_FAVOURING_AT_DESPATCH | H112: 1 | I112: identity | J112: Y | K112: ignored if literal `customer name` | N112: =IFERROR(XLOOKUP($F112&"."&$G112,CaseSource!$A$2:$A$371,CaseSource!$B$2:$B$371,""),"")
A113: receivingDate | B113: Pre-File | C113: Section7Record Details | D113: Always | F113: RC_CUSTOMER_ACCOUNT.json | G113: DATE_WHEN_FILE_RECEIVED | H113: 1 | I113: identity | J113: Y | K113: date | N113: =IFERROR(XLOOKUP($F113&"."&$G113,CaseSource!$A$2:$A$371,CaseSource!$B$2:$B$371,""),"")
A114: receivingDate | B114: Pre-File | C114: Section7Record Details | D114: Always | F114: RC_DOC_DESPATCH_MASTER.json | G114: DATE_OF_DESP | H114: 2 | I114: identity | J114: Y | K114: date | N114: =IFERROR(XLOOKUP($F114&"."&$G114,CaseSource!$A$2:$A$371,CaseSource!$B$2:$B$371,""),"")
A115: receivingDate | B115: Pre-File | C115: Section7Record Details | D115: Always | F115: CPV_DETAIL.json | G115: CPV_DATE | H115: 3 | I115: identity | J115: Y | K115: date | N115: =IFERROR(XLOOKUP($F115&"."&$G115,CaseSource!$A$2:$A$371,CaseSource!$B$2:$B$371,""),"")
A116: receivingTime | B116: Pre-File | C116: Section7Record Details | D116: Always | F116: RC_CUSTOMER_ACCOUNT.json | G116: TIME_WHEN_FILE_RECEIVED | H116: 1 | I116: identity | J116: Y | K116: time normalize | N116: =IFERROR(XLOOKUP($F116&"."&$G116,CaseSource!$A$2:$A$371,CaseSource!$B$2:$B$371,""),"")
A117: receivingTime | B117: Pre-File | C117: Section7Record Details | D117: Always | F117: RC_DOC_DESPATCH_MASTER.json | G117: TIME_OF_DESP | H117: 2 | I117: identity | J117: Y | K117: time normalize | N117: =IFERROR(XLOOKUP($F117&"."&$G117,CaseSource!$A$2:$A$371,CaseSource!$B$2:$B$371,""),"")
A118: approval_bankName` / `postfile_bankName | D118: Always | F118: RC_CUSTOMER_ACCOUNT.json | G118: HP_TO | H118: 1 | I118: identity | J118: Y | K118: bank normalization | N118: =IFERROR(XLOOKUP($F118&"."&$G118,CaseSource!$A$2:$A$371,CaseSource!$B$2:$B$371,""),"")
A119: approval_bankName` / `postfile_bankName | D119: Always | F119: CPV_DETAIL.json | G119: FINANCER | H119: 2 | I119: identity | J119: Y | K119: bank normalization | N119: =IFERROR(XLOOKUP($F119&"."&$G119,CaseSource!$A$2:$A$371,CaseSource!$B$2:$B$371,""),"")
A120: approval_loanAmountApproved` / `postfile_loanAmountApproved | D120: Always | F120: RC_CUSTOMER_ACCOUNT.json | G120: LOAN_AMOUNT | H120: 1 | I120: identity | J120: Y | K120: numeric | N120: =IFERROR(XLOOKUP($F120&"."&$G120,CaseSource!$A$2:$A$371,CaseSource!$B$2:$B$371,""),"")
A121: approval_loanAmountApproved` / `postfile_loanAmountApproved | D121: Always | F121: CPV_DETAIL.json | G121: LOAN_EXPECTED | H121: 2 | I121: identity | J121: Y | K121: numeric | N121: =IFERROR(XLOOKUP($F121&"."&$G121,CaseSource!$A$2:$A$371,CaseSource!$B$2:$B$371,""),"")
A122: approval_roi` / `postfile_roi | D122: Always | F122: RC_CUSTOMER_ACCOUNT.json | G122: ROI | H122: 1 | I122: identity | J122: Y | K122: numeric | N122: =IFERROR(XLOOKUP($F122&"."&$G122,CaseSource!$A$2:$A$371,CaseSource!$B$2:$B$371,""),"")
A123: approval_tenureMonths` / `postfile_tenureMonths | D123: Always | F123: RC_CUSTOMER_ACCOUNT.json | G123: TENOR | H123: 1 | I123: identity | J123: Y | K123: numeric | N123: =IFERROR(XLOOKUP($F123&"."&$G123,CaseSource!$A$2:$A$371,CaseSource!$B$2:$B$371,""),"")
A124: approval_tenureMonths` / `postfile_tenureMonths | D124: Always | F124: CPV_DETAIL.json | G124: TENDOR | H124: 2 | I124: identity | J124: Y | K124: numeric | N124: =IFERROR(XLOOKUP($F124&"."&$G124,CaseSource!$A$2:$A$371,CaseSource!$B$2:$B$371,""),"")
A125: approval_approvalDate | B125: Approval | C125: Loan Form With Steps | D125: Financed flow | E125: For legacy migration, use disbursement date when explicit approval date is absent. | F125: RC_CUSTOMER_ACCOUNT.json | G125: DATE_OF_DISBURSE | H125: 1 | I125: identity | J125: Y | K125: ISO | N125: =IFERROR(XLOOKUP($F125&"."&$G125,CaseSource!$A$2:$A$371,CaseSource!$B$2:$B$371,""),"")
A126: approval_approvalDate | B126: Approval | C126: Loan Form With Steps | D126: Financed flow | E126: For legacy migration, use disbursement date when explicit approval date is absent. | F126: RC_RC_INV_STATUS.json | G126: DATE_OF_DISBURSE | H126: 2 | I126: identity | J126: Y | K126: ISO | N126: =IFERROR(XLOOKUP($F126&"."&$G126,CaseSource!$A$2:$A$371,CaseSource!$B$2:$B$371,""),"")
...

Sheet NewFieldCatalog
A1: new_field | B1: new_type | C1: new_page | D1: new_section | E1: applies_when | F1: flow_notes | G1: new_source_files
A2: aadhaarCardDocUrl | B2: string | C2: Post-File | D2: Documents List | E2: Always | G2: src/modules/loans/components/loan-form/post-file/DocumentsList.jsx; src/modules/loans/components/loan-form/post-file/PostFileDocumentManagement.jsx
A3: aadhaarNumber | B3: string | C3: Header / Shared | D3: Loan Sticky Header | E3: Always | G3: src/modules/loans/components/LoanStickyHeader.jsx
A4: accessoriesAmount | B4: number | C4: Pre-File | D4: Post File Vehicle Verification | E4: Always | G4: src/modules/loans/components/loan-form/post-file/PostFileVehicleVerification.jsx; src/modules/loans/components/loan-form/pre-file/VehiclePricingLoanDetails.jsx
A5: accountNumber | B5: number | C5: Pre-File | D5: Post File Dispatch And Records | E5: Always | G5: src/modules/loans/components/loan-form/post-file/PostFileDispatchAndRecords.jsx; src/modules/loans/components/loan-form/pre-file/IncomeBankingDetailsPreFile.jsx
A6: accountSinceYears | B6: number | C6: Pre-File | D6: Income Banking Details Pre File | E6: Always | G6: src/modules/loans/components/loan-form/pre-file/IncomeBankingDetailsPreFile.jsx
A7: accountType | B7: string | C7: Pre-File | D7: Income Banking Details Pre File | E7: Always | G7: src/modules/loans/components/loan-form/pre-file/IncomeBankingDetailsPreFile.jsx
A8: addressProofDocUrl | B8: string | C8: Post-File | D8: Documents List | E8: Always | G8: src/modules/loans/components/loan-form/post-file/DocumentsList.jsx; src/modules/loans/components/loan-form/post-file/PostFileDocumentManagement.jsx
A9: addressProofNumber | B9: boolean | C9: Pre-File | D9: Personal Details Pre File | E9: Always | G9: src/modules/loans/components/loan-form/pre-file/PersonalDetailsPreFile.jsx
A10: addressProofType | B10: boolean | C10: Pre-File | D10: Personal Details Pre File | E10: Always | G10: src/modules/loans/components/loan-form/pre-file/PersonalDetailsPreFile.jsx
A11: addressType | B11: number | C11: Pre-File | D11: Personal Details Pre File | E11: Always | G11: src/modules/loans/components/loan-form/pre-file/PersonalDetailsPreFile.jsx
A12: advanceEmi | B12: number | C12: Pre-File | D12: Vehicle Pricing Loan Details | E12: Always | G12: src/modules/loans/components/loan-form/pre-file/VehiclePricingLoanDetails.jsx
A13: applicantType | B13: string | C13: Profile | D13: Lead Details | E13: Always | F13: Individual vs Company changes form visibility and required sections. | G13: src/modules/loans/components/loan-form/customer-profile/LeadDetails.jsx; src/modules/loans/components/loan-form/pre-file/AuthorisedSignatorySection.jsx; src/modules/loans/components/loan-form/pre-file/OccupationalDetailsPreFile.jsx
A14: approval_approvalDate | B14: string | C14: Approval | D14: Loan Form With Steps | E14: Financed flow | F14: For legacy migration, use disbursement date when explicit approval date is absent. | G14: src/modules/loans/components/LoanFormWithSteps.jsx; src/modules/loans/components/loan-form/loan-approval/LoanApprovalStep.jsx
A15: approval_bankId | B15: string | C15: Approval | D15: Loan Form With Steps | E15: Always | G15: src/modules/loans/components/LoanFormWithSteps.jsx; src/modules/loans/components/loan-form/loan-approval/LoanApprovalStep.jsx
A16: approval_bankName | B16: string | C16: Approval | D16: Loan Form With Steps | E16: Always | G16: src/modules/loans/components/LoanFormWithSteps.jsx; src/modules/loans/components/LoanStickyHeader.jsx; src/modules/loans/components/loan-form/loan-approval/LoanApprovalStep.jsx; src/modules/loans/components/loan-form/payout/PayoutSection.jsx; src/modules/loans/components/loan-form/post-file/PostFileApprovalDetails.jsx; src/modules/loans/components/loan-form/vehicle-delivery/VehicleDeliveryStep.jsx
A17: approval_banksData | B17: string | C17: Shared | D17: Loan Form With Steps | E17: Always | G17: src/modules/loans/components/LoanFormWithSteps.jsx
A18: approval_breakup_creditAssured | B18: string | C18: Approval | D18: Loan Form With Steps | E18: Always | G18: src/modules/loans/components/LoanFormWithSteps.jsx; src/modules/loans/components/loan-form/loan-approval/LoanApprovalStep.jsx
A19: approval_breakup_ewFinance | B19: string | C19: Approval | D19: Loan Form With Steps | E19: Always | G19: src/modules/loans/components/LoanFormWithSteps.jsx; src/modules/loans/components/loan-form/loan-approval/LoanApprovalStep.jsx
A20: approval_breakup_insuranceFinance | B20: string | C20: Approval | D20: Loan Form With Steps | E20: Always | G20: src/modules/loans/components/LoanFormWithSteps.jsx; src/modules/loans/components/loan-form/loan-approval/LoanApprovalStep.jsx
A21: approval_breakup_netLoanApproved | B21: string | C21: Approval | D21: Loan Form With Steps | E21: Always | G21: src/modules/loans/components/LoanFormWithSteps.jsx; src/modules/loans/components/loan-form/loan-approval/LoanApprovalStep.jsx; src/modules/loans/components/loan-form/payout/PayoutSection.jsx
A22: approval_disbursedDate | B22: string | C22: Approval | D22: Loan Form With Steps | E22: Financed flow | F22: Critical for post-file/delivery unlock in migrated records. | G22: src/modules/loans/components/LoanFormWithSteps.jsx; src/modules/loans/components/loan-form/loan-approval/LoanApprovalStep.jsx; src/modules/loans/components/loan-form/post-file/PostFileApprovalDetails.jsx
A23: approval_loanAmountApproved | B23: string | C23: Approval | D23: Loan Form With Steps | E23: Always | G23: src/modules/loans/components/LoanFormWithSteps.jsx; src/modules/loans/components/LoanStickyHeader.jsx; src/modules/loans/components/loan-form/loan-approval/LoanApprovalStep.jsx; src/modules/loans/components/loan-form/post-file/PostFileApprovalDetails.jsx
A24: approval_loanAmountDisbursed | B24: string | C24: Approval | D24: Loan Form With Steps | E24: Always | G24: src/modules/loans/components/LoanFormWithSteps.jsx; src/modules/loans/components/loan-form/loan-approval/LoanApprovalStep.jsx; src/modules/loans/components/loan-form/payout/PayoutSection.jsx; src/modules/loans/components/loan-form/post-file/PostFileApprovalDetails.jsx
A25: approval_processingFees | B25: string | C25: Approval | D25: Loan Form With Steps | E25: Always | G25: src/modules/loans/components/LoanFormWithSteps.jsx; src/modules/loans/components/loan-form/loan-approval/LoanApprovalStep.jsx; src/modules/loans/components/loan-form/post-file/PostFileApprovalDetails.jsx
A26: approval_roi | B26: string | C26: Approval | D26: Loan Form With Steps | E26: Always | G26: src/modules/loans/components/LoanFormWithSteps.jsx; src/modules/loans/components/loan-form/loan-approval/LoanApprovalStep.jsx; src/modules/loans/components/loan-form/post-file/PostFileApprovalDetails.jsx
A27: approval_status | B27: string | C27: Approval | D27: Loan Form With Steps | E27: Financed flow | F27: Set approved/disbursed correctly; downstream stages depend on it. | G27: src/modules/loans/components/LoanFormWithSteps.jsx; src/modules/loans/components/LoanStickyHeader.jsx; src/modules/loans/components/loan-form/loan-approval/LoanApprovalStep.jsx; src/modules/loans/components/loan-form/payout/PayoutSection.jsx; src/modules/loans/components/loan-form/post-file/PostFileApprovalDetails.jsx
A28: approval_statusHistory | B28: string | C28: Approval | D28: Loan Approval Step | E28: Always | G28: src/modules/loans/components/loan-form/loan-approval/LoanApprovalStep.jsx
A29: approval_tenureMonths | B29: string | C29: Approval | D29: Loan Form With Steps | E29: Always | G29: src/modules/loans/components/LoanFormWithSteps.jsx; src/modules/loans/components/LoanStickyHeader.jsx; src/modules/loans/components/loan-form/loan-approval/LoanApprovalStep.jsx; src/modules/loans/components/loan-form/post-file/PostFileApprovalDetails.jsx
A30: bankName | B30: string | C30: Pre-File | D30: Loan Form With Steps | E30: Always | G30: src/modules/loans/components/LoanFormWithSteps.jsx; src/modules/loans/components/loan-form/post-file/PostFileDispatchAndRecords.jsx; src/modules/loans/components/loan-form/pre-file/IncomeBankingDetailsPreFile.jsx
A31: billDate | B31: string | C31: Payout | D31: Bill Printing Modal | E31: Always | G31: src/modules/loans/components/loan-form/payout/BillPrintingModal.jsx
A32: billNumber | B32: string | C32: Payout | D32: Bill Printing Modal | E32: Always | G32: src/modules/loans/components/loan-form/payout/BillPrintingModal.jsx
A33: boughtInYear | B33: number | C33: Pre-File | D33: Post File Vehicle Verification | E33: Always | G33: src/modules/loans/components/loan-form/post-file/PostFileVehicleVerification.jsx; src/modules/loans/components/loan-form/pre-file/VehiclePricingLoanDetails.jsx
A34: branch | B34: number | C34: Pre-File | D34: Post File Dispatch And Records | E34: Always | G34: src/modules/loans/components/loan-form/post-file/PostFileDispatchAndRecords.jsx; src/modules/loans/components/loan-form/pre-file/IncomeBankingDetailsPreFile.jsx
A35: bulk_next_action | B35: string | C35: Payout | D35: Payout Receivables Dashboard | E35: Always | G35: src/modules/loans/components/loan-form/payout/PayoutReceivablesDashboard.jsx
A36: bulk_priority | B36: string | C36: Payout | D36: Payout Receivables Dashboard | E36: Always | G36: src/modules/loans/components/loan-form/payout/PayoutReceivablesDashboard.jsx
A37: bulk_remarks | B37: string | C37: Payout | D37: Payout Receivables Dashboard | E37: Always | G37: src/modules/loans/components/loan-form/payout/PayoutReceivablesDashboard.jsx
A38: businessNature | B38: string | C38: Pre-File | D38: Occupational Details Pre File | E38: Always | G38: src/modules/loans/components/loan-form/pre-file/OccupationalDetailsPreFile.jsx
A39: caseType | B39: string | C39: Header / Shared | D39: Loan Sticky Header | E39: Always | G39: src/modules/loans/components/LoanStickyHeader.jsx
... A82: createdAt | B82: string | C82: Header / Shared | D82: Loan Form With Steps | E82: Always | G82: src/modules/loans/components/LoanFormWithSteps.jsx; src/modules/loans/components/LoanStickyHeader.jsx
A83: currentStage | B83: string | C83: Shared | D83: Loan Form With Steps | E83: Always | F83: Must respect legacy approval/disbursement progression for migration cases. | G83: src/modules/loans/components/LoanFormWithSteps.jsx
A84: customerAadhar | B84: string | C84: Header / Shared | D84: Loan Sticky Header | E84: Always | G84: src/modules/loans/components/LoanStickyHeader.jsx
A85: customerAddress | B85: string | C85: Header / Shared | D85: Loan Sticky Header | E85: Always | G85: src/modules/loans/components/LoanStickyHeader.jsx
A86: customerEmail | B86: string | C86: Header / Shared | D86: Loan Sticky Header | E86: Always | G86: src/modules/loans/components/LoanStickyHeader.jsx
A87: customerId | B87: number | C87: Pre-File | D87: Loan Form With Steps | E87: Always | G87: src/modules/loans/components/LoanFormWithSteps.jsx; src/modules/loans/components/loan-form/post-file/PostFileDocumentManagement.jsx; src/modules/loans/components/loan-form/pre-file/IncomeBankingDetailsPreFile.jsx; src/modules/loans/components/loan-form/pre-file/PreFileStep.jsx
A88: customerName | B88: number | C88: Profile | D88: Emicustomer Details | E88: Always | G88: src/modules/loans/components/EMICustomerDetails.jsx; src/modules/loans/components/LoanFormWithSteps.jsx; src/modules/loans/components/LoanStickyHeader.jsx; src/modules/loans/components/loan-form/customer-profile/PersonalDetailsSimplified.jsx; src/modules/loans/components/loan-form/pre-file/PersonalDetailsPreFile.jsx
A89: customerPan | B89: string | C89: Header / Shared | D89: Loan Sticky Header | E89: Always | G89: src/modules/loans/components/LoanStickyHeader.jsx
A90: customerType | B90: string | C90: Post-File | D90: Post File Document Management | E90: Always | G90: src/modules/loans/components/loan-form/post-file/PostFileDocumentManagement.jsx
A91: dealerAddress | B91: string | C91: Profile | D91: Lead Details | E91: Always | G91: src/modules/loans/components/loan-form/customer-profile/LeadDetails.jsx; src/modules/loans/components/loan-form/post-file/PostFileVehicleVerification.jsx; src/modules/loans/components/loan-form/pre-file/Section7RecordDetails.jsx; src/modules/loans/components/loan-form/pre-file/VehiclePricingLoanDetails.jsx
A92: dealerContactNumber | B92: string | C92: Pre-File | D92: Post File Vehicle Verification | E92: Always | G92: src/modules/loans/components/loan-form/post-file/PostFileVehicleVerification.jsx; src/modules/loans/components/loan-form/pre-file/VehiclePricingLoanDetails.jsx
A93: dealerContactPerson | B93: string | C93: Pre-File | D93: Post File Vehicle Verification | E93: Always | G93: src/modules/loans/components/loan-form/post-file/PostFileVehicleVerification.jsx; src/modules/loans/components/loan-form/pre-file/VehiclePricingLoanDetails.jsx
A94: dealerDiscount | B94: number | C94: Pre-File | D94: Vehicle Pricing Popup | E94: Always | G94: src/modules/loans/components/VehiclePricingPopup.jsx; src/modules/loans/components/loan-form/post-file/PostFileVehicleVerification.jsx; src/modules/loans/components/loan-form/pre-file/VehiclePricingLoanDetails.jsx
A95: dealerMobile | B95: string | C95: Profile | D95: Lead Details | E95: Always | G95: src/modules/loans/components/loan-form/customer-profile/LeadDetails.jsx; src/modules/loans/components/loan-form/pre-file/Section7RecordDetails.jsx
A96: dealerName | B96: string | C96: Profile | D96: Lead Details | E96: Always | G96: src/modules/loans/components/loan-form/customer-profile/LeadDetails.jsx; src/modules/loans/components/loan-form/post-file/PostFileVehicleVerification.jsx; src/modules/loans/components/loan-form/pre-file/Section7RecordDetails.jsx; src/modules/loans/components/loan-form/pre-file/VehiclePricingLoanDetails.jsx
A97: dealtBy | B97: string | C97: Profile | D97: Lead Details | E97: Record details / dispatch handling | F97: Map from DEALT_BY-like legacy field. Do NOT swap with sourceName. | G97: src/modules/loans/components/loan-form/customer-profile/LeadDetails.jsx; src/modules/loans/components/loan-form/pre-file/Section7RecordDetails.jsx
A98: delivery_by | B98: string | C98: Delivery | D98: Vehicle Delivery Step | E98: Always | G98: src/modules/loans/components/loan-form/vehicle-delivery/VehicleDeliveryStep.jsx
A99: delivery_date | B99: string | C99: Delivery | D99: Vehicle Delivery Step | E99: Always | G99: src/modules/loans/components/loan-form/vehicle-delivery/VehicleDeliveryStep.jsx
A100: delivery_dealerAddress | B100: string | C100: Delivery | D100: Vehicle Delivery Step | E100: Always | G100: src/modules/loans/components/loan-form/vehicle-delivery/VehicleDeliveryStep.jsx
A101: delivery_dealerContactNumber | B101: string | C101: Delivery | D101: Vehicle Delivery Step | E101: Always | G101: src/modules/loans/components/loan-form/vehicle-delivery/VehicleDeliveryStep.jsx
A102: delivery_dealerContactPerson | B102: string | C102: Delivery | D102: Vehicle Delivery Step | E102: Always | G102: src/modules/loans/components/loan-form/vehicle-delivery/VehicleDeliveryStep.jsx
A103: delivery_dealerName | B103: string | C103: Delivery | D103: Vehicle Delivery Step | E103: Always | G103: src/modules/loans/components/loan-form/vehicle-delivery/VehicleDeliveryStep.jsx
A104: delivery_invoiceFile | B104: string | C104: Post-File | D104: Loan Form With Steps | E104: Always | G104: src/modules/loans/components/LoanFormWithSteps.jsx; src/modules/loans/components/loan-form/post-file/DocumentsList.jsx
A105: delivery_rcFile | B105: string | C105: Post-File | D105: Loan Form With Steps | E105: Always | G105: src/modules/loans/components/LoanFormWithSteps.jsx; src/modules/loans/components/loan-form/post-file/DocumentsList.jsx
A106: deliveryStatus | B106: string | C106: Shared | D106: Loan Form With Steps | E106: Always | G106: src/modules/loans/components/LoanFormWithSteps.jsx
A107: dependents | B107: number | C107: Profile | D107: Personal Details Simplified | E107: Always | G107: src/modules/loans/components/loan-form/customer-profile/PersonalDetailsSimplified.jsx; src/modules/loans/components/loan-form/pre-file/PersonalDetailsPreFile.jsx
A108: designation | B108: string | C108: Pre-File | D108: Authorised Signatory Section | E108: Always | G108: src/modules/loans/components/loan-form/pre-file/AuthorisedSignatorySection.jsx; src/modules/loans/components/loan-form/pre-file/OccupationalDetailsPreFile.jsx
A109: disburse_bankName | B109: string | C109: Shared | D109: Loan Form With Steps | E109: Always | G109: src/modules/loans/components/LoanFormWithSteps.jsx
... A113: disbursedDate | B113: string | C113: Shared | D113: Disbursement Step | E113: Always | G113: src/modules/loans/components/loan-form/disbursement/DisbursementStep.jsx
A114: disbursement_date | B114: string | C114: Post-File | D114: Loan Sticky Header | E114: Financed flow | F114: Keep aligned with approval_disbursedDate. | G114: src/modules/loans/components/LoanStickyHeader.jsx; src/modules/loans/components/loan-form/post-file/PostFileDispatchAndRecords.jsx; src/modules/loans/components/loan-form/post-file/PrincipalOutstanding.jsx
A115: disbursement_status | B115: string | C115: Payout | D115: Payout Section | E115: Always | G115: src/modules/loans/components/loan-form/payout/PayoutSection.jsx
A116: disbursement_time | B116: string | C116: Post-File | D116: Post File Dispatch And Records | E116: Always | G116: src/modules/loans/components/loan-form/post-file/PostFileDispatchAndRecords.jsx
A117: disbursementDate | B117: string | C117: Shared | D117: Disbursement Step | E117: Always | G117: src/modules/loans/components/loan-form/disbursement/DisbursementStep.jsx
A118: disbursementStatus | B118: string | C118: Shared | D118: Disbursement Step | E118: Always | G118: src/modules/loans/components/loan-form/disbursement/DisbursementStep.jsx
A119: dispatch_date | B119: string | C119: Post-File | D119: Post File Dispatch And Records | E119: Always | G119: src/modules/loans/components/loan-form/post-file/PostFileDispatchAndRecords.jsx
A120: dispatch_through | B120: string | C120: Post-File | D120: Post File Dispatch And Records | E120: Always | G120: src/modules/loans/components/loan-form/post-file/PostFileDispatchAndRecords.jsx
A121: dispatch_time | B121: string | C121: Post-File | D121: Post File Dispatch And Records | E121: Always | G121: src/modules/loans/components/loan-form/post-file/PostFileDispatchAndRecords.jsx
A122: dlDocUrl | B122: string | C122: Post-File | D122: Documents List | E122: Always | G122: src/modules/loans/components/loan-form/post-file/DocumentsList.jsx; src/modules/loans/components/loan-form/post-file/PostFileDocumentManagement.jsx
A123: dob | B123: number | C123: Pre-File | D123: Personal Details Pre File | E123: Always | G123: src/modules/loans/components/loan-form/pre-file/PersonalDetailsPreFile.jsx
A124: docsPreparedBy | B124: string | C124: Pre-File | D124: Section7Record Details | E124: Pre-file/Post-file record details | F124: Map from PRE/POST docs prepared-by chain, not source channel. | G124: src/modules/loans/components/loan-form/pre-file/Section7RecordDetails.jsx
A125: downPayment | B125: string | C125: Header / Shared | D125: Loan Sticky Header | E125: Always | G125: src/modules/loans/components/LoanStickyHeader.jsx
A126: ecs_accountNumber | B126: number | C126: Post-File | D126: Post File Instrument Details | E126: Always | G126: src/modules/loans/components/loan-form/post-file/PostFileInstrumentDetails.jsx
A127: ecs_amount | B127: number | C127: Post-File | D127: Post File Instrument Details | E127: Always | G127: src/modules/loans/components/loan-form/post-file/PostFileInstrumentDetails.jsx
A128: ecs_bankName | B128: number | C128: Post-File | D128: Post File Instrument Details | E128: Always | G128: src/modules/loans/components/loan-form/post-file/PostFileInstrumentDetails.jsx
A129: ecs_date | B129: number | C129: Post-File | D129: Post File Instrument Details | E129: Always | G129: src/modules/loans/components/loan-form/post-file/PostFileInstrumentDetails.jsx
A130: ecs_favouring | B130: string | C130: Post-File | D130: Post File Instrument Details | E130: Always | G130: src/modules/loans/components/loan-form/post-file/PostFileInstrumentDetails.jsx
A131: ecs_image | B131: string | C131: Post-File | D131: Post File Instrument Details | E131: Always | G131: src/modules/loans/components/loan-form/post-file/PostFileInstrumentDetails.jsx
A132: ecs_micrCode | B132: number | C132: Post-File | D132: Post File Instrument Details | E132: Always | G132: src/modules/loans/components/loan-form/post-file/PostFileInstrumentDetails.jsx
A133: ecs_signedBy | B133: string | C133: Post-File | D133: Post File Instrument Details | E133: Always | G133: src/modules/loans/components/loan-form/post-file/PostFileInstrumentDetails.jsx
A134: ecs_tag | B134: string | C134: Post-File | D134: Post File Instrument Details | E134: Always | G134: src/modules/loans/components/loan-form/post-file/PostFileInstrumentDetails.jsx
A135: education | B135: string | C135: Pre-File | D135: Personal Details Pre File | E135: Always | G135: src/modules/loans/components/loan-form/pre-file/PersonalDetailsPreFile.jsx
A136: email | B136: boolean | C136: Profile | D136: Emicustomer Details | E136: Always | G136: src/modules/loans/components/EMICustomerDetails.jsx; src/modules/loans/components/LoanStickyHeader.jsx; src/modules/loans/components/loan-form/customer-profile/PersonalDetailsSimplified.jsx; src/modules/loans/components/loan-form/pre-file/PersonalDetailsPreFile.jsx
... A202: invoice_received_from | B202: string | C202: Delivery | D202: Vehicle Delivery Step | E202: Always | G202: src/modules/loans/components/loan-form/vehicle-delivery/VehicleDeliveryStep.jsx
A203: isFinanced | B203: string | C203: Profile | D203: Loan Form With Steps | E203: Always | F203: If No => cash flow (Profile + Delivery only). If Yes => Pre-File/Approval/Post-File/Delivery/Payout flow. | G203: src/modules/loans/components/LoanFormWithSteps.jsx; src/modules/loans/components/loan-form/customer-profile/FinanceDetailsForm.jsx; src/modules/loans/components/loan-form/customer-profile/VehicleDetailsForm.jsx; src/modules/loans/components/loan-form/pre-file/PreFileStep.jsx; src/modules/loans/components/loan-form/vehicle-delivery/VehicleDeliveryStep.jsx
A204: isMSME | B204: string | C204: Profile | D204: Lead Details | E204: Always | G204: src/modules/loans/components/loan-form/customer-profile/LeadDetails.jsx; src/modules/loans/components/loan-form/pre-file/OccupationalDetailsPreFile.jsx
A205: isMultipleCars | B205: string | C205: Pre-File | D205: Bulk Loan Creation Section | E205: Always | G205: src/modules/loans/components/loan-form/pre-file/BulkLoanCreationSection.jsx
A206: isSameVehicle | B206: string | C206: Pre-File | D206: Bulk Loan Creation Section | E206: Always | G206: src/modules/loans/components/loan-form/pre-file/BulkLoanCreationSection.jsx
A207: leadDate | B207: string | C207: Profile | D207: Lead Details | E207: Always | G207: src/modules/loans/components/loan-form/customer-profile/LeadDetails.jsx
A208: leadTime | B208: string | C208: Profile | D208: Lead Details | E208: Always | G208: src/modules/loans/components/loan-form/customer-profile/LeadDetails.jsx
A209: loan_notes | B209: string | C209: Shared | D209: Loan Form With Steps | E209: Always | G209: src/modules/loans/components/LoanFormWithSteps.jsx; src/modules/loans/components/NotesModal.jsx
A210: loan_payables | B210: string | C210: Payout | D210: Payout Section | E210: Always | G210: src/modules/loans/components/loan-form/payout/PayoutSection.jsx
...

Sheet LegacyCatalog
A1: legacy_file | B1: legacy_field
A2: AUTH_SIGNATORY.json | B2: ACCOUNT_NUMBER_TYPE
A3: AUTH_SIGNATORY.json | B3: ADD1
A4: AUTH_SIGNATORY.json | B4: ADD2
A5: AUTH_SIGNATORY.json | B5: AUTH_AADHAAR_NUMBER
A6: AUTH_SIGNATORY.json | B6: CITY
A7: AUTH_SIGNATORY.json | B7: CPV_ACCOUNT_NO
A8: AUTH_SIGNATORY.json | B8: DATA_LOCATION_CODE
A9: AUTH_SIGNATORY.json | B9: DATE_OF_BIRTH
A10: AUTH_SIGNATORY.json | B10: DESIGNATION
A11: AUTH_SIGNATORY.json | B11: FAX
A12: AUTH_SIGNATORY.json | B12: HP_GROUP
... A409: RC_SOURCE_REFERENCE.json | B409: TEMP_CUST_CODE

Sheet DropdownData
A1: legacy_files | B1: AUTH_SIGNATORY.json | C1: CPV_DETAIL.json | D1: CUSTOMER_BANK.json | E1: GURANTOR.json | F1: RC_CUSTOMER_ACCOUNT.json | G1: RC_DOC_DESPATCH_MASTER.json | H1: RC_INSTRUMENT_DETAIL.json | I1: RC_RC_INV_RECEIVING_DETAIL.json | J1: RC_RC_INV_STATUS.json | K1: RC_SOURCE_REFERENCE.json
A2: AUTH_SIGNATORY.json | B2: ACCOUNT_NUMBER_TYPE | C2: AADHAAR_NUMBER | D2: ACCOUNT_NUMBER_TYPE | E2: ACCOUNT_NUMBER_TYPE | F2: ACCOUNT_STATUS | G2: DATA_LOCATION_CODE | H2: ACCOUNT_NUMBER | I2: CHASIS_NUMBER | J2: AGEING_FOR_BANK | K2: DATA_LOCATION_CODE
A3: CPV_DETAIL.json | B3: ADD1 | C3: ACCOUNT_NUMBER_TYPE | D3: BANK_ADDRESS | E3: ANNUAL_INCOME | F3: ADDRESS_FOR_REGISTER | G3: DATE_OF_DESP | H3: DATA_LOCATION_CODE | I3: DATA_LOCATION_CODE | J3: AGEING_FOR_US | K3: HP_GROUP
A4: CUSTOMER_BANK.json | B4: ADD2 | C4: ANNUAL_INCOME | D4: BANK_FAX | E4: CPV_ACCOUNT_NO | F4: ADDRESS_PROOF_FOR_REGISTRATION | G4: DESP_THROUGH | H4: DRAWN_ON | I4: DATE_OF_REGISTRATION | J4: CASE_TYPE_CODE | K4: PHONE_NUMBER
A5: GURANTOR.json | B5: AUTH_AADHAAR_NUMBER | C5: CAR_MODEL | D5: BANK_NAME | E5: DATA_LOCATION_CODE | F5: AGEING_FOR_BANK | G5: DESPATCH_ID | H5: ENTERED_BY | I5: DISPLACEMENT | J5: CHASIS_NUMBER | K5: REFERENCE_BY
A6: RC_CUSTOMER_ACCOUNT.json | B6: CITY | C6: CATEGORY | D6: BANK_PHONE | E6: DATE_OF_BIRTH | F6: AGEING_FOR_US | G6: DOC_DESP_AS | H6: ENTERED_ON_DATE | I6: ENGINE_NUMBER | J6: DATA_LOCATION_CODE | K6: TEMP_CUST_CODE
A7: RC_DOC_DESPATCH_MASTER.json | B7: CPV_ACCOUNT_NO | C7: CDB_ACCOUNT_NO | D7: CA_ACCOUNT_NO | E7: EDUCATION | F7: APPLIED_EMI | G7: DOCS_COLLECTED_BY | H7: HP_GROUP | I7: INV_RECEIVED_AS | J7: DATE_OF_DELIVERY
A8: RC_INSTRUMENT_DETAIL.json | B8: DATA_LOCATION_CODE | C8: CLS_REMARKS | D8: CPV_ACCOUNT_NO | E8: G_AADHAAR_NUMBER | F8: APPLIED_EMI_DUE_DATE | G8: DOCS_PREPARED_BY | H8: INSTRMNT_AMOUNT | I8: INV_RECEIVED_FROM | J8: DATE_OF_DISBURSE
A9: RC_RC_INV_RECEIVING_DETAIL.json | B9: DATE_OF_BIRTH | C9: CLS_STATUS | D9: DATA_LOCATION_CODE | E9: G_ICICI_ENTRY_NUMBER | F9: APPLIED_LOAN_AMOUNT | G9: TEMP_CUST_CODE | H9: INSTRMNT_BY_BORWR_GRNTR | I9: INV_RECEIVED_ON_DATE | J9: DATE_OF_REGISTRATION
A10: RC_RC_INV_STATUS.json | B10: DESIGNATION | C10: CPV_ACCOUNT_NO | D10: HP_GROUP | E10: HP_GROUP | F10: APPLIED_ROI | G10: TIME_OF_DESP | H10: INSTRMNT_DATE | I10: INVOICE_DATE | J10: ENGINE_NUMBER
A11: RC_SOURCE_REFERENCE.json | B11: FAX | C11: CPV_DATE | D11: OD_LIMIT | E11: MARITAL_STATUS | F11: APPLIED_TENOR | H11: INSTRMNT_FAVOURING | I11: INVOICE_NUMBER | J11: HP_GROUP
B12: HP_GROUP | C12: CPV_G_OFF_STATUS | D12: ORIGINAL_HP_GROUP | E12: MOBILE | F12: BANK_FILE_NUMBER | H12: INSTRMNT_NO | I12: LIEN_MARK | J12: INV_STATUS
B13: MOBILE | C13: CPV_G_RES_STATUS | D13: SB_ACCOUNT_NO | E13: NAME | F13: BORROWER_CATEGORY | H13: INSTRMNT_RECPT_ID_NO | I13: NO_OF_CYLINDERS | J13: INVOICE_DATE
B14: NAME | C14: CPV_MONTH_YEAR | E14: NO_OF_DEPEND | F14: BORROWER_RELATION | H14: INSTRMNT_TYPE | I14: ON_DATE | J14: INVOICE_NUMBER
B15: ORIGINAL_HP_GROUP | C15: CPV_OFF_STATUS | E15: OFF_ADD1 | F15: CASE_FOR_YEAR_MONTH | H15: LAST_UPDATE_ON_DATE | I15: RC_RECEIVED_AS | J15: IS_RC_DESPATCH_TO_BANK
B16: PHONE | C16: CPV_RES_STATUS | E16: OFF_ADD2 | F16: CASE_ORIGIN | H16: LAST_UPDATED_BY_USER | I16: RC_RECEIVED_FROM | J16: IS_VEHICLE_DELIVERED
B17: PIN | C17: CPV_SEND_AT_TIME | E17: OFF_CITY | F17: CASE_TYPE | H17: MICR_CODE | I17: RC_RECEIVED_ON_DATE | J17: LIEN_MARK
C18: CPV_SEND_ON_DATE | E18: OFF_FAX | F18: CASE_TYPE_CODE | H18: STATUS | I18: RECEIVING_NO | J18: MAKE_MODEL
C19: CREATED_BY_USER | E19: OFF_NAME | F19: CHANNEL_CODE | H19: STATUS_BY_USER | I19: REGD_NUMBER | J19: MANUFACTURER_CODE
C20: CREATED_ON_DATE | E20: OFF_PHONE | F20: CHASIS_NUMBER | H20: STATUS_ON_DATE | I20: SEATING_CAPACITY | J20: MFG_YEAR
C21: CREATED_ON_TIME | E21: OFF_PIN | F21: CLOSED_BY | H21: TEMP_CUST_CODE | I21: TEMP_CUST_CODE | J21: MODEL_CODE
C22: CUST_NAME_FIRST | E22: ORIGINAL_HP_GROUP | F22: CLOSEDBY_CODE | I22: UNLAIDEN_WEIGHT | J22: ORIGINAL_HP_GROUP
C23: CUST_NAME_LAST | E23: PROFESSION_TYPE | F23: CPV_ACCOUNT_NO | I23: USER_NAME | J23: OVERALL_STATUS
C24: CUST_NAME_MIDDLE | E24: RESI_ADD1 | F24: CPV_ACCOUNT_NUMBER_TYPE | J24: RC_STATUS
C25: CUSTOMER_NAME | E25: RESI_ADD2 | F25: CUST_CODE | J25: RC_STORAGE_NUMBER
C26: DATA_LOCATION_CODE | E26: RESI_CITY | F26: CUST_NAME | J26: REGD_NUMBER
C27: DATA_STATUS | E27: RESI_PHONE | F27: DATA_LOCATION_CODE | J27: TEMP_CUST_CODE
C28: DATE_OF_BIRTH | E28: RESI_PIN | F28: DATE_OF_APPROVAL_STATUS_TAKEN | J28: VARIANT_CODE
C29: DEALT_BY | E29: RESIDENCE_TYPE | F29: DATE_OF_DELIVERY
C30: DRIVING_LICENSE | E30: SEX | F30: DATE_OF_DESPATCH_FOR_APPROVAL
C31: E_MAIL | E31: VEHICLE_HAVE | F31: DATE_OF_DISBURSE
C32: EDUCATION | E32: VEHICLE_OWNERSHIP | F32: DATE_OF_FILE_DESPATCH
C33: EMAIL_ADDRESS | E33: YEARS_AT_PROFESSION | F33: DATE_WHEN_FILE_DESPATCH
C34: FATHERS_NAME_FIRST | E34: YEARS_AT_RESIDENCE | F34: DATE_WHEN_FILE_IN_BOOKING
C35: FATHERS_NAME_LAST | F35: DATE_WHEN_FILE_MOVED_TO_BANK
C36: FATHERS_NAME_MIDDLE | F36: DATE_WHEN_FILE_REACHED_AT_CPA
C37: FINANCER | F37: DATE_WHEN_FILE_RECEIVED
C38: GURANTOR_AVAILABLE | F38: DATE_WHEN_FILE_REJECT_WITHDRWN
C39: HEAD_NAME | F39: DEALER_CODE
C40: HIRE_TYPE | F40: DEALER_SUBVENTION
C41: HP_GROUP | F41: DEALT_BY
C42: HUSBAND_NAME | F42: DEALTBY_CODE
C43: ICICI_ENTRY_NUMBER | F43: DELIQUENCY_IN_BUCKET
C44: INDUSTRY_DETAIL | F44: DELIQUENCY_STATUS_GIVE_ON_DATE
C45: IS_REQ_G_OFF_VERIFICATION | F45: DELIQUENTY_STATUS_GIVE_BY
C46: IS_REQ_G_RES_VERIFICATION | F46: DELIVERED_MAKE_MODEL
... C105: YEARS_AT_RESIDENCE | F105: LOAN_RECEIVED_AMOUNT
F106: MAKE_MODEL
F107: MANUFACTURER_CODE
F108: MFG_YEAR
F109: MOBILE_NUMBER
F110: MODEL_CODE
F111: ORIGIN_CODE
F112: ORIGINAL_HP_GROUP
F113: OVERALL_STATUS
F114: PAYMENT_FAVOURING_AT_BOOKING
F115: PAYMENT_FAVOURING_AT_DESPATCH
F116: PAYOUT_RATE
F117: PERSON_WHO_DELIVERED_THE_CAR
... F161: VERIFIED_FILE_RECEIVED

Sheet Instructions
A1: How to use this workbook
A3: 1. Open sheet 'MappingEditor'.
A4: 2. Columns 'applies_when' and 'flow_notes' explain conditional flow dependencies.
A5: 3. Each row is one mapping rule. Duplicate rows to add fallbacks for the same new_field.
A6: 4. Select 'legacy_file' from dropdown first, then 'legacy_field' from dependent dropdown.
A7: 5. Use fallback_priority: 1 (highest), 2, 3 ...
A8: 6. Set transform (identity, normalize_yes_no, to_date, to_number, concat, custom).
A9: 7. Set active = Y/N.
A10: 8. Important: keep Source vs Dealt By separate (sourceName <- SOURCE-like, dealtBy <- DEALT_BY-like).
A11: 9. Save workbook and run parser script to generate JSON mapping config.
A13: Parser command:
A14: python3 scripts/parse_mapping_workbook.py --workbook migration_analysis/loan_field_mapping_workbook.xlsx --out migration_analysis/loan_field_mapping_config.json
... A19: Workbook generated for case: 3000004231

Sheet UnmappedNewFields
A1: new_field | B1: new_page | C1: new_section | D1: status
A2: aadhaarCardDocUrl | B2: Post-File | C2: Documents List | D2: =IF((COUNTIFS(MappingEditor!$A:$A,$A2,MappingEditor!$J:$J,"Y")+COUNTIFS(FallbackEditor!$A:$A,$A2,FallbackEditor!$J:$J,"Y"))>0,"mapped","unmapped")
A3: aadhaarNumber | B3: Header / Shared | C3: Loan Sticky Header | D3: =IF((COUNTIFS(MappingEditor!$A:$A,$A3,MappingEditor!$J:$J,"Y")+COUNTIFS(FallbackEditor!$A:$A,$A3,FallbackEditor!$J:$J,"Y"))>0,"mapped","unmapped")
A4: accessoriesAmount | B4: Pre-File | C4: Post File Vehicle Verification | D4: =IF((COUNTIFS(MappingEditor!$A:$A,$A4,MappingEditor!$J:$J,"Y")+COUNTIFS(FallbackEditor!$A:$A,$A4,FallbackEditor!$J:$J,"Y"))>0,"mapped","unmapped")
A5: accountNumber | B5: Pre-File | C5: Post File Dispatch And Records | D5: =IF((COUNTIFS(MappingEditor!$A:$A,$A5,MappingEditor!$J:$J,"Y")+COUNTIFS(FallbackEditor!$A:$A,$A5,FallbackEditor!$J:$J,"Y"))>0,"mapped","unmapped")
A6: accountSinceYears | B6: Pre-File | C6: Income Banking Details Pre File | D6: =IF((COUNTIFS(MappingEditor!$A:$A,$A6,MappingEditor!$J:$J,"Y")+COUNTIFS(FallbackEditor!$A:$A,$A6,FallbackEditor!$J:$J,"Y"))>0,"mapped","unmapped")
A7: accountType | B7: Pre-File | C7: Income Banking Details Pre File | D7: =IF((COUNTIFS(MappingEditor!$A:$A,$A7,MappingEditor!$J:$J,"Y")+COUNTIFS(FallbackEditor!$A:$A,$A7,FallbackEditor!$J:$J,"Y"))>0,"mapped","unmapped")
A8: addressProofDocUrl | B8: Post-File | C8: Documents List | D8: =IF((COUNTIFS(MappingEditor!$A:$A,$A8,MappingEditor!$J:$J,"Y")+COUNTIFS(FallbackEditor!$A:$A,$A8,FallbackEditor!$J:$J,"Y"))>0,"mapped","unmapped")
A9: addressProofNumber | B9: Pre-File | C9: Personal Details Pre File | D9: =IF((COUNTIFS(MappingEditor!$A:$A,$A9,MappingEditor!$J:$J,"Y")+COUNTIFS(FallbackEditor!$A:$A,$A9,FallbackEditor!$J:$J,"Y"))>0,"mapped","unmapped")
A10: addressProofType | B10: Pre-File | C10: Personal Details Pre File | D10: =IF((COUNTIFS(MappingEditor!$A:$A,$A10,MappingEditor!$J:$J,"Y")+COUNTIFS(FallbackEditor!$A:$A,$A10,FallbackEditor!$J:$J,"Y"))>0,"mapped","unmapped")
A11: addressType | B11: Pre-File | C11: Personal Details Pre File | D11: =IF((COUNTIFS(MappingEditor!$A:$A,$A11,MappingEditor!$J:$J,"Y")+COUNTIFS(FallbackEditor!$A:$A,$A11,FallbackEditor!$J:$J,"Y"))>0,"mapped","unmapped")
A12: advanceEmi | B12: Pre-File | C12: Vehicle Pricing Loan Details | D12: =IF((COUNTIFS(MappingEditor!$A:$A,$A12,MappingEditor!$J:$J,"Y")+COUNTIFS(FallbackEditor!$A:$A,$A12,FallbackEditor!$J:$J,"Y"))>0,"mapped","unmapped")
A13: applicantType | B13: Profile | C13: Lead Details | D13: =IF((COUNTIFS(MappingEditor!$A:$A,$A13,MappingEditor!$J:$J,"Y")+COUNTIFS(FallbackEditor!$A:$A,$A13,FallbackEditor!$J:$J,"Y"))>0,"mapped","unmapped")
... A324: yearsInCurrentHouse | B324: Profile | C324: Personal Details Simplified | D324: =IF((COUNTIFS(MappingEditor!$A:$A,$A324,MappingEditor!$J:$J,"Y")+COUNTIFS(FallbackEditor!$A:$A,$A324,FallbackEditor!$J:$J,"Y"))>0,"mapped","unmapped")

Sheet UnmappedLegacyFields
A1: legacy_file | B1: legacy_field | C1: status
A2: AUTH_SIGNATORY.json | B2: ACCOUNT_NUMBER_TYPE | C2: =IF((COUNTIFS(MappingEditor!$F:$F,$A2,MappingEditor!$G:$G,$B2,MappingEditor!$J:$J,"Y")+COUNTIFS(FallbackEditor!$G:$G,$A2,FallbackEditor!$H:$H,$B2,FallbackEditor!$J:$J,"Y"))>0,"mapped","unmapped")
A3: AUTH_SIGNATORY.json | B3: ADD1 | C3: =IF((COUNTIFS(MappingEditor!$F:$F,$A3,MappingEditor!$G:$G,$B3,MappingEditor!$J:$J,"Y")+COUNTIFS(FallbackEditor!$G:$G,$A3,FallbackEditor!$H:$H,$B3,FallbackEditor!$J:$J,"Y"))>0,"mapped","unmapped")
A4: AUTH_SIGNATORY.json | B4: ADD2 | C4: =IF((COUNTIFS(MappingEditor!$F:$F,$A4,MappingEditor!$G:$G,$B4,MappingEditor!$J:$J,"Y")+COUNTIFS(FallbackEditor!$G:$G,$A4,FallbackEditor!$H:$H,$B4,FallbackEditor!$J:$J,"Y"))>0,"mapped","unmapped")
A5: AUTH_SIGNATORY.json | B5: AUTH_AADHAAR_NUMBER | C5: =IF((COUNTIFS(MappingEditor!$F:$F,$A5,MappingEditor!$G:$G,$B5,MappingEditor!$J:$J,"Y")+COUNTIFS(FallbackEditor!$G:$G,$A5,FallbackEditor!$H:$H,$B5,FallbackEditor!$J:$J,"Y"))>0,"mapped","unmapped")
A6: AUTH_SIGNATORY.json | B6: CITY | C6: =IF((COUNTIFS(MappingEditor!$F:$F,$A6,MappingEditor!$G:$G,$B6,MappingEditor!$J:$J,"Y")+COUNTIFS(FallbackEditor!$G:$G,$A6,FallbackEditor!$H:$H,$B6,FallbackEditor!$J:$J,"Y"))>0,"mapped","unmapped")
A7: AUTH_SIGNATORY.json | B7: CPV_ACCOUNT_NO | C7: =IF((COUNTIFS(MappingEditor!$F:$F,$A7,MappingEditor!$G:$G,$B7,MappingEditor!$J:$J,"Y")+COUNTIFS(FallbackEditor!$G:$G,$A7,FallbackEditor!$H:$H,$B7,FallbackEditor!$J:$J,"Y"))>0,"mapped","unmapped")
A8: AUTH_SIGNATORY.json | B8: DATA_LOCATION_CODE | C8: =IF((COUNTIFS(MappingEditor!$F:$F,$A8,MappingEditor!$G:$G,$B8,MappingEditor!$J:$J,"Y")+COUNTIFS(FallbackEditor!$G:$G,$A8,FallbackEditor!$H:$H,$B8,FallbackEditor!$J:$J,"Y"))>0,"mapped","unmapped")
A9: AUTH_SIGNATORY.json | B9: DATE_OF_BIRTH | C9: =IF((COUNTIFS(MappingEditor!$F:$F,$A9,MappingEditor!$G:$G,$B9,MappingEditor!$J:$J,"Y")+COUNTIFS(FallbackEditor!$G:$G,$A9,FallbackEditor!$H:$H,$B9,FallbackEditor!$J:$J,"Y"))>0,"mapped","unmapped")
A10: AUTH_SIGNATORY.json | B10: DESIGNATION | C10: =IF((COUNTIFS(MappingEditor!$F:$F,$A10,MappingEditor!$G:$G,$B10,MappingEditor!$J:$J,"Y")+COUNTIFS(FallbackEditor!$G:$G,$A10,FallbackEditor!$H:$H,$B10,FallbackEditor!$J:$J,"Y"))>0,"mapped","unmapped")
A11: AUTH_SIGNATORY.json | B11: FAX | C11: =IF((COUNTIFS(MappingEditor!$F:$F,$A11,MappingEditor!$G:$G,$B11,MappingEditor!$J:$J,"Y")+COUNTIFS(FallbackEditor!$G:$G,$A11,FallbackEditor!$H:$H,$B11,FallbackEditor!$J:$J,"Y"))>0,"mapped","unmapped")
A12: AUTH_SIGNATORY.json | B12: HP_GROUP | C12: =IF((COUNTIFS(MappingEditor!$F:$F,$A12,MappingEditor!$G:$G,$B12,MappingEditor!$J:$J,"Y")+COUNTIFS(FallbackEditor!$G:$G,$A12,FallbackEditor!$H:$H,$B12,FallbackEditor!$J:$J,"Y"))>0,"mapped","unmapped")
A13: AUTH_SIGNATORY.json | B13: MOBILE | C13: =IF((COUNTIFS(MappingEditor!$F:$F,$A13,MappingEditor!$G:$G,$B13,MappingEditor!$J:$J,"Y")+COUNTIFS(FallbackEditor!$G:$G,$A13,FallbackEditor!$H:$H,$B13,FallbackEditor!$J:$J,"Y"))>0,"mapped","unmapped")
... A409: RC_SOURCE_REFERENCE.json | B409: TEMP_CUST_CODE | C409: =IF((COUNTIFS(MappingEditor!$F:$F,$A409,MappingEditor!$G:$G,$B409,MappingEditor!$J:$J,"Y")+COUNTIFS(FallbackEditor!$G:$G,$A409,FallbackEditor!$H:$H,$B409,FallbackEditor!$J:$J,"Y"))>0,"mapped","unmapped")

Sheet FallbackEditor
A1: new_field | B1: new_page | C1: new_section | D1: applies_when | E1: flow_notes | F1: fallback_priority | G1: legacy_file | H1: legacy_field | I1: transform | J1: active | K1: notes | L1: case_value_preview
A2: accountNumber | B2: Pre-File | C2: Post File Dispatch And Records | D2: Always | F2: 1 | G2: CUSTOMER_BANK.json | H2: CA_ACCOUNT_NO | I2: identity | J2: Y | K2: clean | L2: =IFERROR(XLOOKUP($G2&"."&$H2,CaseSource!$A$2:$A$371,CaseSource!$B$2:$B$371,""),"")
A3: accountNumber | B3: Pre-File | C3: Post File Dispatch And Records | D3: Always | F3: 2 | G3: CUSTOMER_BANK.json | H3: SB_ACCOUNT_NO | I3: identity | J3: Y | K3: clean | L3: =IFERROR(XLOOKUP($G3&"."&$H3,CaseSource!$A$2:$A$371,CaseSource!$B$2:$B$371,""),"")
A4: addressProofNumber | B4: Pre-File | C4: Personal Details Pre File | D4: Always | F4: 1 | G4: CPV_DETAIL.json | H4: AADHAAR_NUMBER | I4: identity | J4: Y | K4: clean | L4: =IFERROR(XLOOKUP($G4&"."&$H4,CaseSource!$A$2:$A$371,CaseSource!$B$2:$B$371,""),"")
A5: applicantType | B5: Profile | C5: Lead Details | D5: Always | E5: Individual vs Company changes form visibility and required sections. | F5: 1 | G5: CPV_DETAIL.json | H5: HIRE_TYPE | I5: identity | J5: Y | K5: `normalizeApplicantType(...)` => `Individual`/`Company`. | L5: =IFERROR(XLOOKUP($G5&"."&$H5,CaseSource!$A$2:$A$371,CaseSource!$B$2:$B$371,""),"")
A6: approval_approvalDate | B6: Approval | C6: Loan Form With Steps | D6: Financed flow | E6: For legacy migration, use disbursement date when explicit approval date is absent. | F6: 1 | G6: RC_CUSTOMER_ACCOUNT.json | H6: DATE_OF_DISBURSE | I6: identity | J6: Y | K6: ISO | L6: =IFERROR(XLOOKUP($G6&"."&$H6,CaseSource!$A$2:$A$371,CaseSource!$B$2:$B$371,""),"")
A7: approval_approvalDate | B7: Approval | C7: Loan Form With Steps | D7: Financed flow | E7: For legacy migration, use disbursement date when explicit approval date is absent. | F7: 2 | G7: RC_RC_INV_STATUS.json | H7: DATE_OF_DISBURSE | I7: identity | J7: Y | K7: ISO | L7: =IFERROR(XLOOKUP($G7&"."&$H7,CaseSource!$A$2:$A$371,CaseSource!$B$2:$B$371,""),"")
A8: approval_approvalDate | B8: Approval | C8: Loan Form With Steps | D8: Financed flow | E8: For legacy migration, use disbursement date when explicit approval date is absent. | F8: 3 | G8: RC_CUSTOMER_ACCOUNT.json | H8: DATE_OF_FILE_DESPATCH | I8: identity | J8: Y | K8: ISO | L8: =IFERROR(XLOOKUP($G8&"."&$H8,CaseSource!$A$2:$A$371,CaseSource!$B$2:$B$371,""),"")
A9: approval_approvalDate | B9: Approval | C9: Loan Form With Steps | D9: Financed flow | E9: For legacy migration, use disbursement date when explicit approval date is absent. | F9: 4 | G9: CPV_DETAIL.json | H9: CPV_DATE | I9: identity | J9: Y | K9: ISO | L9: =IFERROR(XLOOKUP($G9&"."&$H9,CaseSource!$A$2:$A$371,CaseSource!$B$2:$B$371,""),"")
A10: approval_bankName` / `postfile_bankName | D10: Always | F10: 1 | G10: RC_CUSTOMER_ACCOUNT.json | H10: HP_TO | I10: identity | J10: Y | K10: bank normalization | L10: =IFERROR(XLOOKUP($G10&"."&$H10,CaseSource!$A$2:$A$371,CaseSource!$B$2:$B$371,""),"")
A11: approval_bankName` / `postfile_bankName | D11: Always | F11: 2 | G11: CPV_DETAIL.json | H11: FINANCER | I11: identity | J11: Y | K11: bank normalization | L11: =IFERROR(XLOOKUP($G11&"."&$H11,CaseSource!$A$2:$A$371,CaseSource!$B$2:$B$371,""),"")
A12: approval_disbursedDate` / `disbursement_date | D12: Always | F12: 1 | G12: RC_CUSTOMER_ACCOUNT.json | H12: DATE_OF_DISBURSE | I12: identity | J12: Y | K12: date | L12: =IFERROR(XLOOKUP($G12&"."&$H12,CaseSource!$A$2:$A$371,CaseSource!$B$2:$B$371,""),"")
A13: approval_disbursedDate` / `disbursement_date | D13: Always | F13: 2 | G13: RC_RC_INV_STATUS.json | H13: DATE_OF_DISBURSE | I13: identity | J13: Y | K13: date | L13: =IFERROR(XLOOKUP($G13&"."&$H13,CaseSource!$A$2:$A$371,CaseSource!$B$2:$B$371,""),"")
A14: approval_loanAmountApproved` / `postfile_loanAmountApproved | D14: Always | F14: 1 | G14: RC_CUSTOMER_ACCOUNT.json | H14: LOAN_AMOUNT | I14: identity | J14: Y | K14: numeric | L14: =IFERROR(XLOOKUP($G14&"."&$H14,CaseSource!$A$2:$A$371,CaseSource!$B$2:$B$371,""),"")
A15: approval_loanAmountApproved` / `postfile_loanAmountApproved | D15: Always | F15: 2 | G15: CPV_DETAIL.json | H15: LOAN_EXPECTED | I15: identity | J15: Y | K15: numeric | L15: =IFERROR(XLOOKUP($G15&"."&$H15,CaseSource!$A$2:$A$371,CaseSource!$B$2:$B$371,""),"")
A16: approval_roi` / `postfile_roi | D16: Always | F16: 1 | G16: RC_CUSTOMER_ACCOUNT.json | H16: ROI | I16: identity | J16: Y | K16: numeric | L16: =IFERROR(XLOOKUP($G16&"."&$H16,CaseSource!$A$2:$A$371,CaseSource!$B$2:$B$371,""),"")
A17: approval_tenureMonths` / `postfile_tenureMonths | D17: Always | F17: 1 | G17: RC_CUSTOMER_ACCOUNT.json | H17: TENOR | I17: identity | J17: Y | K17: numeric | L17: =IFERROR(XLOOKUP($G17&"."&$H17,CaseSource!$A$2:$A$371,CaseSource!$B$2:$B$371,""),"")
A18: approval_tenureMonths` / `postfile_tenureMonths | D18: Always | F18: 2 | G18: CPV_DETAIL.json | H18: TENDOR | I18: identity | J18: Y | K18: numeric | L18: =IFERROR(XLOOKUP($G18&"."&$H18,CaseSource!$A$2:$A$371,CaseSource!$B$2:$B$371,""),"")
A19: bankName | B19: Pre-File | C19: Loan Form With Steps | D19: Always | F19: 1 | G19: CUSTOMER_BANK.json | H19: BANK_NAME | I19: identity | J19: Y | K19: normalized bank name | L19: =IFERROR(XLOOKUP($G19&"."&$H19,CaseSource!$A$2:$A$371,CaseSource!$B$2:$B$371,""),"")
A20: boughtInYear | B20: Pre-File | C20: Post File Vehicle Verification | D20: Always | F20: 1 | G20: RC_CUSTOMER_ACCOUNT.json | H20: BOUGHT_IN_YEAR | I20: identity | J20: Y | K20: parse 4-digit/2-digit year normalization | L20: =IFERROR(XLOOKUP($G20&"."&$H20,CaseSource!$A$2:$A$371,CaseSource!$B$2:$B$371,""),"")
A21: boughtInYear | B21: Pre-File | C21: Post File Vehicle Verification | D21: Always | F21: 2 | G21: RC_CUSTOMER_ACCOUNT.json | H21: VEHICLE_YEAR | I21: identity | J21: Y | K21: parse 4-digit/2-digit year normalization | L21: =IFERROR(XLOOKUP($G21&"."&$H21,CaseSource!$A$2:$A$371,CaseSource!$B$2:$B$371,""),"")
A22: boughtInYear | B22: Pre-File | C22: Post File Vehicle Verification | D22: Always | F22: 3 | G22: CPV_DETAIL.json | H22: BOUGHT_IN_YEAR | I22: identity | J22: Y | K22: parse 4-digit/2-digit year normalization | L22: =IFERROR(XLOOKUP($G22&"."&$H22,CaseSource!$A$2:$A$371,CaseSource!$B$2:$B$371,""),"")
A23: branch | B23: Pre-File | C23: Post File Dispatch And Records | D23: Always | F23: 1 | G23: CUSTOMER_BANK.json | H23: BANK_ADDRESS | I23: identity | J23: Y | K23: clean | L23: =IFERROR(XLOOKUP($G23&"."&$H23,CaseSource!$A$2:$A$371,CaseSource!$B$2:$B$371,""),"")
A24: businessNature | B24: Pre-File | C24: Occupational Details Pre File | D24: Always | F24: 1 | G24: CPV_DETAIL.json | H24: ORGANISATION_TYPE | I24: identity | J24: Y | K24: multi-value combined | L24: =IFERROR(XLOOKUP($G24&"."&$H24,CaseSource!$A$2:$A$371,CaseSource!$B$2:$B$371,""),"")
A25: city | B25: Pre-File | C25: Loan Sticky Header | D25: Always | F25: 1 | G25: CPV_DETAIL.json | H25: OFF_CITY | I25: identity | J25: Y | K25: clean | L25: =IFERROR(XLOOKUP($G25&"."&$H25,CaseSource!$A$2:$A$371,CaseSource!$B$2:$B$371,""),"")
A26: city | B26: Pre-File | C26: Loan Sticky Header | D26: Always | F26: 2 | G26: CPV_DETAIL.json | H26: RESI_CITY | I26: identity | J26: Y | K26: clean | L26: =IFERROR(XLOOKUP($G26&"."&$H26,CaseSource!$A$2:$A$371,CaseSource!$B$2:$B$371,""),"")
A27: co_aadhaar | B27: Pre-File | C27: Co Applicant Section | D27: Always | F27: 1 | G27: AUTH_SIGNATORY.json | H27: AUTH_AADHAAR_NUMBER | I27: identity | J27: Y | K27: clean | L27: =IFERROR(XLOOKUP($G27&"."&$H27,CaseSource!$A$2:$A$371,CaseSource!$B$2:$B$371,""),"")
A28: co_aadhaar | B28: Pre-File | C28: Co Applicant Section | D28: Always | F28: 2 | G28: GURANTOR.json | H28: G_AADHAAR_NUMBER | I28: identity | J28: Y | K28: clean | L28: =IFERROR(XLOOKUP($G28&"."&$H28,CaseSource!$A$2:$A$371,CaseSource!$B$2:$B$371,""),"")
A29: co_aadhaar | B29: Pre-File | C29: Co Applicant Section | D29: Always | F29: 3 | G29: CPV_DETAIL.json | H29: AADHAAR_NUMBER | I29: identity | J29: Y | K29: clean | L29: =IFERROR(XLOOKUP($G29&"."&$H29,CaseSource!$A$2:$A$371,CaseSource!$B$2:$B$371,""),"")
A30: co_address | B30: Pre-File | C30: Co Applicant Section | D30: Always | F30: 1 | G30: AUTH_SIGNATORY.json | H30: ADD1_1 | I30: identity | J30: Y | K30: clean | L30: =IFERROR(XLOOKUP($G30&"."&$H30,CaseSource!$A$2:$A$371,CaseSource!$B$2:$B$371,""),"")
... A36: co_city | B36: Pre-File | C36: Co Applicant Section | D36: Always | F36: 3 | G36: CPV_DETAIL.json | H36: RESI_CITY | I36: identity | J36: Y | K36: clean | L36: =IFERROR(XLOOKUP($G36&"."&$H36,CaseSource!$A$2:$A$371,CaseSource!$B$2:$B$371,""),"")
A37: co_currentExperience` / `co_totalExperience | D37: Always | F37: 1 | G37: CPV_DETAIL.json | H37: YEAR_AT_PROFESSION | I37: identity | J37: Y | K37: numeric | L37: =IFERROR(XLOOKUP($G37&"."&$H37,CaseSource!$A$2:$A$371,CaseSource!$B$2:$B$371,""),"")
A38: co_customerName | B38: Pre-File | C38: Co Applicant Section | D38: Always | F38: 1 | G38: AUTH_SIGNATORY.json | H38: NAME_1 | I38: identity | J38: Y | K38: clean | L38: =IFERROR(XLOOKUP($G38&"."&$H38,CaseSource!$A$2:$A$371,CaseSource!$B$2:$B$371,""),"")
A39: co_customerName | B39: Pre-File | C39: Co Applicant Section | D39: Always | F39: 2 | G39: AUTH_SIGNATORY.json | H39: NAME | I39: identity | J39: Y | K39: clean | L39: =IFERROR(XLOOKUP($G39&"."&$H39,CaseSource!$A$2:$A$371,CaseSource!$B$2:$B$371,""),"")
A40: co_customerName | B40: Pre-File | C40: Co Applicant Section | D40: Always | F40: 3 | G40: GURANTOR.json | H40: NAME | I40: identity | J40: Y | K40: clean | L40: =IFERROR(XLOOKUP($G40&"."&$H40,CaseSource!$A$2:$A$371,CaseSource!$B$2:$B$371,""),"")
A41: co_dependents | B41: Pre-File | C41: Co Applicant Section | D41: Always | F41: 1 | G41: CPV_DETAIL.json | H41: NO_OF_DEPENDANTS | I41: identity | J41: Y | K41: numeric | L41: =IFERROR(XLOOKUP($G41&"."&$H41,CaseSource!$A$2:$A$371,CaseSource!$B$2:$B$371,""),"")
A42: co_dependents | B42: Pre-File | C42: Co Applicant Section | D42: Always | F42: 2 | G42: GURANTOR.json | H42: NO_OF_DEPEND | I42: identity | J42: Y | K42: numeric | L42: =IFERROR(XLOOKUP($G42&"."&$H42,CaseSource!$A$2:$A$371,CaseSource!$B$2:$B$371,""),"")
A43: co_designation | B43: Pre-File | C43: Co Applicant Section | D43: Always | F43: 1 | G43: AUTH_SIGNATORY.json | H43: DESIGNATION_1 | I43: identity | J43: Y | K43: clean | L43: =IFERROR(XLOOKUP($G43&"."&$H43,CaseSource!$A$2:$A$371,CaseSource!$B$2:$B$371,""),"")
A44: co_dob | B44: Pre-File | C44: Co Applicant Section | D44: Always | F44: 1 | G44: AUTH_SIGNATORY.json | H44: DATE_OF_BIRTH_1 | I44: identity | J44: Y | K44: ISO | L44: =IFERROR(XLOOKUP($G44&"."&$H44,CaseSource!$A$2:$A$371,CaseSource!$B$2:$B$371,""),"")
A45: co_dob | B45: Pre-File | C45: Co Applicant Section | D45: Always | F45: 2 | G45: CPV_DETAIL.json | H45: DATE_OF_BIRTH | I45: identity | J45: Y | K45: ISO | L45: =IFERROR(XLOOKUP($G45&"."&$H45,CaseSource!$A$2:$A$371,CaseSource!$B$2:$B$371,""),"")
A46: co_houseType | B46: Pre-File | C46: Co Applicant Section | D46: Always | F46: 1 | G46: CPV_DETAIL.json | H46: RESIDENCE_TYPE | I46: identity | J46: Y | K46: normalized | L46: =IFERROR(XLOOKUP($G46&"."&$H46,CaseSource!$A$2:$A$371,CaseSource!$B$2:$B$371,""),"")
A47: co_houseType | B47: Pre-File | C47: Co Applicant Section | D47: Always | F47: 2 | G47: GURANTOR.json | H47: RESIDENCE_TYPE | I47: identity | J47: Y | K47: normalized | L47: =IFERROR(XLOOKUP($G47&"."&$H47,CaseSource!$A$2:$A$371,CaseSource!$B$2:$B$371,""),"")
A48: co_pincode | B48: Pre-File | C48: Co Applicant Section | D48: Always | F48: 1 | G48: AUTH_SIGNATORY.json | H48: PIN_1 | I48: identity | J48: Y | K48: clean | L48: =IFERROR(XLOOKUP($G48&"."&$H48,CaseSource!$A$2:$A$371,CaseSource!$B$2:$B$371,""),"")
A49: co_pincode | B49: Pre-File | C49: Co Applicant Section | D49: Always | F49: 2 | G49: GURANTOR.json | H49: RESI_PIN | I49: identity | J49: Y | K49: clean | L49: =IFERROR(XLOOKUP($G49&"."&$H49,CaseSource!$A$2:$A$371,CaseSource!$B$2:$B$371,""),"")
... A57: companyType | B57: Pre-File | C57: Occupational Details Pre File | D57: Always | F57: 2 | G57: CPV_DETAIL.json | H57: ORGANISATION_TYPE | I57: identity | J57: Y | K57: normalized | L57: =IFERROR(XLOOKUP($G57&"."&$H57,CaseSource!$A$2:$A$371,CaseSource!$B$2:$B$371,""),"")
A58: currentStage | B58: Shared | C58: Loan Form With Steps | D58: Always | E58: Must respect legacy approval/disbursement progression for migration cases. | F58: 1 | G58: RC_CUSTOMER_ACCOUNT.json | H58: DATE_OF_DISBURSE | I58: identity | J58: Y | K58: If cash loan (`isFinanced=No`) => `delivery`; cash-in/refinance with disburse => `payout`; else delivery/disburse/dispatch fallback. | L58: =IFERROR(XLOOKUP($G58&"."&$H58,CaseSource!$A$2:$A$371,CaseSource!$B$2:$B$371,""),"")
A59: currentStage | B59: Shared | C59: Loan Form With Steps | D59: Always | E59: Must respect legacy approval/disbursement progression for migration cases. | F59: 2 | G59: RC_RC_INV_STATUS.json | H59: DATE_OF_DISBURSE | I59: identity | J59: Y | K59: If cash loan (`isFinanced=No`) => `delivery`; cash-in/refinance with disburse => `payout`; else delivery/disburse/dispatch fallback. | L59: =IFERROR(XLOOKUP($G59&"."&$H59,CaseSource!$A$2:$A$371,CaseSource!$B$2:$B$371,""),"")
A60: currentStage | B60: Shared | C60: Loan Form With Steps | D60: Always | E60: Must respect legacy approval/disbursement progression for migration cases. | F60: 3 | G60: RC_CUSTOMER_ACCOUNT.json | H60: DATE_OF_DELIVERY | I60: identity | J60: Y | K60: If cash loan (`isFinanced=No`) => `delivery`; cash-in/refinance with disburse => `payout`; else delivery/disburse/dispatch fallback. | L60: =IFERROR(XLOOKUP($G60&"."&$H60,CaseSource!$A$2:$A$371,CaseSource!$B$2:$B$371,""),"")
A61: currentStage | B61: Shared | C61: Loan Form With Steps | D61: Always | E61: Must respect legacy approval/disbursement progression for migration cases. | F61: 4 | G61: RC_RC_INV_STATUS.json | H61: DATE_OF_DELIVERY | I61: identity | J61: Y | K61: If cash loan (`isFinanced=No`) => `delivery`; cash-in/refinance with disburse => `payout`; else delivery/disburse/dispatch fallback. | L61: =IFERROR(XLOOKUP($G61&"."&$H61,CaseSource!$A$2:$A$371,CaseSource!$B$2:$B$371,""),"")
A62: currentStage | B62: Shared | C62: Loan Form With Steps | D62: Always | E62: Must respect legacy approval/disbursement progression for migration cases. | F62: 5 | G62: RC_CUSTOMER_ACCOUNT.json | H62: DATE_OF_FILE_DESPATCH | I62: identity | J62: Y | K62: If cash loan (`isFinanced=No`) => `delivery`; cash-in/refinance with disburse => `payout`; else delivery/disburse/dispatch fallback. | L62: =IFERROR(XLOOKUP($G62&"."&$H62,CaseSource!$A$2:$A$371,CaseSource!$B$2:$B$371,""),"")
A63: currentStage | B63: Shared | C63: Loan Form With Steps | D63: Always | E63: Must respect legacy approval/disbursement progression for migration cases. | F63: 6 | G63: RC_CUSTOMER_ACCOUNT.json | H63: DATE_WHEN_FILE_DESPATCH | I63: identity | J63: Y | K63: If cash loan (`isFinanced=No`) => `delivery`; cash-in/refinance with disburse => `payout`; else delivery/disburse/dispatch fallback. | L63: =IFERROR(XLOOKUP($G63&"."&$H63,CaseSource!$A$2:$A$371,CaseSource!$B$2:$B$371,""),"")
A64: customerName | B64: Profile | C64: Emicustomer Details | D64: Always | F64: 1 | G64: RC_CUSTOMER_ACCOUNT.json | H64: CUST_NAME | I64: identity | J64: Y | K64: `pickName(...)` uses case-aware row preference. | L64: =IFERROR(XLOOKUP($G64&"."&$H64,CaseSource!$A$2:$A$371,CaseSource!$B$2:$B$371,""),"")
A65: customerName | B65: Profile | C65: Emicustomer Details | D65: Always | F65: 2 | G65: CPV_DETAIL.json | H65: CUSTOMER_NAME | I65: identity | J65: Y | K65: `pickName(...)` uses case-aware row preference. | L65: =IFERROR(XLOOKUP($G65&"."&$H65,CaseSource!$A$2:$A$371,CaseSource!$B$2:$B$371,""),"")
A66: dealerName | B66: Profile | C66: Lead Details | D66: Always | F66: 1 | G66: RC_CUSTOMER_ACCOUNT.json | H66: PAYMENT_FAVOURING_AT_DESPATCH | I66: identity | J66: Y | K66: ignored if literal `customer name` | L66: =IFERROR(XLOOKUP($G66&"."&$H66,CaseSource!$A$2:$A$371,CaseSource!$B$2:$B$371,""),"")
A67: delivery_date | B67: Delivery | C67: Vehicle Delivery Step | D67: Always | F67: 1 | G67: RC_CUSTOMER_ACCOUNT.json | H67: DATE_OF_DELIVERY | I67: identity | J67: Y | K67: only when `typeOfLoan=New Car` in payload currently | L67: =IFERROR(XLOOKUP($G67&"."&$H67,CaseSource!$A$2:$A$371,CaseSource!$B$2:$B$371,""),"")
A68: delivery_date | B68: Delivery | C68: Vehicle Delivery Step | D68: Always | F68: 2 | G68: RC_RC_INV_STATUS.json | H68: DATE_OF_DELIVERY | I68: identity | J68: Y | K68: only when `typeOfLoan=New Car` in payload currently | L68: =IFERROR(XLOOKUP($G68&"."&$H68,CaseSource!$A$2:$A$371,CaseSource!$B$2:$B$371,""),"")
A69: dependents | B69: Profile | C69: Personal Details Simplified | D69: Always | F69: 1 | G69: CPV_DETAIL.json | H69: NO_OF_DEPENDANTS | I69: identity | J69: Y | K69: numeric | L69: =IFERROR(XLOOKUP($G69&"."&$H69,CaseSource!$A$2:$A$371,CaseSource!$B$2:$B$371,""),"")
A70: designation | B70: Pre-File | C70: Authorised Signatory Section | D70: Always | F70: 1 | G70: AUTH_SIGNATORY.json | H70: DESIGNATION_1 | I70: identity | J70: Y | K70: clean | L70: =IFERROR(XLOOKUP($G70&"."&$H70,CaseSource!$A$2:$A$371,CaseSource!$B$2:$B$371,""),"")
A71: designation | B71: Pre-File | C71: Authorised Signatory Section | D71: Always | F71: 2 | G71: CPV_DETAIL.json | H71: INDUSTRY_DETAIL | I71: identity | J71: Y | K71: clean | L71: =IFERROR(XLOOKUP($G71&"."&$H71,CaseSource!$A$2:$A$371,CaseSource!$B$2:$B$371,""),"")
A72: dispatch_date | B72: Post-File | C72: Post File Dispatch And Records | D72: Always | F72: 1 | G72: RC_DOC_DESPATCH_MASTER.json | H72: DATE_OF_DESP | I72: identity | J72: Y | K72: date | L72: =IFERROR(XLOOKUP($G72&"."&$H72,CaseSource!$A$2:$A$371,CaseSource!$B$2:$B$371,""),"")
A73: dispatch_date | B73: Post-File | C73: Post File Dispatch And Records | D73: Always | F73: 2 | G73: RC_CUSTOMER_ACCOUNT.json | H73: DATE_OF_FILE_DESPATCH | I73: identity | J73: Y | K73: date | L73: =IFERROR(XLOOKUP($G73&"."&$H73,CaseSource!$A$2:$A$371,CaseSource!$B$2:$B$371,""),"")
A74: dispatch_through | B74: Post-File | C74: Post File Dispatch And Records | D74: Always | F74: 1 | G74: RC_DOC_DESPATCH_MASTER.json | H74: DESP_THROUGH | I74: identity | J74: Y | K74: clean | L74: =IFERROR(XLOOKUP($G74&"."&$H74,CaseSource!$A$2:$A$371,CaseSource!$B$2:$B$371,""),"")
A75: dispatch_through | B75: Post-File | C75: Post File Dispatch And Records | D75: Always | F75: 2 | G75: RC_CUSTOMER_ACCOUNT.json | H75: DESPATCH_FOR_APPROVAL_THROUGH | I75: identity | J75: Y | K75: clean | L75: =IFERROR(XLOOKUP($G75&"."&$H75,CaseSource!$A$2:$A$371,CaseSource!$B$2:$B$371,""),"")
... A78: dob | B78: Pre-File | C78: Personal Details Pre File | D78: Always | F78: 1 | G78: CPV_DETAIL.json | H78: DATE_OF_BIRTH | I78: identity | J78: Y | K78: ISO date | L78: =IFERROR(XLOOKUP($G78&"."&$H78,CaseSource!$A$2:$A$371,CaseSource!$B$2:$B$371,""),"")
A79: docsPreparedBy | B79: Pre-File | C79: Section7Record Details | D79: Pre-file/Post-file record details | E79: Map from PRE/POST docs prepared-by chain, not source channel. | F79: 1 | G79: RC_DOC_DESPATCH_MASTER.json | H79: DOCS_PREPARED_BY | I79: identity | J79: Y | K79: clean | L79: =IFERROR(XLOOKUP($G79&"."&$H79,CaseSource!$A$2:$A$371,CaseSource!$B$2:$B$371,""),"")
A80: docsPreparedBy | B80: Pre-File | C80: Section7Record Details | D80: Pre-file/Post-file record details | E80: Map from PRE/POST docs prepared-by chain, not source channel. | F80: 2 | G80: RC_CUSTOMER_ACCOUNT.json | H80: PRE_DOCS_PREPARED_BY | I80: identity | J80: Y | K80: clean | L80: =IFERROR(XLOOKUP($G80&"."&$H80,CaseSource!$A$2:$A$371,CaseSource!$B$2:$B$371,""),"")
A81: dsaCode | D81: Always | F81: 1 | G81: RC_CUSTOMER_ACCOUNT.json | H81: DSA_CODE | I81: identity | J81: Y | K81: clean | L81: =IFERROR(XLOOKUP($G81&"."&$H81,CaseSource!$A$2:$A$371,CaseSource!$B$2:$B$371,""),"")
A82: education | B82: Pre-File | C82: Personal Details Pre File | D82: Always | F82: 1 | G82: CPV_DETAIL.json | H82: EDUCATION | I82: identity | J82: Y | K82: normalized | L82: =IFERROR(XLOOKUP($G82&"."&$H82,CaseSource!$A$2:$A$371,CaseSource!$B$2:$B$371,""),"")
A83: email | B83: Profile | C83: Emicustomer Details | D83: Always | F83: 1 | G83: CPV_DETAIL.json | H83: E_MAIL | I83: identity | J83: Y | K83: clean text | L83: =IFERROR(XLOOKUP($G83&"."&$H83,CaseSource!$A$2:$A$371,CaseSource!$B$2:$B$371,""),"")
A84: email | B84: Profile | C84: Emicustomer Details | D84: Always | F84: 2 | G84: CPV_DETAIL.json | H84: EMAIL_ADDRESS | I84: identity | J84: Y | K84: clean text | L84: =IFERROR(XLOOKUP($G84&"."&$H84,CaseSource!$A$2:$A$371,CaseSource!$B$2:$B$371,""),"")
A85: employmentAddress | B85: Pre-File | C85: Occupational Details Pre File | D85: Always | F85: 1 | G85: CPV_DETAIL.json | H85: OFF_ADD1 | I85: identity | J85: Y | K85: clean | L85: =IFERROR(XLOOKUP($G85&"."&$H85,CaseSource!$A$2:$A$371,CaseSource!$B$2:$B$371,""),"")
A86: employmentCity | B86: Pre-File | C86: Occupational Details Pre File | D86: Always | F86: 1 | G86: CPV_DETAIL.json | H86: OFF_CITY | I86: identity | J86: Y | K86: clean | L86: =IFERROR(XLOOKUP($G86&"."&$H86,CaseSource!$A$2:$A$371,CaseSource!$B$2:$B$371,""),"")
A87: employmentPincode | B87: Pre-File | C87: Occupational Details Pre File | D87: Always | F87: 1 | G87: CPV_DETAIL.json | H87: OFF_PIN | I87: identity | J87: Y | K87: clean | L87: =IFERROR(XLOOKUP($G87&"."&$H87,CaseSource!$A$2:$A$371,CaseSource!$B$2:$B$371,""),"")
A88: experienceCurrent | B88: Pre-File | C88: Occupational Details Pre File | D88: Always | F88: 1 | G88: CPV_DETAIL.json | H88: YEAR_AT_PROFESSION | I88: identity | J88: Y | K88: numeric | L88: =IFERROR(XLOOKUP($G88&"."&$H88,CaseSource!$A$2:$A$371,CaseSource!$B$2:$B$371,""),"")
A89: exShowroomPrice | B89: Pre-File | C89: Loan Sticky Header | D89: Always | F89: 1 | G89: RC_CUSTOMER_ACCOUNT.json | H89: EX_SHOWROOM_OR_VALUATION | I89: identity | J89: Y | K89: numeric | L89: =IFERROR(XLOOKUP($G89&"."&$H89,CaseSource!$A$2:$A$371,CaseSource!$B$2:$B$371,""),"")
A90: financeExpectation | B90: Profile | C90: Loan Sticky Header | D90: Always | F90: 1 | G90: RC_CUSTOMER_ACCOUNT.json | H90: LOAN_AMOUNT | I90: identity | J90: Y | K90: numeric | L90: =IFERROR(XLOOKUP($G90&"."&$H90,CaseSource!$A$2:$A$371,CaseSource!$B$2:$B$371,""),"")
A91: financeExpectation | B91: Profile | C91: Loan Sticky Header | D91: Always | F91: 2 | G91: RC_CUSTOMER_ACCOUNT.json | H91: APPLIED_LOAN_AMOUNT | I91: identity | J91: Y | K91: numeric | L91: =IFERROR(XLOOKUP($G91&"."&$H91,CaseSource!$A$2:$A$371,CaseSource!$B$2:$B$371,""),"")
A92: financeExpectation | B92: Profile | C92: Loan Sticky Header | D92: Always | F92: 3 | G92: CPV_DETAIL.json | H92: LOAN_EXPECTED | I92: identity | J92: Y | K92: numeric | L92: =IFERROR(XLOOKUP($G92&"."&$H92,CaseSource!$A$2:$A$371,CaseSource!$B$2:$B$371,""),"")
A93: gender | B93: Pre-File | C93: Personal Details Pre File | D93: Always | F93: 1 | G93: CPV_DETAIL.json | H93: SEX | I93: identity | J93: Y | K93: normalized | L93: =IFERROR(XLOOKUP($G93&"."&$H93,CaseSource!$A$2:$A$371,CaseSource!$B$2:$B$371,""),"")
A94: gstNumber | D94: Always | F94: 1 | G94: CPV_DETAIL.json | H94: GST_NUMBER | I94: identity | J94: Y | K94: company flow only | L94: =IFERROR(XLOOKUP($G94&"."&$H94,CaseSource!$A$2:$A$371,CaseSource!$B$2:$B$371,""),"")
A95: gstNumber | D95: Always | F95: 2 | G95: RC_CUSTOMER_ACCOUNT.json | H95: GST_NUMBER | I95: identity | J95: Y | K95: company flow only | L95: =IFERROR(XLOOKUP($G95&"."&$H95,CaseSource!$A$2:$A$371,CaseSource!$B$2:$B$371,""),"")
A96: houseType | B96: Profile | C96: Personal Details Simplified | D96: Always | F96: 1 | G96: CPV_DETAIL.json | H96: RESIDENCE_TYPE | I96: identity | J96: Y | K96: normalized (e.g., your own->Owned) | L96: =IFERROR(XLOOKUP($G96&"."&$H96,CaseSource!$A$2:$A$371,CaseSource!$B$2:$B$371,""),"")
A97: hypothecationBank | B97: Pre-File | C97: Vehicle Pricing Loan Details | D97: Always | F97: 1 | G97: RC_CUSTOMER_ACCOUNT.json | H97: HP_TO | I97: identity | J97: Y | K97: normalized bank name | L97: =IFERROR(XLOOKUP($G97&"."&$H97,CaseSource!$A$2:$A$371,CaseSource!$B$2:$B$371,""),"")
A98: hypothecationBank | B98: Pre-File | C98: Vehicle Pricing Loan Details | D98: Always | F98: 2 | G98: CPV_DETAIL.json | H98: FINANCER | I98: identity | J98: Y | K98: normalized bank name | L98: =IFERROR(XLOOKUP($G98&"."&$H98,CaseSource!$A$2:$A$371,CaseSource!$B$2:$B$371,""),"")
A99: identityProofNumber | B99: Pre-File | C99: Personal Details Pre File | D99: Always | F99: 1 | G99: CPV_DETAIL.json | H99: AADHAAR_NUMBER | I99: identity | J99: Y | K99: clean | L99: =IFERROR(XLOOKUP($G99&"."&$H99,CaseSource!$A$2:$A$371,CaseSource!$B$2:$B$371,""),"")
A100: instrumentType | B100: Post-File | C100: Post File Instrument Details | D100: Always | F100: 1 | G100: RC_INSTRUMENT_DETAIL.json | H100: INSTRMNT_TYPE | I100: identity | J100: Y | K100: Priority: `SI` > `ECS` > `Cheque`. | L100: =IFERROR(XLOOKUP($G100&"."&$H100,CaseSource!$A$2:$A$371,CaseSource!$B$2:$B$371,""),"")
A101: invoice_date | B101: Delivery | C101: Vehicle Delivery Step | D101: Always | F101: 1 | G101: RC_RC_INV_RECEIVING_DETAIL.json | H101: INVOICE_DATE | I101: identity | J101: Y | K101: date | L101: =IFERROR(XLOOKUP($G101&"."&$H101,CaseSource!$A$2:$A$371,CaseSource!$B$2:$B$371,""),"")
A102: invoice_date | B102: Delivery | C102: Vehicle Delivery Step | D102: Always | F102: 2 | G102: RC_RC_INV_STATUS.json | H102: INVOICE_DATE | I102: identity | J102: Y | K102: date | L102: =IFERROR(XLOOKUP($G102&"."&$H102,CaseSource!$A$2:$A$371,CaseSource!$B$2:$B$371,""),"")
A103: invoice_number | B103: Delivery | C103: Loan Sticky Header | D103: Always | F103: 1 | G103: RC_RC_INV_RECEIVING_DETAIL.json | H103: INVOICE_NUMBER | I103: identity | J103: Y | K103: invoice-row priority logic | L103: =IFERROR(XLOOKUP($G103&"."&$H103,CaseSource!$A$2:$A$371,CaseSource!$B$2:$B$371,""),"")
A104: invoice_number | B104: Delivery | C104: Loan Sticky Header | D104: Always | F104: 2 | G104: RC_RC_INV_STATUS.json | H104: INVOICE_NUMBER | I104: identity | J104: Y | K104: invoice-row priority logic | L104: =IFERROR(XLOOKUP($G104&"."&$H104,CaseSource!$A$2:$A$371,CaseSource!$B$2:$B$371,""),"")
A105: invoice_received_as | B105: Delivery | C105: Vehicle Delivery Step | D105: Always | F105: 1 | G105: RC_RC_INV_RECEIVING_DETAIL.json | H105: INV_RECEIVED_ON_DATE_2 | I105: identity | J105: Y | K105: normalized enum | L105: =IFERROR(XLOOKUP($G105&"."&$H105,CaseSource!$A$2:$A$371,CaseSource!$B$2:$B$371,""),"")
A106: invoice_received_date | B106: Delivery | C106: Vehicle Delivery Step | D106: Always | F106: 1 | G106: RC_RC_INV_RECEIVING_DETAIL.json | H106: INV_RECEIVED_ON_DATE | I106: identity | J106: Y | K106: date | L106: =IFERROR(XLOOKUP($G106&"."&$H106,CaseSource!$A$2:$A$371,CaseSource!$B$2:$B$371,""),"")
A107: invoice_received_from | B107: Delivery | C107: Vehicle Delivery Step | D107: Always | F107: 1 | G107: RC_RC_INV_RECEIVING_DETAIL.json | H107: INV_RECEIVED_FROM | I107: identity | J107: Y | K107: clean | L107: =IFERROR(XLOOKUP($G107&"."&$H107,CaseSource!$A$2:$A$371,CaseSource!$B$2:$B$371,""),"")
A108: isFinanced | B108: Profile | C108: Loan Form With Steps | D108: Always | E108: If No => cash flow (Profile + Delivery only). If Yes => Pre-File/Approval/Post-File/Delivery/Payout flow. | F108: 1 | G108: RC_CUSTOMER_ACCOUNT.json | H108: LOAN_AMOUNT | I108: identity | J108: Y | K108: `Car Cash-in/Refinance => Yes`; else loan amount or financier present => `Yes`, else `No`. | L108: =IFERROR(XLOOKUP($G108&"."&$H108,CaseSource!$A$2:$A$371,CaseSource!$B$2:$B$371,""),"")
A109: isFinanced | B109: Profile | C109: Loan Form With Steps | D109: Always | E109: If No => cash flow (Profile + Delivery only). If Yes => Pre-File/Approval/Post-File/Delivery/Payout flow. | F109: 2 | G109: RC_CUSTOMER_ACCOUNT.json | H109: APPLIED_LOAN_AMOUNT | I109: identity | J109: Y | K109: `Car Cash-in/Refinance => Yes`; else loan amount or financier present => `Yes`, else `No`. | L109: =IFERROR(XLOOKUP($G109&"."&$H109,CaseSource!$A$2:$A$371,CaseSource!$B$2:$B$371,""),"")
A110: isFinanced | B110: Profile | C110: Loan Form With Steps | D110: Always | E110: If No => cash flow (Profile + Delivery only). If Yes => Pre-File/Approval/Post-File/Delivery/Payout flow. | F110: 3 | G110: CPV_DETAIL.json | H110: LOAN_EXPECTED | I110: identity | J110: Y | K110: `Car Cash-in/Refinance => Yes`; else loan amount or financier present => `Yes`, else `No`. | L110: =IFERROR(XLOOKUP($G110&"."&$H110,CaseSource!$A$2:$A$371,CaseSource!$B$2:$B$371,""),"")
A111: isFinanced | B111: Profile | C111: Loan Form With Steps | D111: Always | E111: If No => cash flow (Profile + Delivery only). If Yes => Pre-File/Approval/Post-File/Delivery/Payout flow. | F111: 4 | G111: RC_CUSTOMER_ACCOUNT.json | H111: HP_TO | I111: identity | J111: Y | K111: `Car Cash-in/Refinance => Yes`; else loan amount or financier present => `Yes`, else `No`. | L111: =IFERROR(XLOOKUP($G111&"."&$H111,CaseSource!$A$2:$A$371,CaseSource!$B$2:$B$371,""),"")
A112: isFinanced | B112: Profile | C112: Loan Form With Steps | D112: Always | E112: If No => cash flow (Profile + Delivery only). If Yes => Pre-File/Approval/Post-File/Delivery/Payout flow. | F112: 5 | G112: CPV_DETAIL.json | H112: FINANCER | I112: identity | J112: Y | K112: `Car Cash-in/Refinance => Yes`; else loan amount or financier present => `Yes`, else `No`. | L112: =IFERROR(XLOOKUP($G112&"."&$H112,CaseSource!$A$2:$A$371,CaseSource!$B$2:$B$371,""),"")
A113: loan_number | D113: Always | F113: 1 | G113: RC_CUSTOMER_ACCOUNT.json | H113: LOAN_NUMBER_PREFIX | I113: identity | J113: Y | K113: concatenated available parts | L113: =IFERROR(XLOOKUP($G113&"."&$H113,CaseSource!$A$2:$A$371,CaseSource!$B$2:$B$371,""),"")
A114: loanTenureMonths | B114: Profile | C114: Finance Details Form | D114: Always | F114: 1 | G114: RC_CUSTOMER_ACCOUNT.json | H114: TENOR | I114: identity | J114: Y | K114: numeric | L114: =IFERROR(XLOOKUP($G114&"."&$H114,CaseSource!$A$2:$A$371,CaseSource!$B$2:$B$371,""),"")
...

Sheet CaseSource
A1: source_path | B1: value
A2: AUTH_SIGNATORY.json.ACCOUNT_NUMBER_TYPE | B2: CPV
A3: AUTH_SIGNATORY.json.ADD1 | B3: C-5 1504 CLEO COUNTY NOIDA SECTOR-121
A4: AUTH_SIGNATORY.json.ADD2
A5: AUTH_SIGNATORY.json.AUTH_AADHAAR_NUMBER | B5: 951419463882
A6: AUTH_SIGNATORY.json.CITY | B6: NOIDA
A7: AUTH_SIGNATORY.json.CPV_ACCOUNT_NO | B7: 3419
A8: AUTH_SIGNATORY.json.DATA_LOCATION_CODE | B8: 03
A9: AUTH_SIGNATORY.json.DATE_OF_BIRTH | B9: 1987-09-09T00:00:00
A10: AUTH_SIGNATORY.json.DESIGNATION | B10: DIRECTOR
A11: AUTH_SIGNATORY.json.FAX
A12: AUTH_SIGNATORY.json.HP_GROUP | B12: 01
A13: AUTH_SIGNATORY.json.MOBILE
A14: AUTH_SIGNATORY.json.NAME | B14: GAURAV KHANNA
A15: AUTH_SIGNATORY.json.ORIGINAL_HP_GROUP
A16: AUTH_SIGNATORY.json.PHONE | B16: 9811542232
A17: AUTH_SIGNATORY.json.PIN | B17: 201309
A18: CPV_DETAIL.json.AADHAAR_NUMBER
A19: CPV_DETAIL.json.ACCOUNT_NUMBER_TYPE | B19: CPV
A20: CPV_DETAIL.json.ANNUAL_INCOME | B20: 3797080
A21: CPV_DETAIL.json.CAR_MODEL | B21: S PRESSO LXI CNG
A22: CPV_DETAIL.json.CATEGORY | B22: PVT LTD
A23: CPV_DETAIL.json.CDB_ACCOUNT_NO | B23: 3000004231
A24: CPV_DETAIL.json.CLS_REMARKS
A25: CPV_DETAIL.json.CLS_STATUS
A26: CPV_DETAIL.json.CPV_ACCOUNT_NO | B26: 3419
A27: CPV_DETAIL.json.CPV_DATE | B27: 2025-01-02T00:00:00
A28: CPV_DETAIL.json.CPV_G_OFF_STATUS
A29: CPV_DETAIL.json.CPV_G_RES_STATUS
A30: CPV_DETAIL.json.CPV_MONTH_YEAR | B30: 012025
A31: CPV_DETAIL.json.CPV_OFF_STATUS
A32: CPV_DETAIL.json.CPV_RES_STATUS
A33: CPV_DETAIL.json.CPV_SEND_AT_TIME
A34: CPV_DETAIL.json.CPV_SEND_ON_DATE
A35: CPV_DETAIL.json.CREATED_BY_USER
A36: CPV_DETAIL.json.CREATED_ON_DATE
A37: CPV_DETAIL.json.CREATED_ON_TIME
A38: CPV_DETAIL.json.CUST_NAME_FIRST | B38: GOURAV
A39: CPV_DETAIL.json.CUST_NAME_LAST | B39: PVT LTD 2
A40: CPV_DETAIL.json.CUST_NAME_MIDDLE | B40: LUMINARIES
A41: CPV_DETAIL.json.CUSTOMER_NAME | B41: GOURAV LUMINARIES PVT LTD 2
A42: CPV_DETAIL.json.DATA_LOCATION_CODE | B42: 03
A43: CPV_DETAIL.json.DATA_STATUS | B43: COMPLETE
A44: CPV_DETAIL.json.DATE_OF_BIRTH | B44: 1995-10-12T00:00:00
A45: CPV_DETAIL.json.DEALT_BY | B45: DRG
A46: CPV_DETAIL.json.DRIVING_LICENSE
A47: CPV_DETAIL.json.E_MAIL | B47: GAURAV@GOURAVROSHNI.COM
A48: CPV_DETAIL.json.EDUCATION | B48: NA
A49: CPV_DETAIL.json.EMAIL_ADDRESS | B49: gaurav@gouravroshni.com
A50: CPV_DETAIL.json.FATHERS_NAME_FIRST
A51: CPV_DETAIL.json.FATHERS_NAME_LAST
A52: CPV_DETAIL.json.FATHERS_NAME_MIDDLE
A53: CPV_DETAIL.json.FINANCER | B53: HDFC
A54: CPV_DETAIL.json.GURANTOR_AVAILABLE | B54: N
A55: CPV_DETAIL.json.HEAD_NAME | B55: M/s.
A56: CPV_DETAIL.json.HIRE_TYPE | B56: Company
A57: CPV_DETAIL.json.HP_GROUP | B57: 01
A58: CPV_DETAIL.json.HUSBAND_NAME
A59: CPV_DETAIL.json.ICICI_ENTRY_NUMBER | B59: BY BANK
A60: CPV_DETAIL.json.INDUSTRY_DETAIL | B60: TRADING
A61: CPV_DETAIL.json.IS_REQ_G_OFF_VERIFICATION | B61: 0
A62: CPV_DETAIL.json.IS_REQ_G_RES_VERIFICATION | B62: 0
A63: CPV_DETAIL.json.IS_REQ_OFF_VERIFICATION | B63: 0
A64: CPV_DETAIL.json.IS_REQ_RES_VERIFICATION | B64: 1
A65: CPV_DETAIL.json.LAST_EDIT_BY_USER
A66: CPV_DETAIL.json.LAST_EDIT_ON_DATE
A67: CPV_DETAIL.json.LAST_EDIT_ON_TIME
A68: CPV_DETAIL.json.LOAN_EXPECTED | B68: 525000
A69: CPV_DETAIL.json.LOAN_TYPE | B69: Auto Loan
A70: CPV_DETAIL.json.MARITAL_STATUS
A71: CPV_DETAIL.json.MARKETING_BY | B71: 2021
A72: CPV_DETAIL.json.MOBILE
A73: CPV_DETAIL.json.MOTHERS_MAIDEN_NAME
A74: CPV_DETAIL.json.NCCB
A75: CPV_DETAIL.json.NO_OF_DEPENDANTS | B75: 0
A76: CPV_DETAIL.json.OFF_ADD1 | B76: PLOT NO-11/1,2 & 12/1 SITE-IV SAHIBABAD
A77: CPV_DETAIL.json.OFF_ADD2 | B77: INDUSTRIAL AREA
A78: CPV_DETAIL.json.OFF_CITY | B78: GHAZIABAD
A79: CPV_DETAIL.json.OFF_FAX
A80: CPV_DETAIL.json.OFF_NAME | B80: GOURAV LUMINARIES PVT LTD
A81: CPV_DETAIL.json.OFF_PHONE1 | B81: 9811542232
A82: CPV_DETAIL.json.OFF_PHONE2
A83: CPV_DETAIL.json.OFF_PHONE3
A84: CPV_DETAIL.json.OFF_PIN | B84: 201010
A85: CPV_DETAIL.json.ORGANISATION_TYPE | B85: ELECTRONIC
A86: CPV_DETAIL.json.ORIGINAL_HP_GROUP
A87: CPV_DETAIL.json.PAGER
A88: CPV_DETAIL.json.PAN_NUMBER | B88: AAACG3334L
A89: CPV_DETAIL.json.PASSPORT_NUMBER
A90: CPV_DETAIL.json.PERMANENT_ADDRESS | B90: C-5 1504 CLEO COUNTY NOIDA SECTOR-121 NOIDA 201309
A91: CPV_DETAIL.json.PREVIOUS_RELATION_WITH_US | B91: NO
A92: CPV_DETAIL.json.PROFESSION_TYPE | B92: Self-Employed
A93: CPV_DETAIL.json.PURPOSE_OF_LOAN | B93: Business
A94: CPV_DETAIL.json.REF1_ADD | B94: 12-D BLOCK PREET VIHAR DELHI 110092
A95: CPV_DETAIL.json.REF1_NAME | B95: ANIL SETHI
A96: CPV_DETAIL.json.REF1_PHONE | B96: 9811024536
A97: CPV_DETAIL.json.REF1_RELATION | B97: FRIEND
A98: CPV_DETAIL.json.REF2_ADD | B98: B-209 S/F SURYA NAGAR GHAZIABAD 201010
A99: CPV_DETAIL.json.REF2_NAME | B99: SANJAY NAGPAL
A100: CPV_DETAIL.json.REF2_PHONE | B100: 9811161499
...
