Workbook
Name NewFieldOptionsDisplay: 'DropdownData'!$A$2:$A$500
Name RoleFirst: 'DropdownData'!$C$2:$C$22
Name RoleNext: 'DropdownData'!$D$2:$D$21

Sheet LegacyToNewMap
A1: legacy_file | B1: legacy_field | C1: legacy_value | D1: new_field_1 | E1: new_field_2 | F1: new_field_3 | G1: new_field_4 | H1: new_field_5 | I1: role_1 | J1: role_2 | K1: role_3 | L1: role_4 | M1: role_5 | N1: comments_normalization | O1: legacy_map_status
A2: AUTH_SIGNATORY.json | B2: ACCOUNT_NUMBER_TYPE | C2: CPV | O2: =IF(COUNTA(D2:H2)=0,"UNMAPPED","MAPPED")
A3: AUTH_SIGNATORY.json | B3: ADD1 | C3: C-5 1504 CLEO COUNTY NOIDA SECTOR-121 | O3: =IF(COUNTA(D3:H3)=0,"UNMAPPED","MAPPED")
A4: AUTH_SIGNATORY.json | B4: ADD2 | O4: =IF(COUNTA(D4:H4)=0,"UNMAPPED","MAPPED")
A5: AUTH_SIGNATORY.json | B5: AUTH_AADHAAR_NUMBER | C5: 951419463882 | D5: co_aadhaar (Aadhaar) | I5: Mapping | O5: =IF(COUNTA(D5:H5)=0,"UNMAPPED","MAPPED")
A6: AUTH_SIGNATORY.json | B6: CITY | C6: NOIDA | O6: =IF(COUNTA(D6:H6)=0,"UNMAPPED","MAPPED")
A7: AUTH_SIGNATORY.json | B7: CPV_ACCOUNT_NO | C7: 3419 | O7: =IF(COUNTA(D7:H7)=0,"UNMAPPED","MAPPED")
A8: AUTH_SIGNATORY.json | B8: DATA_LOCATION_CODE | C8: 03 | O8: =IF(COUNTA(D8:H8)=0,"UNMAPPED","MAPPED")
A9: AUTH_SIGNATORY.json | B9: DATE_OF_BIRTH | C9: 1987-09-09T00:00:00 | O9: =IF(COUNTA(D9:H9)=0,"UNMAPPED","MAPPED")
A10: AUTH_SIGNATORY.json | B10: DESIGNATION | C10: DIRECTOR | O10: =IF(COUNTA(D10:H10)=0,"UNMAPPED","MAPPED")
A11: AUTH_SIGNATORY.json | B11: FAX | O11: =IF(COUNTA(D11:H11)=0,"UNMAPPED","MAPPED")
A12: AUTH_SIGNATORY.json | B12: HP_GROUP | C12: 01 | O12: =IF(COUNTA(D12:H12)=0,"UNMAPPED","MAPPED")
A13: AUTH_SIGNATORY.json | B13: MOBILE | O13: =IF(COUNTA(D13:H13)=0,"UNMAPPED","MAPPED")
A14: AUTH_SIGNATORY.json | B14: NAME | C14: GAURAV KHANNA | D14: co_customerName (Name) | I14: Fallback1 | O14: =IF(COUNTA(D14:H14)=0,"UNMAPPED","MAPPED")
A15: AUTH_SIGNATORY.json | B15: ORIGINAL_HP_GROUP | O15: =IF(COUNTA(D15:H15)=0,"UNMAPPED","MAPPED")
A16: AUTH_SIGNATORY.json | B16: PHONE | C16: 9811542232 | D16: primaryMobile (Primary Mobile [Individual: Mobile | Company: Office Mobile]) | I16: Fallback3 | O16: =IF(COUNTA(D16:H16)=0,"UNMAPPED","MAPPED")
A17: AUTH_SIGNATORY.json | B17: PIN | C17: 201309 | O17: =IF(COUNTA(D17:H17)=0,"UNMAPPED","MAPPED")
A18: CPV_DETAIL.json | B18: AADHAAR_NUMBER | D18: addressProofNumber (Address Proof Number) | E18: co_aadhaar (Aadhaar) | F18: identityProofNumber (Identity Proof Number) | I18: Mapping | J18: Fallback2 | K18: Mapping | O18: =IF(COUNTA(D18:H18)=0,"UNMAPPED","MAPPED")
A19: CPV_DETAIL.json | B19: ACCOUNT_NUMBER_TYPE | C19: CPV | O19: =IF(COUNTA(D19:H19)=0,"UNMAPPED","MAPPED")
A20: CPV_DETAIL.json | B20: ANNUAL_INCOME | C20: 3797080 | D20: totalIncomeITR (Total Income (as per ITR)) | I20: Mapping | O20: =IF(COUNTA(D20:H20)=0,"UNMAPPED","MAPPED")
A21: CPV_DETAIL.json | B21: CAR_MODEL | C21: S PRESSO LXI CNG | D21: vehicleMake (Make) | I21: Fallback2 | O21: =IF(COUNTA(D21:H21)=0,"UNMAPPED","MAPPED")
A22: CPV_DETAIL.json | B22: CATEGORY | C22: PVT LTD | D22: companyType (Type of Company) | I22: Mapping | O22: =IF(COUNTA(D22:H22)=0,"UNMAPPED","MAPPED")
A23: CPV_DETAIL.json | B23: CDB_ACCOUNT_NO | C23: 3000004231 | O23: =IF(COUNTA(D23:H23)=0,"UNMAPPED","MAPPED")
A24: CPV_DETAIL.json | B24: CLS_REMARKS | O24: =IF(COUNTA(D24:H24)=0,"UNMAPPED","MAPPED")
A25: CPV_DETAIL.json | B25: CLS_STATUS | O25: =IF(COUNTA(D25:H25)=0,"UNMAPPED","MAPPED")
A26: CPV_DETAIL.json | B26: CPV_ACCOUNT_NO | C26: 3419 | O26: =IF(COUNTA(D26:H26)=0,"UNMAPPED","MAPPED")
A27: CPV_DETAIL.json | B27: CPV_DATE | C27: 2025-01-02T00:00:00 | D27: approval_approvalDate (approval_approvalDate) | E27: receivingDate (Receiving Date) | I27: Fallback3 | J27: Fallback2 | O27: =IF(COUNTA(D27:H27)=0,"UNMAPPED","MAPPED")
A28: CPV_DETAIL.json | B28: CPV_G_OFF_STATUS | O28: =IF(COUNTA(D28:H28)=0,"UNMAPPED","MAPPED")
A29: CPV_DETAIL.json | B29: CPV_G_RES_STATUS | O29: =IF(COUNTA(D29:H29)=0,"UNMAPPED","MAPPED")
A30: CPV_DETAIL.json | B30: CPV_MONTH_YEAR | C30: 012025 | O30: =IF(COUNTA(D30:H30)=0,"UNMAPPED","MAPPED")
A31: CPV_DETAIL.json | B31: CPV_OFF_STATUS | O31: =IF(COUNTA(D31:H31)=0,"UNMAPPED","MAPPED")
A32: CPV_DETAIL.json | B32: CPV_RES_STATUS | O32: =IF(COUNTA(D32:H32)=0,"UNMAPPED","MAPPED")
A33: CPV_DETAIL.json | B33: CPV_SEND_AT_TIME | O33: =IF(COUNTA(D33:H33)=0,"UNMAPPED","MAPPED")
A34: CPV_DETAIL.json | B34: CPV_SEND_ON_DATE | O34: =IF(COUNTA(D34:H34)=0,"UNMAPPED","MAPPED")
A35: CPV_DETAIL.json | B35: CREATED_BY_USER | O35: =IF(COUNTA(D35:H35)=0,"UNMAPPED","MAPPED")
A36: CPV_DETAIL.json | B36: CREATED_ON_DATE | O36: =IF(COUNTA(D36:H36)=0,"UNMAPPED","MAPPED")
A37: CPV_DETAIL.json | B37: CREATED_ON_TIME | O37: =IF(COUNTA(D37:H37)=0,"UNMAPPED","MAPPED")
A38: CPV_DETAIL.json | B38: CUST_NAME_FIRST | C38: GOURAV | O38: =IF(COUNTA(D38:H38)=0,"UNMAPPED","MAPPED")
A39: CPV_DETAIL.json | B39: CUST_NAME_LAST | C39: PVT LTD 2 | O39: =IF(COUNTA(D39:H39)=0,"UNMAPPED","MAPPED")
A40: CPV_DETAIL.json | B40: CUST_NAME_MIDDLE | C40: LUMINARIES | O40: =IF(COUNTA(D40:H40)=0,"UNMAPPED","MAPPED")
A41: CPV_DETAIL.json | B41: CUSTOMER_NAME | C41: GOURAV LUMINARIES PVT LTD 2 | D41: customerName (isCompany ? "Company Name" : "Customer Name" [Individual: Customer Name | Company: Company Name]) | I41: Fallback1 | O41: =IF(COUNTA(D41:H41)=0,"UNMAPPED","MAPPED")
A42: CPV_DETAIL.json | B42: DATA_LOCATION_CODE | C42: 03 | O42: =IF(COUNTA(D42:H42)=0,"UNMAPPED","MAPPED")
A43: CPV_DETAIL.json | B43: DATA_STATUS | C43: COMPLETE | O43: =IF(COUNTA(D43:H43)=0,"UNMAPPED","MAPPED")
A44: CPV_DETAIL.json | B44: DATE_OF_BIRTH | C44: 1995-10-12T00:00:00 | D44: co_dob (DOB) | E44: dob (isCompany ? "Date of Incorporation" : "Date of Birth" [Individual: Date of Birth | Company: Date of Incorporation]) | I44: Fallback1 | J44: Mapping | O44: =IF(COUNTA(D44:H44)=0,"UNMAPPED","MAPPED")
A45: CPV_DETAIL.json | B45: DEALT_BY | C45: DRG | O45: =IF(COUNTA(D45:H45)=0,"UNMAPPED","MAPPED")
A46: CPV_DETAIL.json | B46: DRIVING_LICENSE | O46: =IF(COUNTA(D46:H46)=0,"UNMAPPED","MAPPED")
A47: CPV_DETAIL.json | B47: E_MAIL | C47: GAURAV@GOURAVROSHNI.COM | D47: email (Email) | I47: Mapping | O47: =IF(COUNTA(D47:H47)=0,"UNMAPPED","MAPPED")
A48: CPV_DETAIL.json | B48: EDUCATION | C48: NA | D48: education (Education) | I48: Mapping | O48: =IF(COUNTA(D48:H48)=0,"UNMAPPED","MAPPED")
A49: CPV_DETAIL.json | B49: EMAIL_ADDRESS | C49: gaurav@gouravroshni.com | D49: email (Email) | I49: Fallback1 | O49: =IF(COUNTA(D49:H49)=0,"UNMAPPED","MAPPED")
A50: CPV_DETAIL.json | B50: FATHERS_NAME_FIRST | D50: sdwOf (Father / Husband Name) | I50: Mapping | O50: =IF(COUNTA(D50:H50)=0,"UNMAPPED","MAPPED")
A51: CPV_DETAIL.json | B51: FATHERS_NAME_LAST | O51: =IF(COUNTA(D51:H51)=0,"UNMAPPED","MAPPED")
A52: CPV_DETAIL.json | B52: FATHERS_NAME_MIDDLE | O52: =IF(COUNTA(D52:H52)=0,"UNMAPPED","MAPPED")
A53: CPV_DETAIL.json | B53: FINANCER | C53: HDFC | D53: approval_bankName (approval_bankName) | E53: postfile_bankName (Bank Name) | F53: hypothecationBank (Hypothecation Bank) | G53: isFinanced (isFinanced) | I53: Fallback1 | J53: Fallback1 | K53: Fallback1 | L53: Fallback4 | O53: =IF(COUNTA(D53:H53)=0,"UNMAPPED","MAPPED")
A54: CPV_DETAIL.json | B54: GURANTOR_AVAILABLE | C54: N | O54: =IF(COUNTA(D54:H54)=0,"UNMAPPED","MAPPED")
A55: CPV_DETAIL.json | B55: HEAD_NAME | C55: M/s. | O55: =IF(COUNTA(D55:H55)=0,"UNMAPPED","MAPPED")
A56: CPV_DETAIL.json | B56: HIRE_TYPE | C56: Company | D56: applicantType (Applicant Category) | I56: Mapping | O56: =IF(COUNTA(D56:H56)=0,"UNMAPPED","MAPPED")
A57: CPV_DETAIL.json | B57: HP_GROUP | C57: 01 | O57: =IF(COUNTA(D57:H57)=0,"UNMAPPED","MAPPED")
A58: CPV_DETAIL.json | B58: HUSBAND_NAME | O58: =IF(COUNTA(D58:H58)=0,"UNMAPPED","MAPPED")
A59: CPV_DETAIL.json | B59: ICICI_ENTRY_NUMBER | C59: BY BANK | O59: =IF(COUNTA(D59:H59)=0,"UNMAPPED","MAPPED")
A60: CPV_DETAIL.json | B60: INDUSTRY_DETAIL | C60: TRADING | D60: designation (Designation) | I60: Fallback1 | O60: =IF(COUNTA(D60:H60)=0,"UNMAPPED","MAPPED")
A61: CPV_DETAIL.json | B61: IS_REQ_G_OFF_VERIFICATION | C61: 0 | O61: =IF(COUNTA(D61:H61)=0,"UNMAPPED","MAPPED")
A62: CPV_DETAIL.json | B62: IS_REQ_G_RES_VERIFICATION | C62: 0 | O62: =IF(COUNTA(D62:H62)=0,"UNMAPPED","MAPPED")
A63: CPV_DETAIL.json | B63: IS_REQ_OFF_VERIFICATION | C63: 0 | O63: =IF(COUNTA(D63:H63)=0,"UNMAPPED","MAPPED")
A64: CPV_DETAIL.json | B64: IS_REQ_RES_VERIFICATION | C64: 1 | O64: =IF(COUNTA(D64:H64)=0,"UNMAPPED","MAPPED")
A65: CPV_DETAIL.json | B65: LAST_EDIT_BY_USER | O65: =IF(COUNTA(D65:H65)=0,"UNMAPPED","MAPPED")
A66: CPV_DETAIL.json | B66: LAST_EDIT_ON_DATE | O66: =IF(COUNTA(D66:H66)=0,"UNMAPPED","MAPPED")
A67: CPV_DETAIL.json | B67: LAST_EDIT_ON_TIME | O67: =IF(COUNTA(D67:H67)=0,"UNMAPPED","MAPPED")
A68: CPV_DETAIL.json | B68: LOAN_EXPECTED | C68: 525000 | D68: approval_loanAmountApproved (approval_loanAmountApproved) | E68: postfile_loanAmountApproved (Loan Amount Approved) | F68: financeExpectation (Expected Funding) | G68: isFinanced (isFinanced) | I68: Fallback1 | J68: Fallback1 | K68: Fallback2 | L68: Fallback2 | O68: =IF(COUNTA(D68:H68)=0,"UNMAPPED","MAPPED")
A69: CPV_DETAIL.json | B69: LOAN_TYPE | C69: Auto Loan | D69: typeOfLoan (Type of Loan) | I69: Fallback2 | O69: =IF(COUNTA(D69:H69)=0,"UNMAPPED","MAPPED")
A70: CPV_DETAIL.json | B70: MARITAL_STATUS | D70: maritalStatus (Marital Status) | I70: Mapping | O70: =IF(COUNTA(D70:H70)=0,"UNMAPPED","MAPPED")
A71: CPV_DETAIL.json | B71: MARKETING_BY | C71: 2021 | O71: =IF(COUNTA(D71:H71)=0,"UNMAPPED","MAPPED")
A72: CPV_DETAIL.json | B72: MOBILE | D72: co_primaryMobile (Mobile) | E72: primaryMobile (Primary Mobile [Individual: Mobile | Company: Office Mobile]) | I72: Fallback4 | J72: Fallback5 | O72: =IF(COUNTA(D72:H72)=0,"UNMAPPED","MAPPED")
A73: CPV_DETAIL.json | B73: MOTHERS_MAIDEN_NAME | D73: motherName (Mother's Name) | I73: Mapping | O73: =IF(COUNTA(D73:H73)=0,"UNMAPPED","MAPPED")
A74: CPV_DETAIL.json | B74: NCCB | O74: =IF(COUNTA(D74:H74)=0,"UNMAPPED","MAPPED")
A75: CPV_DETAIL.json | B75: NO_OF_DEPENDANTS | C75: 0 | D75: co_dependents (Dependents) | E75: dependents (Dependents) | I75: Mapping | J75: Mapping | O75: =IF(COUNTA(D75:H75)=0,"UNMAPPED","MAPPED")
A76: CPV_DETAIL.json | B76: OFF_ADD1 | C76: PLOT NO-11/1,2 & 12/1 SITE-IV SAHIBABAD | D76: employmentAddress (Company Address) | E76: residenceAddress (Present Address [Individual: Residence Address | Company: Office Address]) | I76: Mapping | J76: Mapping | O76: =IF(COUNTA(D76:H76)=0,"UNMAPPED","MAPPED")
A77: CPV_DETAIL.json | B77: OFF_ADD2 | C77: INDUSTRIAL AREA | O77: =IF(COUNTA(D77:H77)=0,"UNMAPPED","MAPPED")
A78: CPV_DETAIL.json | B78: OFF_CITY | C78: GHAZIABAD | D78: city (isCompany ? "Present City" : "City" [Individual: Residence City | Company: Office City]) | E78: employmentCity (City) | I78: Mapping | J78: Mapping | O78: =IF(COUNTA(D78:H78)=0,"UNMAPPED","MAPPED")
A79: CPV_DETAIL.json | B79: OFF_FAX | O79: =IF(COUNTA(D79:H79)=0,"UNMAPPED","MAPPED")
A80: CPV_DETAIL.json | B80: OFF_NAME | C80: GOURAV LUMINARIES PVT LTD | O80: =IF(COUNTA(D80:H80)=0,"UNMAPPED","MAPPED")
A81: CPV_DETAIL.json | B81: OFF_PHONE1 | C81: 9811542232 | D81: primaryMobile (Primary Mobile [Individual: Mobile | Company: Office Mobile]) | I81: Mapping | O81: =IF(COUNTA(D81:H81)=0,"UNMAPPED","MAPPED")
A82: CPV_DETAIL.json | B82: OFF_PHONE2 | O82: =IF(COUNTA(D82:H82)=0,"UNMAPPED","MAPPED")
A83: CPV_DETAIL.json | B83: OFF_PHONE3 | O83: =IF(COUNTA(D83:H83)=0,"UNMAPPED","MAPPED")
A84: CPV_DETAIL.json | B84: OFF_PIN | C84: 201010 | D84: employmentPincode (Pincode) | E84: pincode (isCompany ? "Present Pincode" : "Pincode" [Individual: Residence Pincode | Company: Office Pincode]) | I84: Mapping | J84: Mapping | O84: =IF(COUNTA(D84:H84)=0,"UNMAPPED","MAPPED")
A85: CPV_DETAIL.json | B85: ORGANISATION_TYPE | C85: ELECTRONIC | D85: businessNature (Nature of Business) | E85: companyType (Type of Company) | I85: Mapping | J85: Fallback1 | O85: =IF(COUNTA(D85:H85)=0,"UNMAPPED","MAPPED")
A86: CPV_DETAIL.json | B86: ORIGINAL_HP_GROUP | O86: =IF(COUNTA(D86:H86)=0,"UNMAPPED","MAPPED")
A87: CPV_DETAIL.json | B87: PAGER | O87: =IF(COUNTA(D87:H87)=0,"UNMAPPED","MAPPED")
A88: CPV_DETAIL.json | B88: PAN_NUMBER | C88: AAACG3334L | D88: panNumber (PAN Number) | I88: Mapping | O88: =IF(COUNTA(D88:H88)=0,"UNMAPPED","MAPPED")
A89: CPV_DETAIL.json | B89: PASSPORT_NUMBER | O89: =IF(COUNTA(D89:H89)=0,"UNMAPPED","MAPPED")
A90: CPV_DETAIL.json | B90: PERMANENT_ADDRESS | C90: C-5 1504 CLEO COUNTY NOIDA SECTOR-121 NOIDA 201309 | D90: permanentAddress (Permanent Address) | I90: Mapping | O90: =IF(COUNTA(D90:H90)=0,"UNMAPPED","MAPPED")
A91: CPV_DETAIL.json | B91: PREVIOUS_RELATION_WITH_US | C91: NO | O91: =IF(COUNTA(D91:H91)=0,"UNMAPPED","MAPPED")
A92: CPV_DETAIL.json | B92: PROFESSION_TYPE | C92: Self-Employed | D92: occupationType (Occupation) | I92: Mapping | O92: =IF(COUNTA(D92:H92)=0,"UNMAPPED","MAPPED")
A93: CPV_DETAIL.json | B93: PURPOSE_OF_LOAN | C93: Business | D93: purposeOfLoan (Purpose of Loan) | E93: typeOfLoan (Type of Loan) | I93: Mapping | J93: Fallback4 | O93: =IF(COUNTA(D93:H93)=0,"UNMAPPED","MAPPED")
A94: CPV_DETAIL.json | B94: REF1_ADD | C94: 12-D BLOCK PREET VIHAR DELHI 110092 | O94: =IF(COUNTA(D94:H94)=0,"UNMAPPED","MAPPED")
A95: CPV_DETAIL.json | B95: REF1_NAME | C95: ANIL SETHI | O95: =IF(COUNTA(D95:H95)=0,"UNMAPPED","MAPPED")
A96: CPV_DETAIL.json | B96: REF1_PHONE | C96: 9811024536 | O96: =IF(COUNTA(D96:H96)=0,"UNMAPPED","MAPPED")
A97: CPV_DETAIL.json | B97: REF1_RELATION | C97: FRIEND | O97: =IF(COUNTA(D97:H97)=0,"UNMAPPED","MAPPED")
A98: CPV_DETAIL.json | B98: REF2_ADD | C98: B-209 S/F SURYA NAGAR GHAZIABAD 201010 | O98: =IF(COUNTA(D98:H98)=0,"UNMAPPED","MAPPED")
A99: CPV_DETAIL.json | B99: REF2_NAME | C99: SANJAY NAGPAL | O99: =IF(COUNTA(D99:H99)=0,"UNMAPPED","MAPPED")
A100: CPV_DETAIL.json | B100: REF2_PHONE | C100: 9811161499 | O100: =IF(COUNTA(D100:H100)=0,"UNMAPPED","MAPPED")
...

Sheet NewFieldOptions
A1: display | B1: new_field | C1: display_label | D1: dropdown_values | E1: new_type
A2: __deliveryInitialized (__deliveryInitialized) | B2: __deliveryInitialized | C2: __deliveryInitialized | E2: string
A3: __dispatchInitialized (__dispatchInitialized) | B3: __dispatchInitialized | C3: __dispatchInitialized | E3: string
A4: __postfileLocked (__postfileLocked) | B4: __postfileLocked | C4: __postfileLocked | E4: string
A5: aadhaarCardDocUrl (aadhaarCardDocUrl) | B5: aadhaarCardDocUrl | C5: aadhaarCardDocUrl | E5: string
A6: accessoriesAmount (Accessories Amount) | B6: accessoriesAmount | C6: Accessories Amount | E6: number
A7: accountNumber (Applicant Account Number) | B7: accountNumber | C7: Applicant Account Number | E7: number
A8: accountSinceYears (Account Since (Years)) | B8: accountSinceYears | C8: Account Since (Years) | E8: number
A9: accountType (Account Type) | B9: accountType | C9: Account Type | E9: string
A10: addressProofDocUrl (addressProofDocUrl) | B10: addressProofDocUrl | C10: addressProofDocUrl | E10: string
A11: addressProofNumber (Address Proof Number) | B11: addressProofNumber | C11: Address Proof Number | E11: boolean
A12: addressProofType (Address Proof (type)) | B12: addressProofType | C12: Address Proof (type) | E12: boolean
A13: addressType (Address Type) | B13: addressType | C13: Address Type | E13: number
... A279: delivery_rcFile (delivery_rcFile) | B279: delivery_rcFile | C279: delivery_rcFile | E279: string
A280: dependents (Dependents) | B280: dependents | C280: Dependents | D280: owned | rented | Undergraduate | Graduate | Postgraduate | Others | E280: number
A281: designation (Designation) | B281: designation | C281: Designation | E281: string
A282: disburseAmount (Disbursement Amount) | B282: disburseAmount | C282: Disbursement Amount | E282: number
A283: disbursedDate (Disbursement Date) | B283: disbursedDate | C283: Disbursement Date | E283: string
A284: disbursement_date (disbursement_date) | B284: disbursement_date | C284: disbursement_date | E284: string
A285: disbursement_status (disbursement_status) | B285: disbursement_status | C285: disbursement_status | E285: string
A286: disbursement_time (disbursement_time) | B286: disbursement_time | C286: disbursement_time | E286: string
A287: disbursementDate (disbursementDate) | B287: disbursementDate | C287: disbursementDate | E287: string
A288: disbursementStatus (disbursementStatus) | B288: disbursementStatus | C288: disbursementStatus | E288: string
A289: dispatch_date (dispatch_date) | B289: dispatch_date | C289: dispatch_date | E289: string
A290: dispatch_through (dispatch_through) | B290: dispatch_through | C290: dispatch_through | E290: string
A291: dispatch_time (dispatch_time) | B291: dispatch_time | C291: dispatch_time | E291: string
A292: dlDocUrl (dlDocUrl) | B292: dlDocUrl | C292: dlDocUrl | E292: string
A293: dob (isCompany ? "Date of Incorporation" : "Date of Birth" [Individual: Date of Birth | Company: Date of Incorporation]) | B293: dob | C293: isCompany ? "Date of Incorporation" : "Date of Birth" [Individual: Date of Birth | Company: Date of Incorporation] | D293: Male | Female | Married | E293: number
A294: docs_prepared_by (docs_prepared_by) | B294: docs_prepared_by | C294: docs_prepared_by | E294: string
A295: docsPreparedBy (Docs Prepared By) | B295: docsPreparedBy | C295: Docs Prepared By | E295: string
A296: ecs_accountNumber (ecs_accountNumber) | B296: ecs_accountNumber | C296: ecs_accountNumber | E296: number
A297: ecs_amount (ecs_amount) | B297: ecs_amount | C297: ecs_amount | E297: number
A298: ecs_bankName (ecs_bankName) | B298: ecs_bankName | C298: ecs_bankName | E298: number
A299: ecs_date (ecs_date) | B299: ecs_date | C299: ecs_date | E299: number
A300: ecs_favouring (ecs_favouring) | B300: ecs_favouring | C300: ecs_favouring | E300: string
A301: ecs_image (ecs_image) | B301: ecs_image | C301: ecs_image | E301: string
A302: ecs_micrCode (ecs_micrCode) | B302: ecs_micrCode | C302: ecs_micrCode | E302: number
A303: ecs_signedBy (ecs_signedBy) | B303: ecs_signedBy | C303: ecs_signedBy | E303: string
A304: ecs_tag (ecs_tag) | B304: ecs_tag | C304: ecs_tag | E304: string
A305: education (Education) | B305: education | C305: Education | D305: Undergraduate | Graduate | Postgraduate | Others | E305: string
A306: email (Email) | B306: email | C306: Email | E306: boolean
A307: employmentAddress (Company Address) | B307: employmentAddress | C307: Company Address | E307: string
A308: employmentCity (City) | B308: employmentCity | C308: City | E308: string
A309: employmentPhone (Phone Number) | B309: employmentPhone | C309: Phone Number | E309: string
A310: employmentPincode (Pincode) | B310: employmentPincode | C310: Pincode | E310: string
A311: experienceCurrent (companyMode ? "Business Since / Current Vintage (Years)" : "Current Exp (Years)") | B311: experienceCurrent | C311: companyMode ? "Business Since / Current Vintage (Years)" : "Current Exp (Years)" | E311: string
A312: exShowroomPrice (Ex-Showroom Price) | B312: exShowroomPrice | C312: Ex-Showroom Price | E312: number
A313: financeExpectation (Expected Funding) | B313: financeExpectation | C313: Expected Funding | E313: number
A314: gender (Gender) | B314: gender | C314: Gender | D314: Male | Female | Married | Unmarried | Undergraduate | E314: number
A315: gstDocUrl (gstDocUrl) | B315: gstDocUrl | C315: gstDocUrl | E315: string
A316: gstNumber (GST Number) | B316: gstNumber | C316: GST Number | D316: Single | Married | Divorced | Widowed | E316: string
A317: gu_aadhaar (Aadhaar) | B317: gu_aadhaar | C317: Aadhaar | E317: string
A318: gu_aadhaarCardDocUrl (gu_aadhaarCardDocUrl) | B318: gu_aadhaarCardDocUrl | C318: gu_aadhaarCardDocUrl | E318: string
A319: gu_address (Address) | B319: gu_address | C319: Address | E319: string
A320: gu_addressProofDocUrl (gu_addressProofDocUrl) | B320: gu_addressProofDocUrl | C320: gu_addressProofDocUrl | E320: string
A321: gu_businessNature (Nature of Business) | B321: gu_businessNature | C321: Nature of Business | E321: string
A322: gu_city (City) | B322: gu_city | C322: City | E322: string
A323: gu_companyAddress (Company Address) | B323: gu_companyAddress | C323: Company Address | E323: string
A324: gu_companyCity (City) | B324: gu_companyCity | C324: City | E324: string
A325: gu_companyName (Company Name) | B325: gu_companyName | C325: Company Name | E325: string
A326: gu_companyPhone (Phone No) | B326: gu_companyPhone | C326: Phone No | E326: string
A327: gu_companyPincode (Pin Code) | B327: gu_companyPincode | C327: Pin Code | E327: string
A328: gu_companyType (Type of Company) | B328: gu_companyType | C328: Type of Company | E328: string
... A351: hasGuarantor (Is Guarantor Applicable) | B351: hasGuarantor | C351: Is Guarantor Applicable | E351: boolean
A352: houseType (House Type) | B352: houseType | C352: House Type | D352: owned | rented | E352: number
A353: hypothecation (Hypothecation) | B353: hypothecation | C353: Hypothecation | E353: string
A354: hypothecationBank (Hypothecation Bank) | B354: hypothecationBank | C354: Hypothecation Bank | E354: string
A355: hypothecationDocUrl (hypothecationDocUrl) | B355: hypothecationDocUrl | C355: hypothecationDocUrl | E355: string
A356: identityProofExpiry (Identity Proof Expiry) | B356: identityProofExpiry | C356: Identity Proof Expiry | E356: number
A357: identityProofNumber (Identity Proof Number) | B357: identityProofNumber | C357: Identity Proof Number | E357: number
A358: identityProofType (Identity Proof) | B358: identityProofType | C358: Identity Proof | E358: number
A359: ifsc (IFSC Code) | B359: ifsc | C359: IFSC Code | E359: string
A360: ifscCode (ifscCode) | B360: ifscCode | C360: ifscCode | E360: string
A361: instrumentType (instrumentType) | B361: instrumentType | C361: instrumentType | E361: string
A362: insurance_by (Insurance By) | B362: insurance_by | C362: Insurance By | E362: string
A363: insurance_company_name (Insurance Company Name) | B363: insurance_company_name | C363: Insurance Company Name | E363: string
A364: insurance_policy_duration_od (Policy Duration) | B364: insurance_policy_duration_od | C364: Policy Duration | E364: string
... A374: invoice_received_from (Received From) | B374: invoice_received_from | C374: Received From | E374: string
A375: isFinanced (isFinanced) | B375: isFinanced | C375: isFinanced | D375: Yes | No | E375: string
A376: isMSME (Is MSME Registered?) | B376: isMSME | C376: Is MSME Registered? | D376: Yes | No | E376: string
A377: isMultipleCars (isMultipleCars) | B377: isMultipleCars | C377: isMultipleCars | E377: string
A378: isSameVehicle (isSameVehicle) | B378: isSameVehicle | C378: isSameVehicle | E378: string
A379: leadDate (Lead Date) | B379: leadDate | C379: Lead Date | D379: Direct | Indirect | E379: string
A380: leadTime (Lead Time) | B380: leadTime | C380: Lead Time | D380: Direct | Indirect | E380: string
A381: loan_number (loan_number) | B381: loan_number | C381: loan_number | E381: string
A382: loan_payables (loan_payables) | B382: loan_payables | C382: loan_payables | E382: string
A383: loan_receivables (loan_receivables) | B383: loan_receivables | C383: loan_receivables | E383: string
A384: loanId (loanId) | B384: loanId | C384: loanId | E384: string
A385: loanTenureMonths (Requested Tenure (Months)) | B385: loanTenureMonths | C385: Requested Tenure (Months) | E385: number
A386: manufacturerDiscount (Manufacturer Discount) | B386: manufacturerDiscount | C386: Manufacturer Discount | E386: number
A387: marginMoney (Margin Money) | B387: marginMoney | C387: Margin Money | E387: number
A388: maritalStatus (Marital Status) | B388: maritalStatus | C388: Marital Status | D388: Single | Married | Divorced | Widowed | Unmarried | Undergraduate | Graduate | Postgraduate | Others | E388: number
A389: motherName (Mother's Name) | B389: motherName | C389: Mother's Name | E389: number
A390: nach_accountNumber (nach_accountNumber) | B390: nach_accountNumber | C390: nach_accountNumber | E390: string
A391: nach_image (nach_image) | B391: nach_image | C391: nach_image | E391: string
A392: nach_signedBy (nach_signedBy) | B392: nach_signedBy | C392: nach_signedBy | E392: string
A393: NEW (NEW) | B393: NEW | C393: NEW | E393: string
A394: numberOfCars (numberOfCars) | B394: numberOfCars | C394: numberOfCars | E394: number
A395: occupationType (Occupation) | B395: occupationType | C395: Occupation | E395: string
A396: officialEmail (Official Email ID) | B396: officialEmail | C396: Official Email ID | E396: string
...

Sheet DropdownData
A1: new_field_display_options | C1: role_first | D1: role_next
A2: __deliveryInitialized (__deliveryInitialized) | C2: Mapping | D2: Fallback1
A3: __dispatchInitialized (__dispatchInitialized) | C3: Fallback1 | D3: Fallback2
A4: __postfileLocked (__postfileLocked) | C4: Fallback2 | D4: Fallback3
A5: aadhaarCardDocUrl (aadhaarCardDocUrl) | C5: Fallback3 | D5: Fallback4
A6: accessoriesAmount (Accessories Amount) | C6: Fallback4 | D6: Fallback5
A7: accountNumber (Applicant Account Number) | C7: Fallback5 | D7: Fallback6
A8: accountSinceYears (Account Since (Years)) | C8: Fallback6 | D8: Fallback7
A9: accountType (Account Type) | C9: Fallback7 | D9: Fallback8
A10: addressProofDocUrl (addressProofDocUrl) | C10: Fallback8 | D10: Fallback9
A11: addressProofNumber (Address Proof Number) | C11: Fallback9 | D11: Fallback10
A12: addressProofType (Address Proof (type)) | C12: Fallback10 | D12: Fallback11
... A21: approval_breakup_insuranceFinance (approval_breakup_insuranceFinance) | C21: Fallback19 | D21: Fallback20
A22: approval_breakup_netLoanApproved (approval_breakup_netLoanApproved) | C22: Fallback20
A23: approval_disbursedDate (approval_disbursedDate)
A24: approval_loanAmountApproved (approval_loanAmountApproved)
A25: approval_loanAmountDisbursed (approval_loanAmountDisbursed)
A26: approval_processingFees (approval_processingFees)
A27: approval_roi (approval_roi)
A28: approval_status (approval_status)
A29: approval_statusHistory (approval_statusHistory)
A30: approval_tenureMonths (approval_tenureMonths)
A31: bankName (Bank Name)
A32: billDate (billDate)
A33: billNumber (billNumber)
A34: boughtInYear (Bought In (Year))
... A500: yearsInCurrentHouse (Years in Current House)

Sheet UnmappedLegacyFields
A1: Legacy field mapping status (filter legacy_map_status = UNMAPPED)
A2: legacy_file | B2: legacy_field | C2: legacy_value | D2: legacy_map_status
A3: AUTH_SIGNATORY.json | B3: ACCOUNT_NUMBER_TYPE | C3: CPV | D3: =LegacyToNewMap!O2
A4: AUTH_SIGNATORY.json | B4: ADD1 | C4: C-5 1504 CLEO COUNTY NOIDA SECTOR-121 | D4: =LegacyToNewMap!O3
A5: AUTH_SIGNATORY.json | B5: ADD2 | D5: =LegacyToNewMap!O4
A6: AUTH_SIGNATORY.json | B6: AUTH_AADHAAR_NUMBER | C6: 951419463882 | D6: =LegacyToNewMap!O5
A7: AUTH_SIGNATORY.json | B7: CITY | C7: NOIDA | D7: =LegacyToNewMap!O6
A8: AUTH_SIGNATORY.json | B8: CPV_ACCOUNT_NO | C8: 3419 | D8: =LegacyToNewMap!O7
A9: AUTH_SIGNATORY.json | B9: DATA_LOCATION_CODE | C9: 03 | D9: =LegacyToNewMap!O8
A10: AUTH_SIGNATORY.json | B10: DATE_OF_BIRTH | C10: 1987-09-09T00:00:00 | D10: =LegacyToNewMap!O9
A11: AUTH_SIGNATORY.json | B11: DESIGNATION | C11: DIRECTOR | D11: =LegacyToNewMap!O10
A12: AUTH_SIGNATORY.json | B12: FAX | D12: =LegacyToNewMap!O11
A13: AUTH_SIGNATORY.json | B13: HP_GROUP | C13: 01 | D13: =LegacyToNewMap!O12
A14: AUTH_SIGNATORY.json | B14: MOBILE | D14: =LegacyToNewMap!O13
A15: AUTH_SIGNATORY.json | B15: NAME | C15: GAURAV KHANNA | D15: =LegacyToNewMap!O14
A16: AUTH_SIGNATORY.json | B16: ORIGINAL_HP_GROUP | D16: =LegacyToNewMap!O15
A17: AUTH_SIGNATORY.json | B17: PHONE | C17: 9811542232 | D17: =LegacyToNewMap!O16
A18: AUTH_SIGNATORY.json | B18: PIN | C18: 201309 | D18: =LegacyToNewMap!O17
A19: CPV_DETAIL.json | B19: AADHAAR_NUMBER | D19: =LegacyToNewMap!O18
A20: CPV_DETAIL.json | B20: ACCOUNT_NUMBER_TYPE | C20: CPV | D20: =LegacyToNewMap!O19
A21: CPV_DETAIL.json | B21: ANNUAL_INCOME | C21: 3797080 | D21: =LegacyToNewMap!O20
A22: CPV_DETAIL.json | B22: CAR_MODEL | C22: S PRESSO LXI CNG | D22: =LegacyToNewMap!O21
A23: CPV_DETAIL.json | B23: CATEGORY | C23: PVT LTD | D23: =LegacyToNewMap!O22
A24: CPV_DETAIL.json | B24: CDB_ACCOUNT_NO | C24: 3000004231 | D24: =LegacyToNewMap!O23
A25: CPV_DETAIL.json | B25: CLS_REMARKS | D25: =LegacyToNewMap!O24
A26: CPV_DETAIL.json | B26: CLS_STATUS | D26: =LegacyToNewMap!O25
A27: CPV_DETAIL.json | B27: CPV_ACCOUNT_NO | C27: 3419 | D27: =LegacyToNewMap!O26
A28: CPV_DETAIL.json | B28: CPV_DATE | C28: 2025-01-02T00:00:00 | D28: =LegacyToNewMap!O27
A29: CPV_DETAIL.json | B29: CPV_G_OFF_STATUS | D29: =LegacyToNewMap!O28
A30: CPV_DETAIL.json | B30: CPV_G_RES_STATUS | D30: =LegacyToNewMap!O29
A31: CPV_DETAIL.json | B31: CPV_MONTH_YEAR | C31: 012025 | D31: =LegacyToNewMap!O30
A32: CPV_DETAIL.json | B32: CPV_OFF_STATUS | D32: =LegacyToNewMap!O31
A33: CPV_DETAIL.json | B33: CPV_RES_STATUS | D33: =LegacyToNewMap!O32
A34: CPV_DETAIL.json | B34: CPV_SEND_AT_TIME | D34: =LegacyToNewMap!O33
A35: CPV_DETAIL.json | B35: CPV_SEND_ON_DATE | D35: =LegacyToNewMap!O34
A36: CPV_DETAIL.json | B36: CREATED_BY_USER | D36: =LegacyToNewMap!O35
A37: CPV_DETAIL.json | B37: CREATED_ON_DATE | D37: =LegacyToNewMap!O36
A38: CPV_DETAIL.json | B38: CREATED_ON_TIME | D38: =LegacyToNewMap!O37
A39: CPV_DETAIL.json | B39: CUST_NAME_FIRST | C39: GOURAV | D39: =LegacyToNewMap!O38
A40: CPV_DETAIL.json | B40: CUST_NAME_LAST | C40: PVT LTD 2 | D40: =LegacyToNewMap!O39
A41: CPV_DETAIL.json | B41: CUST_NAME_MIDDLE | C41: LUMINARIES | D41: =LegacyToNewMap!O40
A42: CPV_DETAIL.json | B42: CUSTOMER_NAME | C42: GOURAV LUMINARIES PVT LTD 2 | D42: =LegacyToNewMap!O41
A43: CPV_DETAIL.json | B43: DATA_LOCATION_CODE | C43: 03 | D43: =LegacyToNewMap!O42
A44: CPV_DETAIL.json | B44: DATA_STATUS | C44: COMPLETE | D44: =LegacyToNewMap!O43
A45: CPV_DETAIL.json | B45: DATE_OF_BIRTH | C45: 1995-10-12T00:00:00 | D45: =LegacyToNewMap!O44
A46: CPV_DETAIL.json | B46: DEALT_BY | C46: DRG | D46: =LegacyToNewMap!O45
A47: CPV_DETAIL.json | B47: DRIVING_LICENSE | D47: =LegacyToNewMap!O46
A48: CPV_DETAIL.json | B48: E_MAIL | C48: GAURAV@GOURAVROSHNI.COM | D48: =LegacyToNewMap!O47
A49: CPV_DETAIL.json | B49: EDUCATION | C49: NA | D49: =LegacyToNewMap!O48
A50: CPV_DETAIL.json | B50: EMAIL_ADDRESS | C50: gaurav@gouravroshni.com | D50: =LegacyToNewMap!O49
A51: CPV_DETAIL.json | B51: FATHERS_NAME_FIRST | D51: =LegacyToNewMap!O50
A52: CPV_DETAIL.json | B52: FATHERS_NAME_LAST | D52: =LegacyToNewMap!O51
A53: CPV_DETAIL.json | B53: FATHERS_NAME_MIDDLE | D53: =LegacyToNewMap!O52
A54: CPV_DETAIL.json | B54: FINANCER | C54: HDFC | D54: =LegacyToNewMap!O53
A55: CPV_DETAIL.json | B55: GURANTOR_AVAILABLE | C55: N | D55: =LegacyToNewMap!O54
A56: CPV_DETAIL.json | B56: HEAD_NAME | C56: M/s. | D56: =LegacyToNewMap!O55
A57: CPV_DETAIL.json | B57: HIRE_TYPE | C57: Company | D57: =LegacyToNewMap!O56
A58: CPV_DETAIL.json | B58: HP_GROUP | C58: 01 | D58: =LegacyToNewMap!O57
A59: CPV_DETAIL.json | B59: HUSBAND_NAME | D59: =LegacyToNewMap!O58
A60: CPV_DETAIL.json | B60: ICICI_ENTRY_NUMBER | C60: BY BANK | D60: =LegacyToNewMap!O59
A61: CPV_DETAIL.json | B61: INDUSTRY_DETAIL | C61: TRADING | D61: =LegacyToNewMap!O60
A62: CPV_DETAIL.json | B62: IS_REQ_G_OFF_VERIFICATION | C62: 0 | D62: =LegacyToNewMap!O61
A63: CPV_DETAIL.json | B63: IS_REQ_G_RES_VERIFICATION | C63: 0 | D63: =LegacyToNewMap!O62
A64: CPV_DETAIL.json | B64: IS_REQ_OFF_VERIFICATION | C64: 0 | D64: =LegacyToNewMap!O63
A65: CPV_DETAIL.json | B65: IS_REQ_RES_VERIFICATION | C65: 1 | D65: =LegacyToNewMap!O64
A66: CPV_DETAIL.json | B66: LAST_EDIT_BY_USER | D66: =LegacyToNewMap!O65
A67: CPV_DETAIL.json | B67: LAST_EDIT_ON_DATE | D67: =LegacyToNewMap!O66
A68: CPV_DETAIL.json | B68: LAST_EDIT_ON_TIME | D68: =LegacyToNewMap!O67
A69: CPV_DETAIL.json | B69: LOAN_EXPECTED | C69: 525000 | D69: =LegacyToNewMap!O68
A70: CPV_DETAIL.json | B70: LOAN_TYPE | C70: Auto Loan | D70: =LegacyToNewMap!O69
A71: CPV_DETAIL.json | B71: MARITAL_STATUS | D71: =LegacyToNewMap!O70
A72: CPV_DETAIL.json | B72: MARKETING_BY | C72: 2021 | D72: =LegacyToNewMap!O71
A73: CPV_DETAIL.json | B73: MOBILE | D73: =LegacyToNewMap!O72
A74: CPV_DETAIL.json | B74: MOTHERS_MAIDEN_NAME | D74: =LegacyToNewMap!O73
A75: CPV_DETAIL.json | B75: NCCB | D75: =LegacyToNewMap!O74
A76: CPV_DETAIL.json | B76: NO_OF_DEPENDANTS | C76: 0 | D76: =LegacyToNewMap!O75
A77: CPV_DETAIL.json | B77: OFF_ADD1 | C77: PLOT NO-11/1,2 & 12/1 SITE-IV SAHIBABAD | D77: =LegacyToNewMap!O76
A78: CPV_DETAIL.json | B78: OFF_ADD2 | C78: INDUSTRIAL AREA | D78: =LegacyToNewMap!O77
A79: CPV_DETAIL.json | B79: OFF_CITY | C79: GHAZIABAD | D79: =LegacyToNewMap!O78
A80: CPV_DETAIL.json | B80: OFF_FAX | D80: =LegacyToNewMap!O79
A81: CPV_DETAIL.json | B81: OFF_NAME | C81: GOURAV LUMINARIES PVT LTD | D81: =LegacyToNewMap!O80
A82: CPV_DETAIL.json | B82: OFF_PHONE1 | C82: 9811542232 | D82: =LegacyToNewMap!O81
A83: CPV_DETAIL.json | B83: OFF_PHONE2 | D83: =LegacyToNewMap!O82
A84: CPV_DETAIL.json | B84: OFF_PHONE3 | D84: =LegacyToNewMap!O83
A85: CPV_DETAIL.json | B85: OFF_PIN | C85: 201010 | D85: =LegacyToNewMap!O84
A86: CPV_DETAIL.json | B86: ORGANISATION_TYPE | C86: ELECTRONIC | D86: =LegacyToNewMap!O85
A87: CPV_DETAIL.json | B87: ORIGINAL_HP_GROUP | D87: =LegacyToNewMap!O86
A88: CPV_DETAIL.json | B88: PAGER | D88: =LegacyToNewMap!O87
A89: CPV_DETAIL.json | B89: PAN_NUMBER | C89: AAACG3334L | D89: =LegacyToNewMap!O88
A90: CPV_DETAIL.json | B90: PASSPORT_NUMBER | D90: =LegacyToNewMap!O89
A91: CPV_DETAIL.json | B91: PERMANENT_ADDRESS | C91: C-5 1504 CLEO COUNTY NOIDA SECTOR-121 NOIDA 201309 | D91: =LegacyToNewMap!O90
A92: CPV_DETAIL.json | B92: PREVIOUS_RELATION_WITH_US | C92: NO | D92: =LegacyToNewMap!O91
A93: CPV_DETAIL.json | B93: PROFESSION_TYPE | C93: Self-Employed | D93: =LegacyToNewMap!O92
A94: CPV_DETAIL.json | B94: PURPOSE_OF_LOAN | C94: Business | D94: =LegacyToNewMap!O93
A95: CPV_DETAIL.json | B95: REF1_ADD | C95: 12-D BLOCK PREET VIHAR DELHI 110092 | D95: =LegacyToNewMap!O94
A96: CPV_DETAIL.json | B96: REF1_NAME | C96: ANIL SETHI | D96: =LegacyToNewMap!O95
A97: CPV_DETAIL.json | B97: REF1_PHONE | C97: 9811024536 | D97: =LegacyToNewMap!O96
A98: CPV_DETAIL.json | B98: REF1_RELATION | C98: FRIEND | D98: =LegacyToNewMap!O97
A99: CPV_DETAIL.json | B99: REF2_ADD | C99: B-209 S/F SURYA NAGAR GHAZIABAD 201010 | D99: =LegacyToNewMap!O98
A100: CPV_DETAIL.json | B100: REF2_NAME | C100: SANJAY NAGPAL | D100: =LegacyToNewMap!O99
...

Sheet UnmappedNewFields
A1: New field mapping status (filter mapped_count = 0)
A2: new_field_display | B2: new_field_key | C2: dropdown_values | D2: mapped_count
A3: __deliveryInitialized (__deliveryInitialized) | B3: __deliveryInitialized | D3: =COUNTIF(LegacyToNewMap!$D:$H,A3)
A4: __dispatchInitialized (__dispatchInitialized) | B4: __dispatchInitialized | D4: =COUNTIF(LegacyToNewMap!$D:$H,A4)
A5: __postfileLocked (__postfileLocked) | B5: __postfileLocked | D5: =COUNTIF(LegacyToNewMap!$D:$H,A5)
A6: aadhaarCardDocUrl (aadhaarCardDocUrl) | B6: aadhaarCardDocUrl | D6: =COUNTIF(LegacyToNewMap!$D:$H,A6)
A7: accessoriesAmount (Accessories Amount) | B7: accessoriesAmount | D7: =COUNTIF(LegacyToNewMap!$D:$H,A7)
A8: accountNumber (Applicant Account Number) | B8: accountNumber | D8: =COUNTIF(LegacyToNewMap!$D:$H,A8)
A9: accountSinceYears (Account Since (Years)) | B9: accountSinceYears | D9: =COUNTIF(LegacyToNewMap!$D:$H,A9)
A10: accountType (Account Type) | B10: accountType | D10: =COUNTIF(LegacyToNewMap!$D:$H,A10)
A11: addressProofDocUrl (addressProofDocUrl) | B11: addressProofDocUrl | D11: =COUNTIF(LegacyToNewMap!$D:$H,A11)
A12: addressProofNumber (Address Proof Number) | B12: addressProofNumber | D12: =COUNTIF(LegacyToNewMap!$D:$H,A12)
A13: addressProofType (Address Proof (type)) | B13: addressProofType | D13: =COUNTIF(LegacyToNewMap!$D:$H,A13)
A14: addressType (Address Type) | B14: addressType | D14: =COUNTIF(LegacyToNewMap!$D:$H,A14)
... A280: delivery_rcFile (delivery_rcFile) | B280: delivery_rcFile | D280: =COUNTIF(LegacyToNewMap!$D:$H,A280)
A281: dependents (Dependents) | B281: dependents | C281: owned | rented | Undergraduate | Graduate | Postgraduate | Others | D281: =COUNTIF(LegacyToNewMap!$D:$H,A281)
A282: designation (Designation) | B282: designation | D282: =COUNTIF(LegacyToNewMap!$D:$H,A282)
A283: disburseAmount (Disbursement Amount) | B283: disburseAmount | D283: =COUNTIF(LegacyToNewMap!$D:$H,A283)
A284: disbursedDate (Disbursement Date) | B284: disbursedDate | D284: =COUNTIF(LegacyToNewMap!$D:$H,A284)
A285: disbursement_date (disbursement_date) | B285: disbursement_date | D285: =COUNTIF(LegacyToNewMap!$D:$H,A285)
A286: disbursement_status (disbursement_status) | B286: disbursement_status | D286: =COUNTIF(LegacyToNewMap!$D:$H,A286)
A287: disbursement_time (disbursement_time) | B287: disbursement_time | D287: =COUNTIF(LegacyToNewMap!$D:$H,A287)
A288: disbursementDate (disbursementDate) | B288: disbursementDate | D288: =COUNTIF(LegacyToNewMap!$D:$H,A288)
A289: disbursementStatus (disbursementStatus) | B289: disbursementStatus | D289: =COUNTIF(LegacyToNewMap!$D:$H,A289)
A290: dispatch_date (dispatch_date) | B290: dispatch_date | D290: =COUNTIF(LegacyToNewMap!$D:$H,A290)
A291: dispatch_through (dispatch_through) | B291: dispatch_through | D291: =COUNTIF(LegacyToNewMap!$D:$H,A291)
A292: dispatch_time (dispatch_time) | B292: dispatch_time | D292: =COUNTIF(LegacyToNewMap!$D:$H,A292)
A293: dlDocUrl (dlDocUrl) | B293: dlDocUrl | D293: =COUNTIF(LegacyToNewMap!$D:$H,A293)
A294: dob (isCompany ? "Date of Incorporation" : "Date of Birth" [Individual: Date of Birth | Company: Date of Incorporation]) | B294: dob | C294: Male | Female | Married | D294: =COUNTIF(LegacyToNewMap!$D:$H,A294)
A295: docs_prepared_by (docs_prepared_by) | B295: docs_prepared_by | D295: =COUNTIF(LegacyToNewMap!$D:$H,A295)
A296: docsPreparedBy (Docs Prepared By) | B296: docsPreparedBy | D296: =COUNTIF(LegacyToNewMap!$D:$H,A296)
A297: ecs_accountNumber (ecs_accountNumber) | B297: ecs_accountNumber | D297: =COUNTIF(LegacyToNewMap!$D:$H,A297)
A298: ecs_amount (ecs_amount) | B298: ecs_amount | D298: =COUNTIF(LegacyToNewMap!$D:$H,A298)
A299: ecs_bankName (ecs_bankName) | B299: ecs_bankName | D299: =COUNTIF(LegacyToNewMap!$D:$H,A299)
A300: ecs_date (ecs_date) | B300: ecs_date | D300: =COUNTIF(LegacyToNewMap!$D:$H,A300)
A301: ecs_favouring (ecs_favouring) | B301: ecs_favouring | D301: =COUNTIF(LegacyToNewMap!$D:$H,A301)
A302: ecs_image (ecs_image) | B302: ecs_image | D302: =COUNTIF(LegacyToNewMap!$D:$H,A302)
A303: ecs_micrCode (ecs_micrCode) | B303: ecs_micrCode | D303: =COUNTIF(LegacyToNewMap!$D:$H,A303)
A304: ecs_signedBy (ecs_signedBy) | B304: ecs_signedBy | D304: =COUNTIF(LegacyToNewMap!$D:$H,A304)
A305: ecs_tag (ecs_tag) | B305: ecs_tag | D305: =COUNTIF(LegacyToNewMap!$D:$H,A305)
A306: education (Education) | B306: education | C306: Undergraduate | Graduate | Postgraduate | Others | D306: =COUNTIF(LegacyToNewMap!$D:$H,A306)
A307: email (Email) | B307: email | D307: =COUNTIF(LegacyToNewMap!$D:$H,A307)
A308: employmentAddress (Company Address) | B308: employmentAddress | D308: =COUNTIF(LegacyToNewMap!$D:$H,A308)
A309: employmentCity (City) | B309: employmentCity | D309: =COUNTIF(LegacyToNewMap!$D:$H,A309)
A310: employmentPhone (Phone Number) | B310: employmentPhone | D310: =COUNTIF(LegacyToNewMap!$D:$H,A310)
A311: employmentPincode (Pincode) | B311: employmentPincode | D311: =COUNTIF(LegacyToNewMap!$D:$H,A311)
A312: experienceCurrent (companyMode ? "Business Since / Current Vintage (Years)" : "Current Exp (Years)") | B312: experienceCurrent | D312: =COUNTIF(LegacyToNewMap!$D:$H,A312)
A313: exShowroomPrice (Ex-Showroom Price) | B313: exShowroomPrice | D313: =COUNTIF(LegacyToNewMap!$D:$H,A313)
A314: financeExpectation (Expected Funding) | B314: financeExpectation | D314: =COUNTIF(LegacyToNewMap!$D:$H,A314)
A315: gender (Gender) | B315: gender | C315: Male | Female | Married | Unmarried | Undergraduate | D315: =COUNTIF(LegacyToNewMap!$D:$H,A315)
A316: gstDocUrl (gstDocUrl) | B316: gstDocUrl | D316: =COUNTIF(LegacyToNewMap!$D:$H,A316)
A317: gstNumber (GST Number) | B317: gstNumber | C317: Single | Married | Divorced | Widowed | D317: =COUNTIF(LegacyToNewMap!$D:$H,A317)
A318: gu_aadhaar (Aadhaar) | B318: gu_aadhaar | D318: =COUNTIF(LegacyToNewMap!$D:$H,A318)
A319: gu_aadhaarCardDocUrl (gu_aadhaarCardDocUrl) | B319: gu_aadhaarCardDocUrl | D319: =COUNTIF(LegacyToNewMap!$D:$H,A319)
A320: gu_address (Address) | B320: gu_address | D320: =COUNTIF(LegacyToNewMap!$D:$H,A320)
A321: gu_addressProofDocUrl (gu_addressProofDocUrl) | B321: gu_addressProofDocUrl | D321: =COUNTIF(LegacyToNewMap!$D:$H,A321)
A322: gu_businessNature (Nature of Business) | B322: gu_businessNature | D322: =COUNTIF(LegacyToNewMap!$D:$H,A322)
A323: gu_city (City) | B323: gu_city | D323: =COUNTIF(LegacyToNewMap!$D:$H,A323)
A324: gu_companyAddress (Company Address) | B324: gu_companyAddress | D324: =COUNTIF(LegacyToNewMap!$D:$H,A324)
A325: gu_companyCity (City) | B325: gu_companyCity | D325: =COUNTIF(LegacyToNewMap!$D:$H,A325)
A326: gu_companyName (Company Name) | B326: gu_companyName | D326: =COUNTIF(LegacyToNewMap!$D:$H,A326)
A327: gu_companyPhone (Phone No) | B327: gu_companyPhone | D327: =COUNTIF(LegacyToNewMap!$D:$H,A327)
A328: gu_companyPincode (Pin Code) | B328: gu_companyPincode | D328: =COUNTIF(LegacyToNewMap!$D:$H,A328)
A329: gu_companyType (Type of Company) | B329: gu_companyType | D329: =COUNTIF(LegacyToNewMap!$D:$H,A329)
... A352: hasGuarantor (Is Guarantor Applicable) | B352: hasGuarantor | D352: =COUNTIF(LegacyToNewMap!$D:$H,A352)
A353: houseType (House Type) | B353: houseType | C353: owned | rented | D353: =COUNTIF(LegacyToNewMap!$D:$H,A353)
A354: hypothecation (Hypothecation) | B354: hypothecation | D354: =COUNTIF(LegacyToNewMap!$D:$H,A354)
A355: hypothecationBank (Hypothecation Bank) | B355: hypothecationBank | D355: =COUNTIF(LegacyToNewMap!$D:$H,A355)
A356: hypothecationDocUrl (hypothecationDocUrl) | B356: hypothecationDocUrl | D356: =COUNTIF(LegacyToNewMap!$D:$H,A356)
A357: identityProofExpiry (Identity Proof Expiry) | B357: identityProofExpiry | D357: =COUNTIF(LegacyToNewMap!$D:$H,A357)
A358: identityProofNumber (Identity Proof Number) | B358: identityProofNumber | D358: =COUNTIF(LegacyToNewMap!$D:$H,A358)
A359: identityProofType (Identity Proof) | B359: identityProofType | D359: =COUNTIF(LegacyToNewMap!$D:$H,A359)
A360: ifsc (IFSC Code) | B360: ifsc | D360: =COUNTIF(LegacyToNewMap!$D:$H,A360)
A361: ifscCode (ifscCode) | B361: ifscCode | D361: =COUNTIF(LegacyToNewMap!$D:$H,A361)
A362: instrumentType (instrumentType) | B362: instrumentType | D362: =COUNTIF(LegacyToNewMap!$D:$H,A362)
A363: insurance_by (Insurance By) | B363: insurance_by | D363: =COUNTIF(LegacyToNewMap!$D:$H,A363)
A364: insurance_company_name (Insurance Company Name) | B364: insurance_company_name | D364: =COUNTIF(LegacyToNewMap!$D:$H,A364)
A365: insurance_policy_duration_od (Policy Duration) | B365: insurance_policy_duration_od | D365: =COUNTIF(LegacyToNewMap!$D:$H,A365)
... A375: invoice_received_from (Received From) | B375: invoice_received_from | D375: =COUNTIF(LegacyToNewMap!$D:$H,A375)
A376: isFinanced (isFinanced) | B376: isFinanced | C376: Yes | No | D376: =COUNTIF(LegacyToNewMap!$D:$H,A376)
A377: isMSME (Is MSME Registered?) | B377: isMSME | C377: Yes | No | D377: =COUNTIF(LegacyToNewMap!$D:$H,A377)
A378: isMultipleCars (isMultipleCars) | B378: isMultipleCars | D378: =COUNTIF(LegacyToNewMap!$D:$H,A378)
A379: isSameVehicle (isSameVehicle) | B379: isSameVehicle | D379: =COUNTIF(LegacyToNewMap!$D:$H,A379)
A380: leadDate (Lead Date) | B380: leadDate | C380: Direct | Indirect | D380: =COUNTIF(LegacyToNewMap!$D:$H,A380)
A381: leadTime (Lead Time) | B381: leadTime | C381: Direct | Indirect | D381: =COUNTIF(LegacyToNewMap!$D:$H,A381)
A382: loan_number (loan_number) | B382: loan_number | D382: =COUNTIF(LegacyToNewMap!$D:$H,A382)
A383: loan_payables (loan_payables) | B383: loan_payables | D383: =COUNTIF(LegacyToNewMap!$D:$H,A383)
A384: loan_receivables (loan_receivables) | B384: loan_receivables | D384: =COUNTIF(LegacyToNewMap!$D:$H,A384)
A385: loanId (loanId) | B385: loanId | D385: =COUNTIF(LegacyToNewMap!$D:$H,A385)
A386: loanTenureMonths (Requested Tenure (Months)) | B386: loanTenureMonths | D386: =COUNTIF(LegacyToNewMap!$D:$H,A386)
A387: manufacturerDiscount (Manufacturer Discount) | B387: manufacturerDiscount | D387: =COUNTIF(LegacyToNewMap!$D:$H,A387)
A388: marginMoney (Margin Money) | B388: marginMoney | D388: =COUNTIF(LegacyToNewMap!$D:$H,A388)
A389: maritalStatus (Marital Status) | B389: maritalStatus | C389: Single | Married | Divorced | Widowed | Unmarried | Undergraduate | Graduate | Postgraduate | Others | D389: =COUNTIF(LegacyToNewMap!$D:$H,A389)
A390: motherName (Mother's Name) | B390: motherName | D390: =COUNTIF(LegacyToNewMap!$D:$H,A390)
A391: nach_accountNumber (nach_accountNumber) | B391: nach_accountNumber | D391: =COUNTIF(LegacyToNewMap!$D:$H,A391)
A392: nach_image (nach_image) | B392: nach_image | D392: =COUNTIF(LegacyToNewMap!$D:$H,A392)
A393: nach_signedBy (nach_signedBy) | B393: nach_signedBy | D393: =COUNTIF(LegacyToNewMap!$D:$H,A393)
A394: NEW (NEW) | B394: NEW | D394: =COUNTIF(LegacyToNewMap!$D:$H,A394)
A395: numberOfCars (numberOfCars) | B395: numberOfCars | D395: =COUNTIF(LegacyToNewMap!$D:$H,A395)
A396: occupationType (Occupation) | B396: occupationType | D396: =COUNTIF(LegacyToNewMap!$D:$H,A396)
...

Sheet Instructions
A1: Reverse Mapping Instructions
A3: 1) Map each legacy field to one or more new fields via new_field_1..new_field_5.
A4: 2) Use role_1..role_5 as Mapping/Fallback1/Fallback2 as needed.
A5: 3) Same legacy field can map to multiple new fields in the same row.
A6: 4) Add normalization rules in comments_normalization (for dropdown conversion etc.).
A7: 5) In UnmappedLegacyFields sheet, filter legacy_map_status = UNMAPPED.
A8: 6) In UnmappedNewFields sheet, filter mapped_count = 0.
A9: 7) No dynamic Excel-only functions are used; workbook is compatibility-safe.
