Workbook
Name NewFieldOptionsDisplay: DropdownData!$A$2:$A$327
Name RoleFirst: DropdownData!$C$2:$C$22
Name RoleNext: DropdownData!$D$2:$D$21

Sheet LegacyToNewMap
A1: legacy_file | B1: legacy_field | C1: legacy_value | D1: new_field_select | E1: mapping_role | F1: comments_normalization | G1: new_field_dropdown_values | H1: new_field_key
A2: AUTH_SIGNATORY.json | B2: ACCOUNT_NUMBER_TYPE | C2: CPV | G2: =IFERROR(_xludf.XLOOKUP($D2,NewFieldOptions!$A:$A,NewFieldOptions!$D:$D,""),"") | H2: =IFERROR(_xludf.XLOOKUP($D2,NewFieldOptions!$A:$A,NewFieldOptions!$B:$B,""),"")
A3: AUTH_SIGNATORY.json | B3: ADD1 | C3: C-5 1504 CLEO COUNTY NOIDA SECTOR-121 | G3: =IFERROR(_xludf.XLOOKUP($D3,NewFieldOptions!$A:$A,NewFieldOptions!$D:$D,""),"") | H3: =IFERROR(_xludf.XLOOKUP($D3,NewFieldOptions!$A:$A,NewFieldOptions!$B:$B,""),"")
A4: AUTH_SIGNATORY.json | B4: ADD2 | G4: =IFERROR(_xludf.XLOOKUP($D4,NewFieldOptions!$A:$A,NewFieldOptions!$D:$D,""),"") | H4: =IFERROR(_xludf.XLOOKUP($D4,NewFieldOptions!$A:$A,NewFieldOptions!$B:$B,""),"")
A5: AUTH_SIGNATORY.json | B5: AUTH_AADHAAR_NUMBER | C5: 951419463882 | G5: =IFERROR(_xludf.XLOOKUP($D5,NewFieldOptions!$A:$A,NewFieldOptions!$D:$D,""),"") | H5: =IFERROR(_xludf.XLOOKUP($D5,NewFieldOptions!$A:$A,NewFieldOptions!$B:$B,""),"")
A6: AUTH_SIGNATORY.json | B6: CITY | C6: NOIDA | G6: =IFERROR(_xludf.XLOOKUP($D6,NewFieldOptions!$A:$A,NewFieldOptions!$D:$D,""),"") | H6: =IFERROR(_xludf.XLOOKUP($D6,NewFieldOptions!$A:$A,NewFieldOptions!$B:$B,""),"")
A7: AUTH_SIGNATORY.json | B7: CPV_ACCOUNT_NO | C7: 3419 | G7: =IFERROR(_xludf.XLOOKUP($D7,NewFieldOptions!$A:$A,NewFieldOptions!$D:$D,""),"") | H7: =IFERROR(_xludf.XLOOKUP($D7,NewFieldOptions!$A:$A,NewFieldOptions!$B:$B,""),"")
A8: AUTH_SIGNATORY.json | B8: DATA_LOCATION_CODE | C8: 03 | G8: =IFERROR(_xludf.XLOOKUP($D8,NewFieldOptions!$A:$A,NewFieldOptions!$D:$D,""),"") | H8: =IFERROR(_xludf.XLOOKUP($D8,NewFieldOptions!$A:$A,NewFieldOptions!$B:$B,""),"")
A9: AUTH_SIGNATORY.json | B9: DATE_OF_BIRTH | C9: 1987-09-09T00:00:00 | G9: =IFERROR(_xludf.XLOOKUP($D9,NewFieldOptions!$A:$A,NewFieldOptions!$D:$D,""),"") | H9: =IFERROR(_xludf.XLOOKUP($D9,NewFieldOptions!$A:$A,NewFieldOptions!$B:$B,""),"")
A10: AUTH_SIGNATORY.json | B10: DESIGNATION | C10: DIRECTOR | G10: =IFERROR(_xludf.XLOOKUP($D10,NewFieldOptions!$A:$A,NewFieldOptions!$D:$D,""),"") | H10: =IFERROR(_xludf.XLOOKUP($D10,NewFieldOptions!$A:$A,NewFieldOptions!$B:$B,""),"")
A11: AUTH_SIGNATORY.json | B11: FAX | G11: =IFERROR(_xludf.XLOOKUP($D11,NewFieldOptions!$A:$A,NewFieldOptions!$D:$D,""),"") | H11: =IFERROR(_xludf.XLOOKUP($D11,NewFieldOptions!$A:$A,NewFieldOptions!$B:$B,""),"")
A12: AUTH_SIGNATORY.json | B12: HP_GROUP | C12: 01 | G12: =IFERROR(_xludf.XLOOKUP($D12,NewFieldOptions!$A:$A,NewFieldOptions!$D:$D,""),"") | H12: =IFERROR(_xludf.XLOOKUP($D12,NewFieldOptions!$A:$A,NewFieldOptions!$B:$B,""),"")
A13: AUTH_SIGNATORY.json | B13: MOBILE | G13: =IFERROR(_xludf.XLOOKUP($D13,NewFieldOptions!$A:$A,NewFieldOptions!$D:$D,""),"") | H13: =IFERROR(_xludf.XLOOKUP($D13,NewFieldOptions!$A:$A,NewFieldOptions!$B:$B,""),"")
A14: AUTH_SIGNATORY.json | B14: NAME | C14: GAURAV KHANNA | G14: =IFERROR(_xludf.XLOOKUP($D14,NewFieldOptions!$A:$A,NewFieldOptions!$D:$D,""),"") | H14: =IFERROR(_xludf.XLOOKUP($D14,NewFieldOptions!$A:$A,NewFieldOptions!$B:$B,""),"")
A15: AUTH_SIGNATORY.json | B15: ORIGINAL_HP_GROUP | G15: =IFERROR(_xludf.XLOOKUP($D15,NewFieldOptions!$A:$A,NewFieldOptions!$D:$D,""),"") | H15: =IFERROR(_xludf.XLOOKUP($D15,NewFieldOptions!$A:$A,NewFieldOptions!$B:$B,""),"")
A16: AUTH_SIGNATORY.json | B16: PHONE | C16: 9811542232 | G16: =IFERROR(_xludf.XLOOKUP($D16,NewFieldOptions!$A:$A,NewFieldOptions!$D:$D,""),"") | H16: =IFERROR(_xludf.XLOOKUP($D16,NewFieldOptions!$A:$A,NewFieldOptions!$B:$B,""),"")
A17: AUTH_SIGNATORY.json | B17: PIN | C17: 201309 | G17: =IFERROR(_xludf.XLOOKUP($D17,NewFieldOptions!$A:$A,NewFieldOptions!$D:$D,""),"") | H17: =IFERROR(_xludf.XLOOKUP($D17,NewFieldOptions!$A:$A,NewFieldOptions!$B:$B,""),"")
A18: CPV_DETAIL.json | B18: AADHAAR_NUMBER | D18: aadhaarCardDocUrl (aadhaarCardDocUrl) | E18: Mapping | G18: =IFERROR(_xludf.XLOOKUP($D18,NewFieldOptions!$A:$A,NewFieldOptions!$D:$D,""),"") | H18: =IFERROR(_xludf.XLOOKUP($D18,NewFieldOptions!$A:$A,NewFieldOptions!$B:$B,""),"")
A19: CPV_DETAIL.json | B19: ACCOUNT_NUMBER_TYPE | C19: CPV | G19: =IFERROR(_xludf.XLOOKUP($D19,NewFieldOptions!$A:$A,NewFieldOptions!$D:$D,""),"") | H19: =IFERROR(_xludf.XLOOKUP($D19,NewFieldOptions!$A:$A,NewFieldOptions!$B:$B,""),"")
A20: CPV_DETAIL.json | B20: ANNUAL_INCOME | C20: 3797080 | G20: =IFERROR(_xludf.XLOOKUP($D20,NewFieldOptions!$A:$A,NewFieldOptions!$D:$D,""),"") | H20: =IFERROR(_xludf.XLOOKUP($D20,NewFieldOptions!$A:$A,NewFieldOptions!$B:$B,""),"")
A21: CPV_DETAIL.json | B21: CAR_MODEL | C21: S PRESSO LXI CNG | G21: =IFERROR(_xludf.XLOOKUP($D21,NewFieldOptions!$A:$A,NewFieldOptions!$D:$D,""),"") | H21: =IFERROR(_xludf.XLOOKUP($D21,NewFieldOptions!$A:$A,NewFieldOptions!$B:$B,""),"")
A22: CPV_DETAIL.json | B22: CATEGORY | C22: PVT LTD | G22: =IFERROR(_xludf.XLOOKUP($D22,NewFieldOptions!$A:$A,NewFieldOptions!$D:$D,""),"") | H22: =IFERROR(_xludf.XLOOKUP($D22,NewFieldOptions!$A:$A,NewFieldOptions!$B:$B,""),"")
A23: CPV_DETAIL.json | B23: CDB_ACCOUNT_NO | C23: 3000004231 | G23: =IFERROR(_xludf.XLOOKUP($D23,NewFieldOptions!$A:$A,NewFieldOptions!$D:$D,""),"") | H23: =IFERROR(_xludf.XLOOKUP($D23,NewFieldOptions!$A:$A,NewFieldOptions!$B:$B,""),"")
A24: CPV_DETAIL.json | B24: CLS_REMARKS | G24: =IFERROR(_xludf.XLOOKUP($D24,NewFieldOptions!$A:$A,NewFieldOptions!$D:$D,""),"") | H24: =IFERROR(_xludf.XLOOKUP($D24,NewFieldOptions!$A:$A,NewFieldOptions!$B:$B,""),"")
A25: CPV_DETAIL.json | B25: CLS_STATUS | G25: =IFERROR(_xludf.XLOOKUP($D25,NewFieldOptions!$A:$A,NewFieldOptions!$D:$D,""),"") | H25: =IFERROR(_xludf.XLOOKUP($D25,NewFieldOptions!$A:$A,NewFieldOptions!$B:$B,""),"")
A26: CPV_DETAIL.json | B26: CPV_ACCOUNT_NO | C26: 3419 | G26: =IFERROR(_xludf.XLOOKUP($D26,NewFieldOptions!$A:$A,NewFieldOptions!$D:$D,""),"") | H26: =IFERROR(_xludf.XLOOKUP($D26,NewFieldOptions!$A:$A,NewFieldOptions!$B:$B,""),"")
A27: CPV_DETAIL.json | B27: CPV_DATE | C27: 2025-01-02T00:00:00 | G27: =IFERROR(_xludf.XLOOKUP($D27,NewFieldOptions!$A:$A,NewFieldOptions!$D:$D,""),"") | H27: =IFERROR(_xludf.XLOOKUP($D27,NewFieldOptions!$A:$A,NewFieldOptions!$B:$B,""),"")
A28: CPV_DETAIL.json | B28: CPV_G_OFF_STATUS | G28: =IFERROR(_xludf.XLOOKUP($D28,NewFieldOptions!$A:$A,NewFieldOptions!$D:$D,""),"") | H28: =IFERROR(_xludf.XLOOKUP($D28,NewFieldOptions!$A:$A,NewFieldOptions!$B:$B,""),"")
A29: CPV_DETAIL.json | B29: CPV_G_RES_STATUS | G29: =IFERROR(_xludf.XLOOKUP($D29,NewFieldOptions!$A:$A,NewFieldOptions!$D:$D,""),"") | H29: =IFERROR(_xludf.XLOOKUP($D29,NewFieldOptions!$A:$A,NewFieldOptions!$B:$B,""),"")
A30: CPV_DETAIL.json | B30: CPV_MONTH_YEAR | C30: 012025 | G30: =IFERROR(_xludf.XLOOKUP($D30,NewFieldOptions!$A:$A,NewFieldOptions!$D:$D,""),"") | H30: =IFERROR(_xludf.XLOOKUP($D30,NewFieldOptions!$A:$A,NewFieldOptions!$B:$B,""),"")
A31: CPV_DETAIL.json | B31: CPV_OFF_STATUS | G31: =IFERROR(_xludf.XLOOKUP($D31,NewFieldOptions!$A:$A,NewFieldOptions!$D:$D,""),"") | H31: =IFERROR(_xludf.XLOOKUP($D31,NewFieldOptions!$A:$A,NewFieldOptions!$B:$B,""),"")
A32: CPV_DETAIL.json | B32: CPV_RES_STATUS | G32: =IFERROR(_xludf.XLOOKUP($D32,NewFieldOptions!$A:$A,NewFieldOptions!$D:$D,""),"") | H32: =IFERROR(_xludf.XLOOKUP($D32,NewFieldOptions!$A:$A,NewFieldOptions!$B:$B,""),"")
A33: CPV_DETAIL.json | B33: CPV_SEND_AT_TIME | G33: =IFERROR(_xludf.XLOOKUP($D33,NewFieldOptions!$A:$A,NewFieldOptions!$D:$D,""),"") | H33: =IFERROR(_xludf.XLOOKUP($D33,NewFieldOptions!$A:$A,NewFieldOptions!$B:$B,""),"")
A34: CPV_DETAIL.json | B34: CPV_SEND_ON_DATE | G34: =IFERROR(_xludf.XLOOKUP($D34,NewFieldOptions!$A:$A,NewFieldOptions!$D:$D,""),"") | H34: =IFERROR(_xludf.XLOOKUP($D34,NewFieldOptions!$A:$A,NewFieldOptions!$B:$B,""),"")
A35: CPV_DETAIL.json | B35: CREATED_BY_USER | G35: =IFERROR(_xludf.XLOOKUP($D35,NewFieldOptions!$A:$A,NewFieldOptions!$D:$D,""),"") | H35: =IFERROR(_xludf.XLOOKUP($D35,NewFieldOptions!$A:$A,NewFieldOptions!$B:$B,""),"")
A36: CPV_DETAIL.json | B36: CREATED_ON_DATE | G36: =IFERROR(_xludf.XLOOKUP($D36,NewFieldOptions!$A:$A,NewFieldOptions!$D:$D,""),"") | H36: =IFERROR(_xludf.XLOOKUP($D36,NewFieldOptions!$A:$A,NewFieldOptions!$B:$B,""),"")
A37: CPV_DETAIL.json | B37: CREATED_ON_TIME | G37: =IFERROR(_xludf.XLOOKUP($D37,NewFieldOptions!$A:$A,NewFieldOptions!$D:$D,""),"") | H37: =IFERROR(_xludf.XLOOKUP($D37,NewFieldOptions!$A:$A,NewFieldOptions!$B:$B,""),"")
A38: CPV_DETAIL.json | B38: CUST_NAME_FIRST | C38: GOURAV | G38: =IFERROR(_xludf.XLOOKUP($D38,NewFieldOptions!$A:$A,NewFieldOptions!$D:$D,""),"") | H38: =IFERROR(_xludf.XLOOKUP($D38,NewFieldOptions!$A:$A,NewFieldOptions!$B:$B,""),"")
A39: CPV_DETAIL.json | B39: CUST_NAME_LAST | C39: PVT LTD 2 | G39: =IFERROR(_xludf.XLOOKUP($D39,NewFieldOptions!$A:$A,NewFieldOptions!$D:$D,""),"") | H39: =IFERROR(_xludf.XLOOKUP($D39,NewFieldOptions!$A:$A,NewFieldOptions!$B:$B,""),"")
A40: CPV_DETAIL.json | B40: CUST_NAME_MIDDLE | C40: LUMINARIES | G40: =IFERROR(_xludf.XLOOKUP($D40,NewFieldOptions!$A:$A,NewFieldOptions!$D:$D,""),"") | H40: =IFERROR(_xludf.XLOOKUP($D40,NewFieldOptions!$A:$A,NewFieldOptions!$B:$B,""),"")
A41: CPV_DETAIL.json | B41: CUSTOMER_NAME | C41: GOURAV LUMINARIES PVT LTD 2 | G41: =IFERROR(_xludf.XLOOKUP($D41,NewFieldOptions!$A:$A,NewFieldOptions!$D:$D,""),"") | H41: =IFERROR(_xludf.XLOOKUP($D41,NewFieldOptions!$A:$A,NewFieldOptions!$B:$B,""),"")
A42: CPV_DETAIL.json | B42: DATA_LOCATION_CODE | C42: 03 | G42: =IFERROR(_xludf.XLOOKUP($D42,NewFieldOptions!$A:$A,NewFieldOptions!$D:$D,""),"") | H42: =IFERROR(_xludf.XLOOKUP($D42,NewFieldOptions!$A:$A,NewFieldOptions!$B:$B,""),"")
A43: CPV_DETAIL.json | B43: DATA_STATUS | C43: COMPLETE | G43: =IFERROR(_xludf.XLOOKUP($D43,NewFieldOptions!$A:$A,NewFieldOptions!$D:$D,""),"") | H43: =IFERROR(_xludf.XLOOKUP($D43,NewFieldOptions!$A:$A,NewFieldOptions!$B:$B,""),"")
A44: CPV_DETAIL.json | B44: DATE_OF_BIRTH | C44: 1995-10-12T00:00:00 | G44: =IFERROR(_xludf.XLOOKUP($D44,NewFieldOptions!$A:$A,NewFieldOptions!$D:$D,""),"") | H44: =IFERROR(_xludf.XLOOKUP($D44,NewFieldOptions!$A:$A,NewFieldOptions!$B:$B,""),"")
A45: CPV_DETAIL.json | B45: DEALT_BY | C45: DRG | G45: =IFERROR(_xludf.XLOOKUP($D45,NewFieldOptions!$A:$A,NewFieldOptions!$D:$D,""),"") | H45: =IFERROR(_xludf.XLOOKUP($D45,NewFieldOptions!$A:$A,NewFieldOptions!$B:$B,""),"")
A46: CPV_DETAIL.json | B46: DRIVING_LICENSE | G46: =IFERROR(_xludf.XLOOKUP($D46,NewFieldOptions!$A:$A,NewFieldOptions!$D:$D,""),"") | H46: =IFERROR(_xludf.XLOOKUP($D46,NewFieldOptions!$A:$A,NewFieldOptions!$B:$B,""),"")
A47: CPV_DETAIL.json | B47: E_MAIL | C47: GAURAV@GOURAVROSHNI.COM | G47: =IFERROR(_xludf.XLOOKUP($D47,NewFieldOptions!$A:$A,NewFieldOptions!$D:$D,""),"") | H47: =IFERROR(_xludf.XLOOKUP($D47,NewFieldOptions!$A:$A,NewFieldOptions!$B:$B,""),"")
A48: CPV_DETAIL.json | B48: EDUCATION | C48: NA | G48: =IFERROR(_xludf.XLOOKUP($D48,NewFieldOptions!$A:$A,NewFieldOptions!$D:$D,""),"") | H48: =IFERROR(_xludf.XLOOKUP($D48,NewFieldOptions!$A:$A,NewFieldOptions!$B:$B,""),"")
A49: CPV_DETAIL.json | B49: EMAIL_ADDRESS | C49: gaurav@gouravroshni.com | G49: =IFERROR(_xludf.XLOOKUP($D49,NewFieldOptions!$A:$A,NewFieldOptions!$D:$D,""),"") | H49: =IFERROR(_xludf.XLOOKUP($D49,NewFieldOptions!$A:$A,NewFieldOptions!$B:$B,""),"")
A50: CPV_DETAIL.json | B50: FATHERS_NAME_FIRST | G50: =IFERROR(_xludf.XLOOKUP($D50,NewFieldOptions!$A:$A,NewFieldOptions!$D:$D,""),"") | H50: =IFERROR(_xludf.XLOOKUP($D50,NewFieldOptions!$A:$A,NewFieldOptions!$B:$B,""),"")
A51: CPV_DETAIL.json | B51: FATHERS_NAME_LAST | G51: =IFERROR(_xludf.XLOOKUP($D51,NewFieldOptions!$A:$A,NewFieldOptions!$D:$D,""),"") | H51: =IFERROR(_xludf.XLOOKUP($D51,NewFieldOptions!$A:$A,NewFieldOptions!$B:$B,""),"")
A52: CPV_DETAIL.json | B52: FATHERS_NAME_MIDDLE | G52: =IFERROR(_xludf.XLOOKUP($D52,NewFieldOptions!$A:$A,NewFieldOptions!$D:$D,""),"") | H52: =IFERROR(_xludf.XLOOKUP($D52,NewFieldOptions!$A:$A,NewFieldOptions!$B:$B,""),"")
A53: CPV_DETAIL.json | B53: FINANCER | C53: HDFC | G53: =IFERROR(_xludf.XLOOKUP($D53,NewFieldOptions!$A:$A,NewFieldOptions!$D:$D,""),"") | H53: =IFERROR(_xludf.XLOOKUP($D53,NewFieldOptions!$A:$A,NewFieldOptions!$B:$B,""),"")
A54: CPV_DETAIL.json | B54: GURANTOR_AVAILABLE | C54: N | G54: =IFERROR(_xludf.XLOOKUP($D54,NewFieldOptions!$A:$A,NewFieldOptions!$D:$D,""),"") | H54: =IFERROR(_xludf.XLOOKUP($D54,NewFieldOptions!$A:$A,NewFieldOptions!$B:$B,""),"")
A55: CPV_DETAIL.json | B55: HEAD_NAME | C55: M/s. | G55: =IFERROR(_xludf.XLOOKUP($D55,NewFieldOptions!$A:$A,NewFieldOptions!$D:$D,""),"") | H55: =IFERROR(_xludf.XLOOKUP($D55,NewFieldOptions!$A:$A,NewFieldOptions!$B:$B,""),"")
A56: CPV_DETAIL.json | B56: HIRE_TYPE | C56: Company | G56: =IFERROR(_xludf.XLOOKUP($D56,NewFieldOptions!$A:$A,NewFieldOptions!$D:$D,""),"") | H56: =IFERROR(_xludf.XLOOKUP($D56,NewFieldOptions!$A:$A,NewFieldOptions!$B:$B,""),"")
A57: CPV_DETAIL.json | B57: HP_GROUP | C57: 01 | G57: =IFERROR(_xludf.XLOOKUP($D57,NewFieldOptions!$A:$A,NewFieldOptions!$D:$D,""),"") | H57: =IFERROR(_xludf.XLOOKUP($D57,NewFieldOptions!$A:$A,NewFieldOptions!$B:$B,""),"")
A58: CPV_DETAIL.json | B58: HUSBAND_NAME | G58: =IFERROR(_xludf.XLOOKUP($D58,NewFieldOptions!$A:$A,NewFieldOptions!$D:$D,""),"") | H58: =IFERROR(_xludf.XLOOKUP($D58,NewFieldOptions!$A:$A,NewFieldOptions!$B:$B,""),"")
A59: CPV_DETAIL.json | B59: ICICI_ENTRY_NUMBER | C59: BY BANK | G59: =IFERROR(_xludf.XLOOKUP($D59,NewFieldOptions!$A:$A,NewFieldOptions!$D:$D,""),"") | H59: =IFERROR(_xludf.XLOOKUP($D59,NewFieldOptions!$A:$A,NewFieldOptions!$B:$B,""),"")
A60: CPV_DETAIL.json | B60: INDUSTRY_DETAIL | C60: TRADING | G60: =IFERROR(_xludf.XLOOKUP($D60,NewFieldOptions!$A:$A,NewFieldOptions!$D:$D,""),"") | H60: =IFERROR(_xludf.XLOOKUP($D60,NewFieldOptions!$A:$A,NewFieldOptions!$B:$B,""),"")
A61: CPV_DETAIL.json | B61: IS_REQ_G_OFF_VERIFICATION | C61: 0 | G61: =IFERROR(_xludf.XLOOKUP($D61,NewFieldOptions!$A:$A,NewFieldOptions!$D:$D,""),"") | H61: =IFERROR(_xludf.XLOOKUP($D61,NewFieldOptions!$A:$A,NewFieldOptions!$B:$B,""),"")
A62: CPV_DETAIL.json | B62: IS_REQ_G_RES_VERIFICATION | C62: 0 | G62: =IFERROR(_xludf.XLOOKUP($D62,NewFieldOptions!$A:$A,NewFieldOptions!$D:$D,""),"") | H62: =IFERROR(_xludf.XLOOKUP($D62,NewFieldOptions!$A:$A,NewFieldOptions!$B:$B,""),"")
A63: CPV_DETAIL.json | B63: IS_REQ_OFF_VERIFICATION | C63: 0 | G63: =IFERROR(_xludf.XLOOKUP($D63,NewFieldOptions!$A:$A,NewFieldOptions!$D:$D,""),"") | H63: =IFERROR(_xludf.XLOOKUP($D63,NewFieldOptions!$A:$A,NewFieldOptions!$B:$B,""),"")
A64: CPV_DETAIL.json | B64: IS_REQ_RES_VERIFICATION | C64: 1 | G64: =IFERROR(_xludf.XLOOKUP($D64,NewFieldOptions!$A:$A,NewFieldOptions!$D:$D,""),"") | H64: =IFERROR(_xludf.XLOOKUP($D64,NewFieldOptions!$A:$A,NewFieldOptions!$B:$B,""),"")
A65: CPV_DETAIL.json | B65: LAST_EDIT_BY_USER | G65: =IFERROR(_xludf.XLOOKUP($D65,NewFieldOptions!$A:$A,NewFieldOptions!$D:$D,""),"") | H65: =IFERROR(_xludf.XLOOKUP($D65,NewFieldOptions!$A:$A,NewFieldOptions!$B:$B,""),"")
A66: CPV_DETAIL.json | B66: LAST_EDIT_ON_DATE | G66: =IFERROR(_xludf.XLOOKUP($D66,NewFieldOptions!$A:$A,NewFieldOptions!$D:$D,""),"") | H66: =IFERROR(_xludf.XLOOKUP($D66,NewFieldOptions!$A:$A,NewFieldOptions!$B:$B,""),"")
A67: CPV_DETAIL.json | B67: LAST_EDIT_ON_TIME | G67: =IFERROR(_xludf.XLOOKUP($D67,NewFieldOptions!$A:$A,NewFieldOptions!$D:$D,""),"") | H67: =IFERROR(_xludf.XLOOKUP($D67,NewFieldOptions!$A:$A,NewFieldOptions!$B:$B,""),"")
A68: CPV_DETAIL.json | B68: LOAN_EXPECTED | C68: 525000 | G68: =IFERROR(_xludf.XLOOKUP($D68,NewFieldOptions!$A:$A,NewFieldOptions!$D:$D,""),"") | H68: =IFERROR(_xludf.XLOOKUP($D68,NewFieldOptions!$A:$A,NewFieldOptions!$B:$B,""),"")
A69: CPV_DETAIL.json | B69: LOAN_TYPE | C69: Auto Loan | G69: =IFERROR(_xludf.XLOOKUP($D69,NewFieldOptions!$A:$A,NewFieldOptions!$D:$D,""),"") | H69: =IFERROR(_xludf.XLOOKUP($D69,NewFieldOptions!$A:$A,NewFieldOptions!$B:$B,""),"")
A70: CPV_DETAIL.json | B70: MARITAL_STATUS | G70: =IFERROR(_xludf.XLOOKUP($D70,NewFieldOptions!$A:$A,NewFieldOptions!$D:$D,""),"") | H70: =IFERROR(_xludf.XLOOKUP($D70,NewFieldOptions!$A:$A,NewFieldOptions!$B:$B,""),"")
A71: CPV_DETAIL.json | B71: MARKETING_BY | C71: 2021 | G71: =IFERROR(_xludf.XLOOKUP($D71,NewFieldOptions!$A:$A,NewFieldOptions!$D:$D,""),"") | H71: =IFERROR(_xludf.XLOOKUP($D71,NewFieldOptions!$A:$A,NewFieldOptions!$B:$B,""),"")
A72: CPV_DETAIL.json | B72: MOBILE | G72: =IFERROR(_xludf.XLOOKUP($D72,NewFieldOptions!$A:$A,NewFieldOptions!$D:$D,""),"") | H72: =IFERROR(_xludf.XLOOKUP($D72,NewFieldOptions!$A:$A,NewFieldOptions!$B:$B,""),"")
A73: CPV_DETAIL.json | B73: MOTHERS_MAIDEN_NAME | G73: =IFERROR(_xludf.XLOOKUP($D73,NewFieldOptions!$A:$A,NewFieldOptions!$D:$D,""),"") | H73: =IFERROR(_xludf.XLOOKUP($D73,NewFieldOptions!$A:$A,NewFieldOptions!$B:$B,""),"")
A74: CPV_DETAIL.json | B74: NCCB | G74: =IFERROR(_xludf.XLOOKUP($D74,NewFieldOptions!$A:$A,NewFieldOptions!$D:$D,""),"") | H74: =IFERROR(_xludf.XLOOKUP($D74,NewFieldOptions!$A:$A,NewFieldOptions!$B:$B,""),"")
A75: CPV_DETAIL.json | B75: NO_OF_DEPENDANTS | C75: 0 | G75: =IFERROR(_xludf.XLOOKUP($D75,NewFieldOptions!$A:$A,NewFieldOptions!$D:$D,""),"") | H75: =IFERROR(_xludf.XLOOKUP($D75,NewFieldOptions!$A:$A,NewFieldOptions!$B:$B,""),"")
A76: CPV_DETAIL.json | B76: OFF_ADD1 | C76: PLOT NO-11/1,2 & 12/1 SITE-IV SAHIBABAD | G76: =IFERROR(_xludf.XLOOKUP($D76,NewFieldOptions!$A:$A,NewFieldOptions!$D:$D,""),"") | H76: =IFERROR(_xludf.XLOOKUP($D76,NewFieldOptions!$A:$A,NewFieldOptions!$B:$B,""),"")
A77: CPV_DETAIL.json | B77: OFF_ADD2 | C77: INDUSTRIAL AREA | G77: =IFERROR(_xludf.XLOOKUP($D77,NewFieldOptions!$A:$A,NewFieldOptions!$D:$D,""),"") | H77: =IFERROR(_xludf.XLOOKUP($D77,NewFieldOptions!$A:$A,NewFieldOptions!$B:$B,""),"")
A78: CPV_DETAIL.json | B78: OFF_CITY | C78: GHAZIABAD | G78: =IFERROR(_xludf.XLOOKUP($D78,NewFieldOptions!$A:$A,NewFieldOptions!$D:$D,""),"") | H78: =IFERROR(_xludf.XLOOKUP($D78,NewFieldOptions!$A:$A,NewFieldOptions!$B:$B,""),"")
A79: CPV_DETAIL.json | B79: OFF_FAX | G79: =IFERROR(_xludf.XLOOKUP($D79,NewFieldOptions!$A:$A,NewFieldOptions!$D:$D,""),"") | H79: =IFERROR(_xludf.XLOOKUP($D79,NewFieldOptions!$A:$A,NewFieldOptions!$B:$B,""),"")
A80: CPV_DETAIL.json | B80: OFF_NAME | C80: GOURAV LUMINARIES PVT LTD | G80: =IFERROR(_xludf.XLOOKUP($D80,NewFieldOptions!$A:$A,NewFieldOptions!$D:$D,""),"") | H80: =IFERROR(_xludf.XLOOKUP($D80,NewFieldOptions!$A:$A,NewFieldOptions!$B:$B,""),"")
A81: CPV_DETAIL.json | B81: OFF_PHONE1 | C81: 9811542232 | G81: =IFERROR(_xludf.XLOOKUP($D81,NewFieldOptions!$A:$A,NewFieldOptions!$D:$D,""),"") | H81: =IFERROR(_xludf.XLOOKUP($D81,NewFieldOptions!$A:$A,NewFieldOptions!$B:$B,""),"")
A82: CPV_DETAIL.json | B82: OFF_PHONE2 | G82: =IFERROR(_xludf.XLOOKUP($D82,NewFieldOptions!$A:$A,NewFieldOptions!$D:$D,""),"") | H82: =IFERROR(_xludf.XLOOKUP($D82,NewFieldOptions!$A:$A,NewFieldOptions!$B:$B,""),"")
A83: CPV_DETAIL.json | B83: OFF_PHONE3 | G83: =IFERROR(_xludf.XLOOKUP($D83,NewFieldOptions!$A:$A,NewFieldOptions!$D:$D,""),"") | H83: =IFERROR(_xludf.XLOOKUP($D83,NewFieldOptions!$A:$A,NewFieldOptions!$B:$B,""),"")
A84: CPV_DETAIL.json | B84: OFF_PIN | C84: 201010 | G84: =IFERROR(_xludf.XLOOKUP($D84,NewFieldOptions!$A:$A,NewFieldOptions!$D:$D,""),"") | H84: =IFERROR(_xludf.XLOOKUP($D84,NewFieldOptions!$A:$A,NewFieldOptions!$B:$B,""),"")
A85: CPV_DETAIL.json | B85: ORGANISATION_TYPE | C85: ELECTRONIC | G85: =IFERROR(_xludf.XLOOKUP($D85,NewFieldOptions!$A:$A,NewFieldOptions!$D:$D,""),"") | H85: =IFERROR(_xludf.XLOOKUP($D85,NewFieldOptions!$A:$A,NewFieldOptions!$B:$B,""),"")
A86: CPV_DETAIL.json | B86: ORIGINAL_HP_GROUP | G86: =IFERROR(_xludf.XLOOKUP($D86,NewFieldOptions!$A:$A,NewFieldOptions!$D:$D,""),"") | H86: =IFERROR(_xludf.XLOOKUP($D86,NewFieldOptions!$A:$A,NewFieldOptions!$B:$B,""),"")
A87: CPV_DETAIL.json | B87: PAGER | G87: =IFERROR(_xludf.XLOOKUP($D87,NewFieldOptions!$A:$A,NewFieldOptions!$D:$D,""),"") | H87: =IFERROR(_xludf.XLOOKUP($D87,NewFieldOptions!$A:$A,NewFieldOptions!$B:$B,""),"")
A88: CPV_DETAIL.json | B88: PAN_NUMBER | C88: AAACG3334L | G88: =IFERROR(_xludf.XLOOKUP($D88,NewFieldOptions!$A:$A,NewFieldOptions!$D:$D,""),"") | H88: =IFERROR(_xludf.XLOOKUP($D88,NewFieldOptions!$A:$A,NewFieldOptions!$B:$B,""),"")
A89: CPV_DETAIL.json | B89: PASSPORT_NUMBER | G89: =IFERROR(_xludf.XLOOKUP($D89,NewFieldOptions!$A:$A,NewFieldOptions!$D:$D,""),"") | H89: =IFERROR(_xludf.XLOOKUP($D89,NewFieldOptions!$A:$A,NewFieldOptions!$B:$B,""),"")
A90: CPV_DETAIL.json | B90: PERMANENT_ADDRESS | C90: C-5 1504 CLEO COUNTY NOIDA SECTOR-121 NOIDA 201309 | G90: =IFERROR(_xludf.XLOOKUP($D90,NewFieldOptions!$A:$A,NewFieldOptions!$D:$D,""),"") | H90: =IFERROR(_xludf.XLOOKUP($D90,NewFieldOptions!$A:$A,NewFieldOptions!$B:$B,""),"")
A91: CPV_DETAIL.json | B91: PREVIOUS_RELATION_WITH_US | C91: NO | G91: =IFERROR(_xludf.XLOOKUP($D91,NewFieldOptions!$A:$A,NewFieldOptions!$D:$D,""),"") | H91: =IFERROR(_xludf.XLOOKUP($D91,NewFieldOptions!$A:$A,NewFieldOptions!$B:$B,""),"")
A92: CPV_DETAIL.json | B92: PROFESSION_TYPE | C92: Self-Employed | G92: =IFERROR(_xludf.XLOOKUP($D92,NewFieldOptions!$A:$A,NewFieldOptions!$D:$D,""),"") | H92: =IFERROR(_xludf.XLOOKUP($D92,NewFieldOptions!$A:$A,NewFieldOptions!$B:$B,""),"")
A93: CPV_DETAIL.json | B93: PURPOSE_OF_LOAN | C93: Business | G93: =IFERROR(_xludf.XLOOKUP($D93,NewFieldOptions!$A:$A,NewFieldOptions!$D:$D,""),"") | H93: =IFERROR(_xludf.XLOOKUP($D93,NewFieldOptions!$A:$A,NewFieldOptions!$B:$B,""),"")
A94: CPV_DETAIL.json | B94: REF1_ADD | C94: 12-D BLOCK PREET VIHAR DELHI 110092 | G94: =IFERROR(_xludf.XLOOKUP($D94,NewFieldOptions!$A:$A,NewFieldOptions!$D:$D,""),"") | H94: =IFERROR(_xludf.XLOOKUP($D94,NewFieldOptions!$A:$A,NewFieldOptions!$B:$B,""),"")
A95: CPV_DETAIL.json | B95: REF1_NAME | C95: ANIL SETHI | G95: =IFERROR(_xludf.XLOOKUP($D95,NewFieldOptions!$A:$A,NewFieldOptions!$D:$D,""),"") | H95: =IFERROR(_xludf.XLOOKUP($D95,NewFieldOptions!$A:$A,NewFieldOptions!$B:$B,""),"")
A96: CPV_DETAIL.json | B96: REF1_PHONE | C96: 9811024536 | G96: =IFERROR(_xludf.XLOOKUP($D96,NewFieldOptions!$A:$A,NewFieldOptions!$D:$D,""),"") | H96: =IFERROR(_xludf.XLOOKUP($D96,NewFieldOptions!$A:$A,NewFieldOptions!$B:$B,""),"")
A97: CPV_DETAIL.json | B97: REF1_RELATION | C97: FRIEND | G97: =IFERROR(_xludf.XLOOKUP($D97,NewFieldOptions!$A:$A,NewFieldOptions!$D:$D,""),"") | H97: =IFERROR(_xludf.XLOOKUP($D97,NewFieldOptions!$A:$A,NewFieldOptions!$B:$B,""),"")
A98: CPV_DETAIL.json | B98: REF2_ADD | C98: B-209 S/F SURYA NAGAR GHAZIABAD 201010 | G98: =IFERROR(_xludf.XLOOKUP($D98,NewFieldOptions!$A:$A,NewFieldOptions!$D:$D,""),"") | H98: =IFERROR(_xludf.XLOOKUP($D98,NewFieldOptions!$A:$A,NewFieldOptions!$B:$B,""),"")
A99: CPV_DETAIL.json | B99: REF2_NAME | C99: SANJAY NAGPAL | G99: =IFERROR(_xludf.XLOOKUP($D99,NewFieldOptions!$A:$A,NewFieldOptions!$D:$D,""),"") | H99: =IFERROR(_xludf.XLOOKUP($D99,NewFieldOptions!$A:$A,NewFieldOptions!$B:$B,""),"")
A100: CPV_DETAIL.json | B100: REF2_PHONE | C100: 9811161499 | G100: =IFERROR(_xludf.XLOOKUP($D100,NewFieldOptions!$A:$A,NewFieldOptions!$D:$D,""),"") | H100: =IFERROR(_xludf.XLOOKUP($D100,NewFieldOptions!$A:$A,NewFieldOptions!$B:$B,""),"")
...

Sheet NewFieldOptions
A1: display | B1: new_field | C1: display_label | D1: dropdown_values | E1: new_type
A2: __deliveryInitialized (__deliveryInitialized) | B2: __deliveryInitialized | C2: __deliveryInitialized | E2: string
A3: __dispatchInitialized (__dispatchInitialized) | B3: __dispatchInitialized | C3: __dispatchInitialized | E3: string
A4: __postfileLocked (__postfileLocked) | B4: __postfileLocked | C4: __postfileLocked | E4: string
A5: aadhaarCardDocUrl (aadhaarCardDocUrl) | B5: aadhaarCardDocUrl | C5: aadhaarCardDocUrl | E5: string
A6: accessoriesAmount (Accessories Amount) | B6: accessoriesAmount | C6: Accessories Amount | E6: number
A7: accountNumber (Applicant Account Number) | B7: accountNumber | C7: Applicant Account Number | E7: number
A8: accountSinceYears (Account Since (Years)) | B8: accountSinceYears | C8: Account Since (Years) | E8: number
A9: accountType (Account Type) | B9: accountType | C9: Account Type | E9: string
A10: addressProofDocUrl (addressProofDocUrl) | B10: addressProofDocUrl | C10: addressProofDocUrl | E10: string
A11: addressProofNumber (Address Proof Number) | B11: addressProofNumber | C11: Address Proof Number | E11: boolean
A12: addressProofType (Address Proof (type)) | B12: addressProofType | C12: Address Proof (type) | E12: boolean
A13: addressType (Address Type) | B13: addressType | C13: Address Type | E13: number
... A107: delivery_rcFile (delivery_rcFile) | B107: delivery_rcFile | C107: delivery_rcFile | E107: string
A108: dependents (Dependents) | B108: dependents | C108: Dependents | D108: owned | rented | Undergraduate | Graduate | Postgraduate | Others | E108: number
A109: designation (Designation) | B109: designation | C109: Designation | E109: string
A110: disburseAmount (Disbursement Amount) | B110: disburseAmount | C110: Disbursement Amount | E110: number
A111: disbursedDate (Disbursement Date) | B111: disbursedDate | C111: Disbursement Date | E111: string
A112: disbursement_date (disbursement_date) | B112: disbursement_date | C112: disbursement_date | E112: string
A113: disbursement_status (disbursement_status) | B113: disbursement_status | C113: disbursement_status | E113: string
A114: disbursement_time (disbursement_time) | B114: disbursement_time | C114: disbursement_time | E114: string
A115: disbursementDate (disbursementDate) | B115: disbursementDate | C115: disbursementDate | E115: string
A116: disbursementStatus (disbursementStatus) | B116: disbursementStatus | C116: disbursementStatus | E116: string
A117: dispatch_date (dispatch_date) | B117: dispatch_date | C117: dispatch_date | E117: string
A118: dispatch_through (dispatch_through) | B118: dispatch_through | C118: dispatch_through | E118: string
A119: dispatch_time (dispatch_time) | B119: dispatch_time | C119: dispatch_time | E119: string
A120: dlDocUrl (dlDocUrl) | B120: dlDocUrl | C120: dlDocUrl | E120: string
A121: dob (isCompany ? "Date of Incorporation" : "Date of Birth" [Individual: Date of Birth | Company: Date of Incorporation]) | B121: dob | C121: isCompany ? "Date of Incorporation" : "Date of Birth" [Individual: Date of Birth | Company: Date of Incorporation] | D121: Male | Female | Married | E121: number
A122: docsPreparedBy (Docs Prepared By) | B122: docsPreparedBy | C122: Docs Prepared By | E122: string
A123: ecs_accountNumber (ecs_accountNumber) | B123: ecs_accountNumber | C123: ecs_accountNumber | E123: number
A124: ecs_amount (ecs_amount) | B124: ecs_amount | C124: ecs_amount | E124: number
A125: ecs_bankName (ecs_bankName) | B125: ecs_bankName | C125: ecs_bankName | E125: number
A126: ecs_date (ecs_date) | B126: ecs_date | C126: ecs_date | E126: number
A127: ecs_favouring (ecs_favouring) | B127: ecs_favouring | C127: ecs_favouring | E127: string
A128: ecs_image (ecs_image) | B128: ecs_image | C128: ecs_image | E128: string
A129: ecs_micrCode (ecs_micrCode) | B129: ecs_micrCode | C129: ecs_micrCode | E129: number
A130: ecs_signedBy (ecs_signedBy) | B130: ecs_signedBy | C130: ecs_signedBy | E130: string
A131: ecs_tag (ecs_tag) | B131: ecs_tag | C131: ecs_tag | E131: string
A132: education (Education) | B132: education | C132: Education | D132: Undergraduate | Graduate | Postgraduate | Others | E132: string
A133: email (Email) | B133: email | C133: Email | E133: boolean
A134: employmentAddress (Company Address) | B134: employmentAddress | C134: Company Address | E134: string
A135: employmentCity (City) | B135: employmentCity | C135: City | E135: string
A136: employmentPhone (Phone Number) | B136: employmentPhone | C136: Phone Number | E136: string
A137: employmentPincode (Pincode) | B137: employmentPincode | C137: Pincode | E137: string
A138: experienceCurrent (companyMode ? "Business Since / Current Vintage (Years)" : "Current Exp (Years)") | B138: experienceCurrent | C138: companyMode ? "Business Since / Current Vintage (Years)" : "Current Exp (Years)" | E138: string
A139: exShowroomPrice (Ex-Showroom Price) | B139: exShowroomPrice | C139: Ex-Showroom Price | E139: number
A140: financeExpectation (Expected Funding) | B140: financeExpectation | C140: Expected Funding | E140: number
A141: gender (Gender) | B141: gender | C141: Gender | D141: Male | Female | Married | Unmarried | Undergraduate | E141: number
A142: gstDocUrl (gstDocUrl) | B142: gstDocUrl | C142: gstDocUrl | E142: string
A143: gstNumber (GST Number) | B143: gstNumber | C143: GST Number | D143: Single | Married | Divorced | Widowed | E143: string
A144: gu_aadhaar (Aadhaar) | B144: gu_aadhaar | C144: Aadhaar | E144: string
A145: gu_aadhaarCardDocUrl (gu_aadhaarCardDocUrl) | B145: gu_aadhaarCardDocUrl | C145: gu_aadhaarCardDocUrl | E145: string
A146: gu_address (Address) | B146: gu_address | C146: Address | E146: string
A147: gu_addressProofDocUrl (gu_addressProofDocUrl) | B147: gu_addressProofDocUrl | C147: gu_addressProofDocUrl | E147: string
A148: gu_businessNature (Nature of Business) | B148: gu_businessNature | C148: Nature of Business | E148: string
A149: gu_city (City) | B149: gu_city | C149: City | E149: string
A150: gu_companyAddress (Company Address) | B150: gu_companyAddress | C150: Company Address | E150: string
A151: gu_companyCity (City) | B151: gu_companyCity | C151: City | E151: string
A152: gu_companyName (Company Name) | B152: gu_companyName | C152: Company Name | E152: string
A153: gu_companyPhone (Phone No) | B153: gu_companyPhone | C153: Phone No | E153: string
A154: gu_companyPincode (Pin Code) | B154: gu_companyPincode | C154: Pin Code | E154: string
A155: gu_companyType (Type of Company) | B155: gu_companyType | C155: Type of Company | E155: string
... A178: hasGuarantor (Is Guarantor Applicable) | B178: hasGuarantor | C178: Is Guarantor Applicable | E178: boolean
A179: houseType (House Type) | B179: houseType | C179: House Type | D179: owned | rented | E179: number
A180: hypothecation (Hypothecation) | B180: hypothecation | C180: Hypothecation | E180: string
A181: hypothecationBank (Hypothecation Bank) | B181: hypothecationBank | C181: Hypothecation Bank | E181: string
A182: hypothecationDocUrl (hypothecationDocUrl) | B182: hypothecationDocUrl | C182: hypothecationDocUrl | E182: string
A183: identityProofExpiry (Identity Proof Expiry) | B183: identityProofExpiry | C183: Identity Proof Expiry | E183: number
A184: identityProofNumber (Identity Proof Number) | B184: identityProofNumber | C184: Identity Proof Number | E184: number
A185: identityProofType (Identity Proof) | B185: identityProofType | C185: Identity Proof | E185: number
A186: ifsc (IFSC Code) | B186: ifsc | C186: IFSC Code | E186: string
A187: ifscCode (ifscCode) | B187: ifscCode | C187: ifscCode | E187: string
A188: instrumentType (instrumentType) | B188: instrumentType | C188: instrumentType | E188: string
A189: insurance_by (Insurance By) | B189: insurance_by | C189: Insurance By | E189: string
A190: insurance_company_name (Insurance Company Name) | B190: insurance_company_name | C190: Insurance Company Name | E190: string
A191: insurance_policy_duration_od (Policy Duration) | B191: insurance_policy_duration_od | C191: Policy Duration | E191: string
... A201: invoice_received_from (Received From) | B201: invoice_received_from | C201: Received From | E201: string
A202: isFinanced (isFinanced) | B202: isFinanced | C202: isFinanced | D202: Yes | No | E202: string
A203: isMSME (Is MSME Registered?) | B203: isMSME | C203: Is MSME Registered? | D203: Yes | No | E203: string
A204: isMultipleCars (isMultipleCars) | B204: isMultipleCars | C204: isMultipleCars | E204: string
A205: isSameVehicle (isSameVehicle) | B205: isSameVehicle | C205: isSameVehicle | E205: string
A206: leadDate (Lead Date) | B206: leadDate | C206: Lead Date | D206: Direct | Indirect | E206: string
A207: leadTime (Lead Time) | B207: leadTime | C207: Lead Time | D207: Direct | Indirect | E207: string
A208: loan_number (loan_number) | B208: loan_number | C208: loan_number | E208: string
A209: loan_payables (loan_payables) | B209: loan_payables | C209: loan_payables | E209: string
A210: loan_receivables (loan_receivables) | B210: loan_receivables | C210: loan_receivables | E210: string
A211: loanId (loanId) | B211: loanId | C211: loanId | E211: string
A212: loanTenureMonths (Requested Tenure (Months)) | B212: loanTenureMonths | C212: Requested Tenure (Months) | E212: number
A213: manufacturerDiscount (Manufacturer Discount) | B213: manufacturerDiscount | C213: Manufacturer Discount | E213: number
A214: marginMoney (Margin Money) | B214: marginMoney | C214: Margin Money | E214: number
A215: maritalStatus (Marital Status) | B215: maritalStatus | C215: Marital Status | D215: Single | Married | Divorced | Widowed | Unmarried | Undergraduate | Graduate | Postgraduate | Others | E215: number
A216: motherName (Mother's Name) | B216: motherName | C216: Mother's Name | E216: number
A217: nach_accountNumber (nach_accountNumber) | B217: nach_accountNumber | C217: nach_accountNumber | E217: string
A218: nach_image (nach_image) | B218: nach_image | C218: nach_image | E218: string
A219: nach_signedBy (nach_signedBy) | B219: nach_signedBy | C219: nach_signedBy | E219: string
A220: NEW (NEW) | B220: NEW | C220: NEW | E220: string
A221: numberOfCars (numberOfCars) | B221: numberOfCars | C221: numberOfCars | E221: number
A222: occupationType (Occupation) | B222: occupationType | C222: Occupation | E222: string
A223: officialEmail (Official Email ID) | B223: officialEmail | C223: Official Email ID | E223: string
A224: openedIn (Opened In) | B224: openedIn | C224: Opened In | E224: string
...

Sheet DropdownData
A1: new_field_display_options | C1: role_first | D1: role_next
A2: __deliveryInitialized (__deliveryInitialized) | C2: Mapping | D2: Fallback1
A3: __dispatchInitialized (__dispatchInitialized) | C3: Fallback1 | D3: Fallback2
A4: __postfileLocked (__postfileLocked) | C4: Fallback2 | D4: Fallback3
A5: aadhaarCardDocUrl (aadhaarCardDocUrl) | C5: Fallback3 | D5: Fallback4
A6: accessoriesAmount (Accessories Amount) | C6: Fallback4 | D6: Fallback5
A7: accountNumber (Applicant Account Number) | C7: Fallback5 | D7: Fallback6
A8: accountSinceYears (Account Since (Years)) | C8: Fallback6 | D8: Fallback7
A9: accountType (Account Type) | C9: Fallback7 | D9: Fallback8
A10: addressProofDocUrl (addressProofDocUrl) | C10: Fallback8 | D10: Fallback9
A11: addressProofNumber (Address Proof Number) | C11: Fallback9 | D11: Fallback10
A12: addressProofType (Address Proof (type)) | C12: Fallback10 | D12: Fallback11
... A21: approval_breakup_insuranceFinance (approval_breakup_insuranceFinance) | C21: Fallback19 | D21: Fallback20
A22: approval_breakup_netLoanApproved (approval_breakup_netLoanApproved) | C22: Fallback20
A23: approval_disbursedDate (approval_disbursedDate)
A24: approval_loanAmountApproved (approval_loanAmountApproved)
A25: approval_loanAmountDisbursed (approval_loanAmountDisbursed)
A26: approval_processingFees (approval_processingFees)
A27: approval_roi (approval_roi)
A28: approval_status (approval_status)
A29: approval_statusHistory (approval_statusHistory)
A30: approval_tenureMonths (approval_tenureMonths)
A31: bankName (Bank Name)
A32: billDate (billDate)
A33: billNumber (billNumber)
A34: boughtInYear (Bought In (Year))
... A327: yearsInCurrentHouse (Years in Current House)

Sheet UnmappedLegacyFields
A1: Unmapped legacy fields (new_field_select is blank)
A3: legacy_file | B3: legacy_field | C3: legacy_value | D3: new_field_select

Sheet UnmappedNewFields
A1: Unmapped new software fields
A3: new_field_display | B3: new_field_key | C3: dropdown_values

Sheet Instructions
A1: Reverse Mapping Instructions
A3: 1) Fill 'new_field_select' using dropdown in LegacyToNewMap.
A4: 2) Pick 'mapping_role' (Mapping/FallbackN).
A5: 3) Add comments and normalization notes in comments_normalization.
A6: 4) Use 'new_field_dropdown_values' to map legacy values to new dropdown values.
A7: 5) Same legacy field can map to multiple new fields (allowed).
A8: 6) First occurrence allows Mapping. Repeated occurrences allow only Fallback1..
A9: 7) Review UnmappedLegacyFields and UnmappedNewFields sheets after updates.
